Workbook

Sheet Master
B2: MASTER
B3: 46081
B5: Code Budget | C5: Code Report (New) | D5: Area | E5: Status | F5: Tình trạng (network) | G5: Tình trạng (PMO) | H5: Store | I5: Zone | J5: Brand | K5: BR | L5: Opening date | M5: Openning date (type) | N5: Openning date per budget | O5: Openning date per revised budget | P5: Closing date | Q5: Closing date (type) | R5: Shutdown/Convert | S5: Convert to | T5: Convert from | U5: Re-Opening Date | V5: Province | W5: Area - detail
B6: 10AS5700 | C6: 10AS5700 | D6: North | E6: CLOSED | H6: Ashima 1 - 21 - 22 - 23 Điện Biên Phủ | I6: HN | J6: AS | K6: Ashima | L6: 38933 | M6: Actual | P6: 44348 | Q6: Actual | V6: HN | W6: North - Hanoi
B7: 10AS5701 | C7: 10AS5701 | D7: North | E7: ACTIVE | H7: Ashima 2 - 182 Triệu Việt Vương | I7: HN | J7: AS | K7: Ashima | L7: 39022 | M7: Actual | U7: 43677 | V7: HN | W7: North - Hanoi
B8: 10AS5702 | C8: 10AS5702 | D8: North | E8: ACTIVE | H8: Ashima 6 - 60 Giang Văn Minh | I8: HN | J8: AS | K8: Ashima | L8: 39479 | M8: Actual | V8: HN | W8: North - Hanoi
B9: 10KK4400 | C9: 10KK4400 | D9: North | E9: ACTIVE | H9: Kichi Kichi Big C | I9: HN | J9: KK | K9: Kichi Kichi | L9: 39845 | M9: Actual | V9: HN | W9: North - Hanoi
B10: 10KK4401 | C10: 10KK4401 | D10: North | E10: CLOSED | H10: Kichi Kichi Tăng Bạt Hổ | I10: HN | J10: KK | K10: Kichi Kichi | L10: 39965 | M10: Actual | P10: 44651 | Q10: Actual | V10: HN | W10: North - Hanoi
B11: 10KK4402 | C11: 10KK4402 | D11: North | E11: CLOSED | H11: Kichi Kichi Phạm Ngọc Thạch | I11: HN | J11: KK | K11: Kichi Kichi | L11: 40087 | M11: Actual | P11: 45519 | Q11: Actual | R11: SHUTDOWN | V11: HN | W11: North - Hanoi
B12: 10KK4403 | C12: 10KK4403 | D12: North | E12: ACTIVE | H12: Kichi Kichi Vincom HN | I12: HN | J12: KK | K12: Kichi Kichi | L12: 40087 | M12: Actual | V12: HN | W12: North - Hanoi
B13: 10KK4404 | C13: 10KK4404 | D13: North | E13: CLOSED | H13: Kichi Kichi Nguyễn Phong Sắc | I13: HN | J13: KK | K13: Kichi Kichi | L13: 40148 | M13: Actual | V13: HN | W13: North - Hanoi
B14: 10KK4406 | C14: 10KK4406 | D14: North | E14: CLOSED | H14: Kichi Kichi Láng Hạ | I14: HN | J14: KK | K14: Kichi Kichi | L14: 40458 | M14: Actual | P14: 45432 | Q14: Actual | R14: CONVERT | S14: 10MG4734 | V14: HN | W14: North - Hanoi
B15: 10SM4901 | C15: 10SM4901 | D15: North | E15: ACTIVE | H15: Sumo BBQ Hoàng Quốc Việt | I15: HN | J15: SM | K15: Sumo BBQ | L15: 40555 | M15: Actual | V15: HN | W15: North - Hanoi
B16: 10SM4902 | C16: 10SM4902 | D16: North | E16: CLOSED | H16: Sumo BBQ Huỳnh Thúc Kháng | I16: HN | J16: SM | K16: Sumo BBQ | L16: 40673 | M16: Actual | P16: 44287 | Q16: Actual | V16: HN | W16: North - Hanoi
B17: 10SM4903 | C17: 10SM4903 | D17: North | E17: CLOSED | H17: Sumo BBQ Quán Sứ | I17: HN | J17: SM | K17: Sumo BBQ | L17: 40754 | M17: Actual | P17: 44081 | Q17: Actual | V17: HN | W17: North - Hanoi
B18: 10SM4904 | C18: 10SM4904 | D18: North | E18: CLOSED | H18: Sumo BBQ Savico - Nguyễn Văn Linh | I18: HN | J18: SM | K18: Sumo BBQ | L18: 40893 | M18: Actual | P18: 45551 | Q18: Actual | R18: SHUTDOWN | V18: HN | W18: North - Hanoi
B19: 10SS5900 | C19: 10SS5900 | D19: North | E19: ACTIVE | H19: I Sushi Nguyễn Chí Thanh | I19: HN | J19: SS | K19: Isushi | L19: 40990 | M19: Actual | U19: 43618 | V19: HN | W19: North - Hanoi
B20: 10ST6100 | C20: 10ST6100 | D20: North | E20: CLOSED | H20: 37 Street Indochina Xuân Thủy | I20: HN | J20: ST | K20: Phố 37 | L20: 41162 | M20: Actual | P20: 45513 | Q20: Actual | R20: CONVERT | S20: 10LC4845 | U20: 44720 | V20: HN | W20: North - Hanoi
B21: 10DR6200 | C21: 10DR6200 | D21: North | E21: CLOSED | H21: Daruma Giảng Võ | I21: HN | J21: DR | K21: Daruma | L21: 41275 | M21: Actual | P21: 43901 | Q21: Actual | V21: HN | W21: North - Hanoi
B22: 10KK4405 | C22: 10KK4405 | D22: North | E22: CLOSED | H22: Kichi Kichi Trung Hòa Nhân Chính | I22: HN | J22: KK | K22: Kichi Kichi | L22: 41379 | M22: Actual | P22: 45271 | Q22: Actual | V22: HN | W22: North - Hanoi
B23: 10GG4100 | C23: 10GG4100 | D23: North | E23: ACTIVE | H23: Gogi House Big C | I23: HN | J23: GG | K23: Gogi | L23: 41438 | M23: Actual | V23: HN | W23: North - Hanoi
B24: 10GG4102 | C24: 10GG4102 | D24: North | E24: ACTIVE | H24: Gogi House Trần Thái Tông | I24: HN | J24: GG | K24: Gogi | L24: 41544 | M24: Actual | V24: HN | W24: North - Hanoi
B25: 10KK4407 | C25: 10KK4407 | D25: North | E25: ACTIVE | H25: Kichi Kichi Royal City | I25: HN | J25: KK | K25: Kichi Kichi | L25: 41557 | M25: Actual | V25: HN | W25: North - Hanoi
B26: 10SM4905 | C26: 10SM4905 | D26: North | E26: CLOSED | H26: Sumo BBQ Royal City | I26: HN | J26: SM | K26: Sumo BBQ | L26: 41557 | M26: Actual | P26: 44091 | Q26: Actual | V26: HN | W26: North - Hanoi
B27: 10GG4101 | C27: 10GG4101 | D27: North | E27: ACTIVE | H27: Gogi House Royal City | I27: HN | J27: GG | K27: Gogi | L27: 41639 | M27: Actual | V27: HN | W27: North - Hanoi
B28: 10GF4001 | C28: 10GF4001 | D28: North | E28: CLOSED | H28: Icook | I28: IC+CT | J28: GF | K28: Icook | L28: 41640 | M28: Actual | P28: 46066 | Q28: Actual | V28: IC+CT | W28: North - Hanoi
B29: 10SM4906 | C29: 10SM4906 | D29: North | E29: CLOSED | H29: Sumo BBQ Tô Hiến Thành | I29: HN | J29: SM | K29: Sumo BBQ | L29: 41652 | M29: Actual | P29: 45418 | Q29: Actual | R29: SHUTDOWN | V29: HN | W29: North - Hanoi
B30: 10VV5300 | C30: 10VV5300 | D30: North | E30: ACTIVE | H30: Vuvuzela Trung Hòa Nhân Chính | I30: HN | J30: VV | K30: Vuvuzela | L30: 41679 | M30: Actual | V30: HN | W30: North - Hanoi
B31: 10GG4103 | C31: 10GG4103 | D31: North | E31: CLOSED | H31: Gogi House Mipec | I31: HN | J31: GG | K31: Gogi | L31: 41725 | M31: Actual | P31: 44362 | Q31: Actual | V31: HN | W31: North - Hanoi
B32: 10VV5310 | C32: 10VV5310 | D32: North | E32: CLOSED | H32: Vuvuzela Tràng Thi | I32: HN | J32: VV | K32: Vuvuzela | L32: 41751 | M32: Actual | P32: 45458 | Q32: Actual | R32: SHUTDOWN | V32: HN | W32: North - Hanoi
B33: 10GG4104 | C33: 10GG4104 | D33: North | E33: CLOSED | H33: Gogi House Phạm Ngọc Thạch | I33: HN | J33: GG | K33: Gogi | L33: 41806 | M33: Actual | P33: 44530 | Q33: Actual | V33: HN | W33: North - Hanoi
B34: 10SM4900 | C34: 10SM4900 | D34: North | E34: CLOSED | H34: Sumo BBQ Big C | I34: HN | J34: SM | K34: Sumo BBQ | L34: 41855 | M34: Actual | P34: 45593 | Q34: Actual | R34: SHUTDOWN | U34: 43733 | V34: HN | W34: North - Hanoi
B35: 10GG4128 | C35: 10GG4128 | D35: North | E35: ACTIVE | H35: Gogi House Hạ Long | I35: QN | J35: GG | K35: Gogi | L35: 41931 | M35: Actual | V35: QN | W35: North - Other Cities
B36: 10GG4105 | C36: 10GG4105 | D36: North | E36: ACTIVE | H36: Gogi House Bùi Thị Xuân | I36: HN | J36: GG | K36: Gogi | L36: 42000 | M36: Actual | V36: HN | W36: North - Hanoi
B37: 10MW5117 | C37: 10MW5117 | D37: North | E37: CLOSED | H37: MW Nguyễn Hoàng | I37: HN | J37: MW | K37: MANWAH | L37: 43709 | M37: Actual | P37: 45658 | Q37: Actual | R37: SHUTDOWN | V37: HN | W37: North - Hanoi
B38: 10VV5308 | C38: 10VV5308 | D38: North | E38: ACTIVE | H38: Vuvuzela Nguyễn Trãi | I38: HN | J38: VV | K38: Vuvuzela | L38: 42017 | M38: Actual | U38: 43976 | V38: HN | W38: North - Hanoi
B39: 10GG4106 | C39: 10GG4106 | D39: North | E39: ACTIVE | H39: Gogi House Trung Yên | I39: HN | J39: GG | K39: Gogi | L39: 42035 | M39: Actual | V39: HN | W39: North - Hanoi
B40: 10CB5400 | C40: 10CB5400 | D40: North | E40: CLOSED | H40: Cowboy jack's Trung Hòa Nhân chính | I40: HN | J40: CB | K40: Cowboy Jack | L40: 42092 | M40: Actual | P40: 44927 | Q40: Actual | V40: HN | W40: North - Hanoi
B41: 10HT4700 | C41: 10HT4700 | D41: North | E41: CLOSED | H41: Hutong Big C Thăng Long | I41: HN | J41: HT | K41: Hutong | L41: 42121 | M41: Actual | P41: 43900 | Q41: Actual | V41: HN | W41: North - Hanoi
B42: 10DR6202 | C42: 10DR6202 | D42: North | E42: CLOSED | H42: Daruma Trung Hòa Nhân Chính | I42: HN | J42: DR | K42: Daruma | L42: 42197 | M42: Actual | P42: 43811 | Q42: Actual | V42: HN | W42: North - Hanoi
B43: 10CB5410 | C43: 10CB5410 | D43: North | E43: CLOSED | H43: Cowboy Jack’s Số 8 Tràng Thi | I43: HN | J43: CB | K43: Cowboy Jack | L43: 42210 | M43: Actual | P43: 43983 | Q43: Actual | V43: HN | W43: North - Hanoi
B44: 10DR6203 | C44: 10DR6203 | D44: North | E44: CLOSED | H44: Daruma Mipec | I44: HN | J44: DR | K44: Daruma | L44: 42249 | M44: Actual | P44: 44266 | Q44: Actual | V44: HN | W44: North - Hanoi
B45: 10GG4107 | C45: 10GG4107 | D45: North | E45: CLOSED | H45: Gogi House Phó Đức Chính | I45: HN | J45: GG | K45: Gogi | L45: 42249 | M45: Actual | P45: 45137 | Q45: Actual | V45: HN | W45: North - Hanoi
B46: 10GG4109 | C46: 10GG4109 | D46: North | E46: CLOSED | H46: Gogi House Trần Phú- Hà Đông | I46: HN | J46: GG | K46: Gogi | L46: 42267 | M46: Actual | P46: 44322 | Q46: Actual | V46: HN | W46: North - Hanoi
B47: 10CB5402 | C47: 10CB5402 | D47: North | E47: CLOSED | H47: Cowboy Jack’s Trần Thái Tông | I47: HN | J47: CB | K47: Cowboy Jack | L47: 42270 | M47: Actual | P47: 44748 | Q47: Actual | U47: 43709 | V47: HN | W47: North - Hanoi
B48: 10KP5603 | C48: 10KP5603 | D48: North | E48: CLOSED | H48: K-PUB Vincom Hải Phòng | I48: HP | J48: KP | K48: K-PUB | L48: 42275 | M48: Actual | P48: 44543 | Q48: Actual | V48: HP | W48: North - Other Cities
B49: 10CB5405 | C49: 10CB5405 | D49: North | E49: CLOSED | H49: Cowboy Jack's Vincom Hải Phòng | I49: HP | J49: CB | K49: Cowboy Jack | L49: 42277 | M49: Actual | P49: 44104 | Q49: Actual | V49: HP | W49: North - Other Cities
B50: 10HT4708 | C50: 10HT4708 | D50: North | E50: CLOSED | H50: Hutong Vincom Hải Phòng | I50: HP | J50: HT | K50: Hutong | L50: 42277 | M50: Actual | P50: 44544 | Q50: Actual | V50: HP | W50: North - Other Cities
B51: 10CB5403 | C51: 10CB5403 | D51: North | E51: CLOSED | H51: Cowboy Jack's AEON- Long Biên | I51: HN | J51: CB | K51: Cowboy Jack | L51: 42305 | M51: Actual | P51: 44958 | Q51: Actual | V51: HN | W51: North - Hanoi
B52: 10KK4408 | C52: 10KK4408 | D52: North | E52: ACTIVE | H52: Kichi Kichi AEON Long Biên | I52: HN | J52: KK | K52: Kichi Kichi | L52: 42305 | M52: Actual | V52: HN | W52: North - Hanoi
B53: 10GG4108 | C53: 10GG4108 | D53: North | E53: ACTIVE | H53: Gogi House Lạc Long Quân | I53: HN | J53: GG | K53: Gogi | L53: 42306 | M53: Actual | V53: HN | W53: North - Hanoi
B54: 10GG4110 | C54: 10GG4110 | D54: North | E54: ACTIVE | H54: Gogi House Giang Văn Minh | I54: HN | J54: GG | K54: Gogi | L54: 42318 | M54: Actual | V54: HN | W54: North - Hanoi
B55: 10DR6204 | C55: 10DR6204 | D55: North | E55: CLOSED | H55: Daruma Vincom Nguyễn Chí Thanh | I55: HN | J55: DR | K55: Daruma | L55: 42328 | M55: Actual | P55: 45249 | Q55: Actual | R55: SHUTDOWN | V55: HN | W55: North - Hanoi
B56: 10CB5404 | C56: 10CB5404 | D56: North | E56: CLOSED | H56: Cowboy Jack's Vincom Nguyễn Chí Thanh | I56: HN | J56: CB | K56: Cowboy Jack | L56: 42328 | M56: Actual | P56: 45227 | Q56: Actual | V56: HN | W56: North - Hanoi
B57: 10GG4203 | C57: 10GG4203 | D57: North | E57: CLOSED | H57: Gogi House Trần Nguyên Hãn HP | I57: HP | J57: GG | K57: GOGI | L57: 43914 | M57: Actual | P57: 45658 | Q57: Actual | R57: SHUTDOWN | V57: HP | W57: North - Other Cities
B58: 10MW5103 | C58: 10MW5103 | D58: North | E58: CLOSED | H58: Manwah Trần Nguyên Hãn HP | I58: HP | J58: MW | K58: MANWAH | L58: 43914 | M58: Actual | P58: 45658 | Q58: Actual | R58: SHUTDOWN | V58: HP | W58: North - Other Cities
B59: 10KK4410 | C59: 10KK4410 | D59: North | E59: ACTIVE | H59: Kichi Kichi Times City | I59: HN | J59: KK | K59: Kichi Kichi | L59: 42353 | M59: Actual | U59: 44488 | V59: HN | W59: North - Hanoi
B60: 10KP5600 | C60: 10KP5600 | D60: North | E60: CLOSED | H60: K-PUB Times City | I60: HN | J60: KP | K60: K-PUB | L60: 42353 | M60: Actual | P60: 44362 | Q60: Actual | V60: HN | W60: North - Hanoi
B61: 10SS5901 | C61: 10SS5901 | D61: North | E61: ACTIVE | H61: I Sushi Triệu Việt Vương | I61: HN | J61: SS | K61: Isushi | L61: 42490 | M61: Actual | V61: HN | W61: North - Hanoi
B62: 10GG4112 | C62: 10GG4112 | D62: North | E62: CLOSED | H62: Gogi House Huỳnh Thúc Kháng | I62: HN | J62: GG | K62: Gogi | L62: 42521 | M62: Actual | P62: 44308 | Q62: Actual | V62: HN | W62: North - Hanoi
B63: 10HT4701 | C63: 10HT4701 | D63: North | E63: CLOSED | H63: Hutong Phó Đức Chính | I63: HN | J63: HT | K63: Hutong | L63: 42521 | M63: Actual | P63: 44260 | Q63: Actual | V63: HN | W63: North - Hanoi
B64: 10GG4129 | C64: 10GG4129 | D64: North | E64: ACTIVE | H64: Gogi House Vincom Thái Bình | I64: TB | J64: GG | K64: Gogi | L64: 42539 | M64: Actual | V64: TB | W64: North - Other Cities
B65: 10GG4113 | C65: 10GG4113 | D65: North | E65: CLOSED | H65: Gogi House Mipec Long Biên | I65: HN | J65: GG | K65: Gogi | L65: 42581 | M65: Actual | P65: 45627 | Q65: Actual | R65: SHUTDOWN | V65: HN | W65: North - Hanoi
B66: 10KK4411 | C66: 10KK4411 | D66: North | E66: CLOSED | H66: Kichi Kichi Mipec Long Biên | I66: HN | J66: KK | K66: Kichi Kichi | L66: 42581 | M66: Actual | P66: 44266 | Q66: Actual | V66: HN | W66: North - Hanoi
B67: 10SG6300 | C67: 10SG6300 | D67: North | E67: CLOSED | H67: Shogun Dịch Vọng | I67: HN | J67: SG | K67: Shogun | L67: 42607 | M67: Actual | P67: 43829 | Q67: Actual | V67: HN | W67: North - Hanoi
B68: 10GG4124 | C68: 10GG4124 | D68: North | E68: CLOSED | H68: Gogi House Nguyễn Đăng Đạo Bắc Ninh | I68: BN | J68: GG | K68: Gogi | L68: 42644 | M68: Actual | P68: 45091 | Q68: Actual | V68: BN | W68: North - Other Cities
B69: 10HT4702 | C69: 10HT4702 | D69: North | E69: CLOSED | H69: Hutong Phạm Ngọc Thạch | I69: HN | J69: HT | K69: Hutong | L69: 42679 | M69: Actual | P69: 44544 | Q69: Actual | V69: HN | W69: North - Hanoi
B70: 10SG6301 | C70: 10SG6301 | D70: North | E70: ACTIVE | H70: Shogun Phạm Ngọc Thạch | I70: HN | J70: SG | K70: Shogun | L70: 42679 | M70: Actual | V70: HN | W70: North - Hanoi
B71: 10SG6302 | C71: 10SG6302 | D71: North | E71: ACTIVE | H71: Shogun Royal | I71: HN | J71: SG | K71: Shogun | L71: 44122 | M71: Actual | V71: HN | W71: North - Hanoi
B72: 10GG4127 | C72: 10GG4127 | D72: North | E72: ACTIVE | H72: Gogi House Nam Định | I72: NĐ | J72: GG | K72: Gogi | L72: 42682 | M72: Actual | V72: NĐ | W72: North - Other Cities
B73: 10GG4114 | C73: 10GG4114 | D73: North | E73: CLOSED | H73: Gogi House Tân Mai | I73: HN | J73: GG | K73: Gogi | L73: 42744 | M73: Actual | P73: 44929 | Q73: Actual | V73: HN | W73: North - Hanoi
B74: 10KK4413 | C74: 10KK4413 | D74: North | E74: ACTIVE | H74: Kichi Kichi Lạc Long Quân | I74: HN | J74: KK | K74: Kichi Kichi | L74: 42770 | M74: Actual | V74: HN | W74: North - Hanoi
B75: 10GG4117 | C75: 10GG4117 | D75: North | E75: ACTIVE | H75: Gogi House Linh Đàm | I75: HN | J75: GG | K75: Gogi | L75: 42790 | M75: Actual | V75: HN | W75: North - Hanoi
B76: 10HT4704 | C76: 10HT4704 | D76: North | E76: CLOSED | H76: Hutong Royal | I76: HN | J76: HT | K76: Hutong | L76: 42791 | M76: Actual | P76: 44742 | Q76: Actual | V76: HN | W76: North - Hanoi
B77: 10GG4116 | C77: 10GG4116 | D77: North | E77: ACTIVE | H77: Gogi House Ngụy Như Kon Tum | I77: HN | J77: GG | K77: Gogi | L77: 42825 | M77: Actual | V77: HN | W77: North - Hanoi
B78: 10KK4414 | C78: 10KK4414 | D78: North | E78: ACTIVE | H78: Kichi Kichi Linh Đàm | I78: HN | J78: KK | K78: Kichi Kichi | L78: 42839 | M78: Actual | V78: HN | W78: North - Hanoi
B79: 10HT4703 | C79: 10HT4703 | D79: North | E79: CLOSED | H79: Hutong Nguyễn Khang | I79: HN | J79: HT | K79: Hutong | L79: 42841 | M79: Actual | P79: 44696 | Q79: Actual | V79: HN | W79: North - Hanoi
B80: 10GG4134 | C80: 10GG4134 | D80: North | E80: ACTIVE | H80: Gogi House Thái Nguyên | I80: TN | J80: GG | K80: Gogi | L80: 42849 | M80: Actual | V80: TN | W80: North - Other Cities
B81: 10GG4115 | C81: 10GG4115 | D81: North | E81: CLOSED | H81: Gogi House ARTERMIS | I81: HN | J81: GG | K81: Gogi | L81: 42869 | M81: Actual | P81: 44280 | Q81: Actual | V81: HN | W81: North - Hanoi
B82: 10KK4412 | C82: 10KK4412 | D82: North | E82: CLOSED | H82: Kichi Kichi ARTERMIS | I82: HN | J82: KK | K82: Kichi Kichi | L82: 42869 | M82: Actual | P82: 44280 | Q82: Actual | V82: HN | W82: North - Hanoi
B83: 10GG4125 | C83: 10GG4125 | D83: North | E83: ACTIVE | H83: Gogi House Từ Sơn Bắc Ninh | I83: BN | J83: GG | K83: Gogi | L83: 42875 | M83: Actual | V83: BN | W83: North - Other Cities
B84: 10HT4705 | C84: 10HT4705 | D84: North | E84: CLOSED | H84: Hutong Time | I84: HN | J84: HT | K84: Hutong | L84: 42903 | M84: Actual | P84: 44362 | Q84: Actual | V84: HN | W84: North - Hanoi
B85: 10GG4118 | C85: 10GG4118 | D85: North | E85: CLOSED | H85: Gogi House Nguyễn Hoàng | I85: HN | J85: GG | K85: Gogi | L85: 42926 | M85: Actual | P85: 45390 | Q85: Actual | R85: SHUTDOWN | V85: HN | W85: North - Hanoi
B86: 10HT4712 | C86: 10HT4712 | D86: North | E86: CLOSED | H86: Hutong Lý Bôn Thái Bình | I86: TB | J86: HT | K86: Hutong | L86: 42927 | M86: Actual | P86: 44821 | Q86: Actual | V86: TB | W86: North - Other Cities
B87: 10YT5512 | C87: 10YT5512 | D87: North | E87: CLOSED | H87: Yutang Chùa Láng | I87: HN | J87: YT | K87: Yutang | L87: 42957 | M87: Actual | P87: 45576 | Q87: Actual | R87: SHUTDOWN | V87: HN | W87: North - Hanoi
B88: 10GG4119 | C88: 10GG4119 | D88: North | E88: CLOSED | H88: Gogi House Trần Văn Lai | I88: HN | J88: GG | K88: Gogi | L88: 42962 | M88: Actual | P88: 45494 | Q88: Actual | R88: SHUTDOWN | V88: HN | W88: North - Hanoi
B89: 10HT4711 | C89: 10HT4711 | D89: North | E89: CLOSED | H89: Hutong Lê Thánh Tông Quảng Ninh | I89: QN | J89: HT | K89: Hutong | L89: 42968 | M89: Actual | P89: 44963 | Q89: Actual | V89: QN | W89: North - Other Cities
B90: 10KK4415 | C90: 10KK4415 | D90: North | E90: CLOSED | H90: Kichi Kichi Nguyễn Hoàng DOLPHIN | I90: HN | J90: KK | K90: Kichi Kichi | L90: 43018 | M90: Actual | P90: 44561 | Q90: Actual | V90: HN | W90: North - Hanoi
B91: 10KK4416 | C91: 10KK4416 | D91: North | E91: CLOSED | H91: Kichi Kichi Eco Tô Hữu | I91: HN | J91: KK | K91: Kichi Kichi | L91: 43039 | M91: Actual | P91: 44362 | Q91: Actual | V91: HN | W91: North - Hanoi
B92: 10MW5100 | C92: 10MW5100 | D92: North | E92: ACTIVE | H92: Manwah Center Point | I92: HN | J92: MW | K92: MANWAH | L92: 43062 | M92: Actual | V92: HN | W92: North - Hanoi
B93: 10HT4710 | C93: 10HT4710 | D93: North | E93: CLOSED | H93: Hutong Nam Định | I93: NĐ | J93: HT | K93: Hutong | L93: 43080 | M93: Actual | P93: 44963 | Q93: Actual | V93: NĐ | W93: North - Other Cities
B94: 10HT4706 | C94: 10HT4706 | D94: North | E94: CLOSED | H94: Hutong Triệu Việt Vương | I94: HN | J94: HT | K94: Hutong | L94: 43090 | M94: Actual | P94: 44717 | Q94: Actual | V94: HN | W94: North - Hanoi
B95: 10GG4126 | C95: 10GG4126 | D95: North | E95: CLOSED | H95: Gogi Lê Hồng Phong Hải Phòng | I95: HP | J95: GG | K95: Gogi | L95: 43105 | M95: Actual | P95: 45572 | Q95: Actual | R95: SHUTDOWN | V95: HP | W95: North - Other Cities
B96: 10HT4709 | C96: 10HT4709 | D96: North | E96: CLOSED | H96: Hutong Lê Hồng Phong Hải Phòng | I96: HP | J96: HT | K96: Hutong | L96: 43105 | M96: Actual | P96: 44963 | Q96: Actual | V96: HP | W96: North - Other Cities
B97: 10AS5703 | C97: 10AS5703 | D97: North | E97: ACTIVE | H97: Ashima Hoàng Đạo Thúy | I97: HN | J97: AS | K97: Ashima | L97: 43233 | M97: Actual | V97: HN | W97: North - Hanoi
B98: 10SS5902 | C98: 10SS5902 | D98: North | E98: CLOSED | H98: I Sushi Hoàng Đạo Thúy | I98: HN | J98: SS | K98: Isushi | L98: 43244 | M98: Actual | P98: 45444 | Q98: Actual | R98: CONVERT | S98: 10SB4801 | V98: HN | W98: North - Hanoi
B99: 10KK4417 | C99: 10KK4417 | D99: North | E99: ACTIVE | H99: Kichi Kichi Savico | I99: HN | J99: KK | K99: Kichi Kichi | L99: 43271 | M99: Actual | P99: 44884 | Q99: Actual | U99: 45077 | V99: HN | W99: North - Hanoi
B100: 10GG4120 | C100: 10GG4120 | D100: North | E100: ACTIVE | H100: Gogi House Vạn Phúc Hà Đông | I100: HN | J100: GG | K100: Gogi | L100: 43273 | M100: Actual | V100: HN | W100: North - Hanoi
B101: 10HT4707 | C101: 10HT4707 | D101: North | E101: CLOSED | H101: Hutong Giảng Võ | I101: HN | J101: HT | K101: Hutong | L101: 43274 | M101: Actual | P101: 44738 | Q101: Actual | V101: HN | W101: North - Hanoi
B102: 10YT5513 | C102: 10YT5513 | D102: North | E102: CLOSED | H102: Yutang Thái Phiên | I102: HN | J102: YT | K102: Yutang | L102: 43276 | M102: Actual | P102: 45653 | Q102: Actual | R102: SHUTDOWN | V102: HN | W102: North - Hanoi
...

Sheet Master MoM
F1: 46053 | G1: 46081 | H1: 46112 | I1: 46142 | J1: 46173 | K1: 46203 | L1: 46234 | M1: 46265 | N1: 46295 | O1: 46326 | P1: 46356 | Q1: 46387
C2: PC | D2: Openning date | E2: Closing date | F2: Jan | G2: Feb | H2: March | I2: April | J2: May | K2: June | L2: July | M2: August | N2: Sept | O2: Oct | P2: Nov | Q2: Dec
B3: {=_xlfn._xlws.FILTER( Master!B:B, ( (Master!M:M="Actual")*(Master!E:E="Active")*ISNUMBER(Master!L:L)*(Master!L:L>0) + (Master!M:M="Forecast")*ISNUMBER(Master!L:L)*(Master!L:L>0) ) )} -> 10AS5701 | C3: =VLOOKUP(B3,Master!B:C,2,0) -> 10AS5701 | D3: =VLOOKUP(B3,Master!B:L,11,0) -> 39022 | E3: =VLOOKUP(B3,Master!B:P,15,0) -> 0 | F3: =IF($E3>0,"CLOSED",IF($D3<F$1,"ACTIVE","WAITING FOR OPEN")) -> ACTIVE | G3: =IF($E3>0,"CLOSED",IF($D3<G$1,"ACTIVE","WAITING FOR OPEN")) -> ACTIVE | H3: =IF($E3>0,"CLOSED",IF($D3<H$1,"ACTIVE","WAITING FOR OPEN")) -> ACTIVE | I3: =IF($E3>0,"CLOSED",IF($D3<I$1,"ACTIVE","WAITING FOR OPEN")) -> ACTIVE | J3: =IF($E3>0,"CLOSED",IF($D3<J$1,"ACTIVE","WAITING FOR OPEN")) -> ACTIVE | K3: =IF($E3>0,"CLOSED",IF($D3<K$1,"ACTIVE","WAITING FOR OPEN")) -> ACTIVE | L3: =IF($E3>0,"CLOSED",IF($D3<L$1,"ACTIVE","WAITING FOR OPEN")) -> ACTIVE | M3: =IF($E3>0,"CLOSED",IF($D3<M$1,"ACTIVE","WAITING FOR OPEN")) -> ACTIVE | ... Q3: =IF($E3>0,"CLOSED",IF($D3<Q$1,"ACTIVE","WAITING FOR OPEN")) -> ACTIVE
B4: 10AS5702 | C4: =VLOOKUP(B4,Master!B:C,2,0) -> 10AS5702 | D4: =VLOOKUP(B4,Master!B:L,11,0) -> 39479 | E4: =VLOOKUP(B4,Master!B:P,15,0) -> 0 | F4: =IF($E4>0,"CLOSED",IF($D4<F$1,"ACTIVE","WAITING FOR OPEN")) -> ACTIVE | G4: =IF($E4>0,"CLOSED",IF($D4<G$1,"ACTIVE","WAITING FOR OPEN")) -> ACTIVE | H4: =IF($E4>0,"CLOSED",IF($D4<H$1,"ACTIVE","WAITING FOR OPEN")) -> ACTIVE | I4: =IF($E4>0,"CLOSED",IF($D4<I$1,"ACTIVE","WAITING FOR OPEN")) -> ACTIVE | J4: =IF($E4>0,"CLOSED",IF($D4<J$1,"ACTIVE","WAITING FOR OPEN")) -> ACTIVE | K4: =IF($E4>0,"CLOSED",IF($D4<K$1,"ACTIVE","WAITING FOR OPEN")) -> ACTIVE | L4: =IF($E4>0,"CLOSED",IF($D4<L$1,"ACTIVE","WAITING FOR OPEN")) -> ACTIVE | M4: =IF($E4>0,"CLOSED",IF($D4<M$1,"ACTIVE","WAITING FOR OPEN")) -> ACTIVE | ... Q4: =IF($E4>0,"CLOSED",IF($D4<Q$1,"ACTIVE","WAITING FOR OPEN")) -> ACTIVE
B5: 10KK4400 | C5: =VLOOKUP(B5,Master!B:C,2,0) -> 10KK4400 | D5: =VLOOKUP(B5,Master!B:L,11,0) -> 39845 | E5: =VLOOKUP(B5,Master!B:P,15,0) -> 0 | F5: =IF($E5>0,"CLOSED",IF($D5<F$1,"ACTIVE","WAITING FOR OPEN")) -> ACTIVE | G5: =IF($E5>0,"CLOSED",IF($D5<G$1,"ACTIVE","WAITING FOR OPEN")) -> ACTIVE | H5: =IF($E5>0,"CLOSED",IF($D5<H$1,"ACTIVE","WAITING FOR OPEN")) -> ACTIVE | I5: =IF($E5>0,"CLOSED",IF($D5<I$1,"ACTIVE","WAITING FOR OPEN")) -> ACTIVE | J5: =IF($E5>0,"CLOSED",IF($D5<J$1,"ACTIVE","WAITING FOR OPEN")) -> ACTIVE | K5: =IF($E5>0,"CLOSED",IF($D5<K$1,"ACTIVE","WAITING FOR OPEN")) -> ACTIVE | L5: =IF($E5>0,"CLOSED",IF($D5<L$1,"ACTIVE","WAITING FOR OPEN")) -> ACTIVE | M5: =IF($E5>0,"CLOSED",IF($D5<M$1,"ACTIVE","WAITING FOR OPEN")) -> ACTIVE | ... Q5: =IF($E5>0,"CLOSED",IF($D5<Q$1,"ACTIVE","WAITING FOR OPEN")) -> ACTIVE
B6: 10KK4403 | C6: =VLOOKUP(B6,Master!B:C,2,0) -> 10KK4403 | D6: =VLOOKUP(B6,Master!B:L,11,0) -> 40087 | E6: =VLOOKUP(B6,Master!B:P,15,0) -> 0 | F6: =IF($E6>0,"CLOSED",IF($D6<F$1,"ACTIVE","WAITING FOR OPEN")) -> ACTIVE | G6: =IF($E6>0,"CLOSED",IF($D6<G$1,"ACTIVE","WAITING FOR OPEN")) -> ACTIVE | H6: =IF($E6>0,"CLOSED",IF($D6<H$1,"ACTIVE","WAITING FOR OPEN")) -> ACTIVE | I6: =IF($E6>0,"CLOSED",IF($D6<I$1,"ACTIVE","WAITING FOR OPEN")) -> ACTIVE | J6: =IF($E6>0,"CLOSED",IF($D6<J$1,"ACTIVE","WAITING FOR OPEN")) -> ACTIVE | K6: =IF($E6>0,"CLOSED",IF($D6<K$1,"ACTIVE","WAITING FOR OPEN")) -> ACTIVE | L6: =IF($E6>0,"CLOSED",IF($D6<L$1,"ACTIVE","WAITING FOR OPEN")) -> ACTIVE | M6: =IF($E6>0,"CLOSED",IF($D6<M$1,"ACTIVE","WAITING FOR OPEN")) -> ACTIVE | ... Q6: =IF($E6>0,"CLOSED",IF($D6<Q$1,"ACTIVE","WAITING FOR OPEN")) -> ACTIVE
B7: 10SM4901 | C7: =VLOOKUP(B7,Master!B:C,2,0) -> 10SM4901 | D7: =VLOOKUP(B7,Master!B:L,11,0) -> 40555 | E7: =VLOOKUP(B7,Master!B:P,15,0) -> 0 | F7: =IF($E7>0,"CLOSED",IF($D7<F$1,"ACTIVE","WAITING FOR OPEN")) -> ACTIVE | G7: =IF($E7>0,"CLOSED",IF($D7<G$1,"ACTIVE","WAITING FOR OPEN")) -> ACTIVE | H7: =IF($E7>0,"CLOSED",IF($D7<H$1,"ACTIVE","WAITING FOR OPEN")) -> ACTIVE | I7: =IF($E7>0,"CLOSED",IF($D7<I$1,"ACTIVE","WAITING FOR OPEN")) -> ACTIVE | J7: =IF($E7>0,"CLOSED",IF($D7<J$1,"ACTIVE","WAITING FOR OPEN")) -> ACTIVE | K7: =IF($E7>0,"CLOSED",IF($D7<K$1,"ACTIVE","WAITING FOR OPEN")) -> ACTIVE | L7: =IF($E7>0,"CLOSED",IF($D7<L$1,"ACTIVE","WAITING FOR OPEN")) -> ACTIVE | M7: =IF($E7>0,"CLOSED",IF($D7<M$1,"ACTIVE","WAITING FOR OPEN")) -> ACTIVE | ... Q7: =IF($E7>0,"CLOSED",IF($D7<Q$1,"ACTIVE","WAITING FOR OPEN")) -> ACTIVE
B8: 10SS5900 | C8: =VLOOKUP(B8,Master!B:C,2,0) -> 10SS5900 | D8: =VLOOKUP(B8,Master!B:L,11,0) -> 40990 | E8: =VLOOKUP(B8,Master!B:P,15,0) -> 0 | F8: =IF($E8>0,"CLOSED",IF($D8<F$1,"ACTIVE","WAITING FOR OPEN")) -> ACTIVE | G8: =IF($E8>0,"CLOSED",IF($D8<G$1,"ACTIVE","WAITING FOR OPEN")) -> ACTIVE | H8: =IF($E8>0,"CLOSED",IF($D8<H$1,"ACTIVE","WAITING FOR OPEN")) -> ACTIVE | I8: =IF($E8>0,"CLOSED",IF($D8<I$1,"ACTIVE","WAITING FOR OPEN")) -> ACTIVE | J8: =IF($E8>0,"CLOSED",IF($D8<J$1,"ACTIVE","WAITING FOR OPEN")) -> ACTIVE | K8: =IF($E8>0,"CLOSED",IF($D8<K$1,"ACTIVE","WAITING FOR OPEN")) -> ACTIVE | L8: =IF($E8>0,"CLOSED",IF($D8<L$1,"ACTIVE","WAITING FOR OPEN")) -> ACTIVE | M8: =IF($E8>0,"CLOSED",IF($D8<M$1,"ACTIVE","WAITING FOR OPEN")) -> ACTIVE | ... Q8: =IF($E8>0,"CLOSED",IF($D8<Q$1,"ACTIVE","WAITING FOR OPEN")) -> ACTIVE
B9: 10GG4100 | C9: =VLOOKUP(B9,Master!B:C,2,0) -> 10GG4100 | D9: =VLOOKUP(B9,Master!B:L,11,0) -> 41438 | E9: =VLOOKUP(B9,Master!B:P,15,0) -> 0 | F9: =IF($E9>0,"CLOSED",IF($D9<F$1,"ACTIVE","WAITING FOR OPEN")) -> ACTIVE | G9: =IF($E9>0,"CLOSED",IF($D9<G$1,"ACTIVE","WAITING FOR OPEN")) -> ACTIVE | H9: =IF($E9>0,"CLOSED",IF($D9<H$1,"ACTIVE","WAITING FOR OPEN")) -> ACTIVE | I9: =IF($E9>0,"CLOSED",IF($D9<I$1,"ACTIVE","WAITING FOR OPEN")) -> ACTIVE | J9: =IF($E9>0,"CLOSED",IF($D9<J$1,"ACTIVE","WAITING FOR OPEN")) -> ACTIVE | K9: =IF($E9>0,"CLOSED",IF($D9<K$1,"ACTIVE","WAITING FOR OPEN")) -> ACTIVE | L9: =IF($E9>0,"CLOSED",IF($D9<L$1,"ACTIVE","WAITING FOR OPEN")) -> ACTIVE | M9: =IF($E9>0,"CLOSED",IF($D9<M$1,"ACTIVE","WAITING FOR OPEN")) -> ACTIVE | ... Q9: =IF($E9>0,"CLOSED",IF($D9<Q$1,"ACTIVE","WAITING FOR OPEN")) -> ACTIVE
B10: 10GG4102 | C10: =VLOOKUP(B10,Master!B:C,2,0) -> 10GG4102 | D10: =VLOOKUP(B10,Master!B:L,11,0) -> 41544 | E10: =VLOOKUP(B10,Master!B:P,15,0) -> 0 | F10: =IF($E10>0,"CLOSED",IF($D10<F$1,"ACTIVE","WAITING FOR OPEN")) -> ACTIVE | G10: =IF($E10>0,"CLOSED",IF($D10<G$1,"ACTIVE","WAITING FOR OPEN")) -> ACTIVE | H10: =IF($E10>0,"CLOSED",IF($D10<H$1,"ACTIVE","WAITING FOR OPEN")) -> ACTIVE | I10: =IF($E10>0,"CLOSED",IF($D10<I$1,"ACTIVE","WAITING FOR OPEN")) -> ACTIVE | J10: =IF($E10>0,"CLOSED",IF($D10<J$1,"ACTIVE","WAITING FOR OPEN")) -> ACTIVE | K10: =IF($E10>0,"CLOSED",IF($D10<K$1,"ACTIVE","WAITING FOR OPEN")) -> ACTIVE | L10: =IF($E10>0,"CLOSED",IF($D10<L$1,"ACTIVE","WAITING FOR OPEN")) -> ACTIVE | M10: =IF($E10>0,"CLOSED",IF($D10<M$1,"ACTIVE","WAITING FOR OPEN")) -> ACTIVE | ... Q10: =IF($E10>0,"CLOSED",IF($D10<Q$1,"ACTIVE","WAITING FOR OPEN")) -> ACTIVE
B11: 10KK4407 | C11: =VLOOKUP(B11,Master!B:C,2,0) -> 10KK4407 | D11: =VLOOKUP(B11,Master!B:L,11,0) -> 41557 | E11: =VLOOKUP(B11,Master!B:P,15,0) -> 0 | F11: =IF($E11>0,"CLOSED",IF($D11<F$1,"ACTIVE","WAITING FOR OPEN")) -> ACTIVE | G11: =IF($E11>0,"CLOSED",IF($D11<G$1,"ACTIVE","WAITING FOR OPEN")) -> ACTIVE | H11: =IF($E11>0,"CLOSED",IF($D11<H$1,"ACTIVE","WAITING FOR OPEN")) -> ACTIVE | I11: =IF($E11>0,"CLOSED",IF($D11<I$1,"ACTIVE","WAITING FOR OPEN")) -> ACTIVE | J11: =IF($E11>0,"CLOSED",IF($D11<J$1,"ACTIVE","WAITING FOR OPEN")) -> ACTIVE | K11: =IF($E11>0,"CLOSED",IF($D11<K$1,"ACTIVE","WAITING FOR OPEN")) -> ACTIVE | L11: =IF($E11>0,"CLOSED",IF($D11<L$1,"ACTIVE","WAITING FOR OPEN")) -> ACTIVE | M11: =IF($E11>0,"CLOSED",IF($D11<M$1,"ACTIVE","WAITING FOR OPEN")) -> ACTIVE | ... Q11: =IF($E11>0,"CLOSED",IF($D11<Q$1,"ACTIVE","WAITING FOR OPEN")) -> ACTIVE
B12: 10GG4101 | C12: =VLOOKUP(B12,Master!B:C,2,0) -> 10GG4101 | D12: =VLOOKUP(B12,Master!B:L,11,0) -> 41639 | E12: =VLOOKUP(B12,Master!B:P,15,0) -> 0 | F12: =IF($E12>0,"CLOSED",IF($D12<F$1,"ACTIVE","WAITING FOR OPEN")) -> ACTIVE | G12: =IF($E12>0,"CLOSED",IF($D12<G$1,"ACTIVE","WAITING FOR OPEN")) -> ACTIVE | H12: =IF($E12>0,"CLOSED",IF($D12<H$1,"ACTIVE","WAITING FOR OPEN")) -> ACTIVE | I12: =IF($E12>0,"CLOSED",IF($D12<I$1,"ACTIVE","WAITING FOR OPEN")) -> ACTIVE | J12: =IF($E12>0,"CLOSED",IF($D12<J$1,"ACTIVE","WAITING FOR OPEN")) -> ACTIVE | K12: =IF($E12>0,"CLOSED",IF($D12<K$1,"ACTIVE","WAITING FOR OPEN")) -> ACTIVE | L12: =IF($E12>0,"CLOSED",IF($D12<L$1,"ACTIVE","WAITING FOR OPEN")) -> ACTIVE | M12: =IF($E12>0,"CLOSED",IF($D12<M$1,"ACTIVE","WAITING FOR OPEN")) -> ACTIVE | ... Q12: =IF($E12>0,"CLOSED",IF($D12<Q$1,"ACTIVE","WAITING FOR OPEN")) -> ACTIVE
B13: 10VV5300 | C13: =VLOOKUP(B13,Master!B:C,2,0) -> 10VV5300 | D13: =VLOOKUP(B13,Master!B:L,11,0) -> 41679 | E13: =VLOOKUP(B13,Master!B:P,15,0) -> 0 | F13: =IF($E13>0,"CLOSED",IF($D13<F$1,"ACTIVE","WAITING FOR OPEN")) -> ACTIVE | G13: =IF($E13>0,"CLOSED",IF($D13<G$1,"ACTIVE","WAITING FOR OPEN")) -> ACTIVE | H13: =IF($E13>0,"CLOSED",IF($D13<H$1,"ACTIVE","WAITING FOR OPEN")) -> ACTIVE | I13: =IF($E13>0,"CLOSED",IF($D13<I$1,"ACTIVE","WAITING FOR OPEN")) -> ACTIVE | J13: =IF($E13>0,"CLOSED",IF($D13<J$1,"ACTIVE","WAITING FOR OPEN")) -> ACTIVE | K13: =IF($E13>0,"CLOSED",IF($D13<K$1,"ACTIVE","WAITING FOR OPEN")) -> ACTIVE | L13: =IF($E13>0,"CLOSED",IF($D13<L$1,"ACTIVE","WAITING FOR OPEN")) -> ACTIVE | M13: =IF($E13>0,"CLOSED",IF($D13<M$1,"ACTIVE","WAITING FOR OPEN")) -> ACTIVE | ... Q13: =IF($E13>0,"CLOSED",IF($D13<Q$1,"ACTIVE","WAITING FOR OPEN")) -> ACTIVE
B14: 10GG4128 | C14: =VLOOKUP(B14,Master!B:C,2,0) -> 10GG4128 | D14: =VLOOKUP(B14,Master!B:L,11,0) -> 41931 | E14: =VLOOKUP(B14,Master!B:P,15,0) -> 0 | F14: =IF($E14>0,"CLOSED",IF($D14<F$1,"ACTIVE","WAITING FOR OPEN")) -> ACTIVE | G14: =IF($E14>0,"CLOSED",IF($D14<G$1,"ACTIVE","WAITING FOR OPEN")) -> ACTIVE | H14: =IF($E14>0,"CLOSED",IF($D14<H$1,"ACTIVE","WAITING FOR OPEN")) -> ACTIVE | I14: =IF($E14>0,"CLOSED",IF($D14<I$1,"ACTIVE","WAITING FOR OPEN")) -> ACTIVE | J14: =IF($E14>0,"CLOSED",IF($D14<J$1,"ACTIVE","WAITING FOR OPEN")) -> ACTIVE | K14: =IF($E14>0,"CLOSED",IF($D14<K$1,"ACTIVE","WAITING FOR OPEN")) -> ACTIVE | L14: =IF($E14>0,"CLOSED",IF($D14<L$1,"ACTIVE","WAITING FOR OPEN")) -> ACTIVE | M14: =IF($E14>0,"CLOSED",IF($D14<M$1,"ACTIVE","WAITING FOR OPEN")) -> ACTIVE | ... Q14: =IF($E14>0,"CLOSED",IF($D14<Q$1,"ACTIVE","WAITING FOR OPEN")) -> ACTIVE
B15: 10GG4105 | C15: =VLOOKUP(B15,Master!B:C,2,0) -> 10GG4105 | D15: =VLOOKUP(B15,Master!B:L,11,0) -> 42000 | E15: =VLOOKUP(B15,Master!B:P,15,0) -> 0 | F15: =IF($E15>0,"CLOSED",IF($D15<F$1,"ACTIVE","WAITING FOR OPEN")) -> ACTIVE | G15: =IF($E15>0,"CLOSED",IF($D15<G$1,"ACTIVE","WAITING FOR OPEN")) -> ACTIVE | H15: =IF($E15>0,"CLOSED",IF($D15<H$1,"ACTIVE","WAITING FOR OPEN")) -> ACTIVE | I15: =IF($E15>0,"CLOSED",IF($D15<I$1,"ACTIVE","WAITING FOR OPEN")) -> ACTIVE | J15: =IF($E15>0,"CLOSED",IF($D15<J$1,"ACTIVE","WAITING FOR OPEN")) -> ACTIVE | K15: =IF($E15>0,"CLOSED",IF($D15<K$1,"ACTIVE","WAITING FOR OPEN")) -> ACTIVE | L15: =IF($E15>0,"CLOSED",IF($D15<L$1,"ACTIVE","WAITING FOR OPEN")) -> ACTIVE | M15: =IF($E15>0,"CLOSED",IF($D15<M$1,"ACTIVE","WAITING FOR OPEN")) -> ACTIVE | ... Q15: =IF($E15>0,"CLOSED",IF($D15<Q$1,"ACTIVE","WAITING FOR OPEN")) -> ACTIVE
... B561: 30UP4954 | C561: =VLOOKUP(B561,Master!B:C,2,0) -> 30UP4954 | D561: =VLOOKUP(B561,Master!B:L,11,0) -> 46048 | E561: =VLOOKUP(B561,Master!B:P,15,0) -> 0 | F561: =IF($E561>0,"CLOSED",IF($D561<F$1,"ACTIVE","WAITING FOR OPEN")) -> ACTIVE | G561: =IF($E561>0,"CLOSED",IF($D561<G$1,"ACTIVE","WAITING FOR OPEN")) -> ACTIVE | H561: =IF($E561>0,"CLOSED",IF($D561<H$1,"ACTIVE","WAITING FOR OPEN")) -> ACTIVE | I561: =IF($E561>0,"CLOSED",IF($D561<I$1,"ACTIVE","WAITING FOR OPEN")) -> ACTIVE | J561: =IF($E561>0,"CLOSED",IF($D561<J$1,"ACTIVE","WAITING FOR OPEN")) -> ACTIVE | K561: =IF($E561>0,"CLOSED",IF($D561<K$1,"ACTIVE","WAITING FOR OPEN")) -> ACTIVE | L561: =IF($E561>0,"CLOSED",IF($D561<L$1,"ACTIVE","WAITING FOR OPEN")) -> ACTIVE | M561: =IF($E561>0,"CLOSED",IF($D561<M$1,"ACTIVE","WAITING FOR OPEN")) -> ACTIVE | ... Q561: =IF($E561>0,"CLOSED",IF($D561<Q$1,"ACTIVE","WAITING FOR OPEN")) -> ACTIVE
B562: 2010319 | C562: =VLOOKUP(B562,Master!B:C,2,0) -> 2010319 | D562: =VLOOKUP(B562,Master!B:L,11,0) -> 45972 | E562: =VLOOKUP(B562,Master!B:P,15,0) -> 0 | F562: =IF($E562>0,"CLOSED",IF($D562<F$1,"ACTIVE","WAITING FOR OPEN")) -> ACTIVE | G562: =IF($E562>0,"CLOSED",IF($D562<G$1,"ACTIVE","WAITING FOR OPEN")) -> ACTIVE | H562: =IF($E562>0,"CLOSED",IF($D562<H$1,"ACTIVE","WAITING FOR OPEN")) -> ACTIVE | I562: =IF($E562>0,"CLOSED",IF($D562<I$1,"ACTIVE","WAITING FOR OPEN")) -> ACTIVE | J562: =IF($E562>0,"CLOSED",IF($D562<J$1,"ACTIVE","WAITING FOR OPEN")) -> ACTIVE | K562: =IF($E562>0,"CLOSED",IF($D562<K$1,"ACTIVE","WAITING FOR OPEN")) -> ACTIVE | L562: =IF($E562>0,"CLOSED",IF($D562<L$1,"ACTIVE","WAITING FOR OPEN")) -> ACTIVE | M562: =IF($E562>0,"CLOSED",IF($D562<M$1,"ACTIVE","WAITING FOR OPEN")) -> ACTIVE | ... Q562: =IF($E562>0,"CLOSED",IF($D562<Q$1,"ACTIVE","WAITING FOR OPEN")) -> ACTIVE
B563: 10CV5020 | C563: =VLOOKUP(B563,Master!B:C,2,0) -> 10CV5020 | D563: =VLOOKUP(B563,Master!B:L,11,0) -> 46023 | E563: =VLOOKUP(B563,Master!B:P,15,0) -> 0 | F563: =IF($E563>0,"CLOSED",IF($D563<F$1,"ACTIVE","WAITING FOR OPEN")) -> ACTIVE | G563: =IF($E563>0,"CLOSED",IF($D563<G$1,"ACTIVE","WAITING FOR OPEN")) -> ACTIVE | H563: =IF($E563>0,"CLOSED",IF($D563<H$1,"ACTIVE","WAITING FOR OPEN")) -> ACTIVE | I563: =IF($E563>0,"CLOSED",IF($D563<I$1,"ACTIVE","WAITING FOR OPEN")) -> ACTIVE | J563: =IF($E563>0,"CLOSED",IF($D563<J$1,"ACTIVE","WAITING FOR OPEN")) -> ACTIVE | K563: =IF($E563>0,"CLOSED",IF($D563<K$1,"ACTIVE","WAITING FOR OPEN")) -> ACTIVE | L563: =IF($E563>0,"CLOSED",IF($D563<L$1,"ACTIVE","WAITING FOR OPEN")) -> ACTIVE | M563: =IF($E563>0,"CLOSED",IF($D563<M$1,"ACTIVE","WAITING FOR OPEN")) -> ACTIVE | ... Q563: =IF($E563>0,"CLOSED",IF($D563<Q$1,"ACTIVE","WAITING FOR OPEN")) -> ACTIVE
B564: 10DNNOBUD03 | C564: =VLOOKUP(B564,Master!B:C,2,0) -> 10DN5016 | D564: =VLOOKUP(B564,Master!B:L,11,0) -> 46075 | E564: =VLOOKUP(B564,Master!B:P,15,0) -> 0 | F564: =IF($E564>0,"CLOSED",IF($D564<F$1,"ACTIVE","WAITING FOR OPEN")) -> WAITING FOR OPEN | G564: =IF($E564>0,"CLOSED",IF($D564<G$1,"ACTIVE","WAITING FOR OPEN")) -> ACTIVE | H564: =IF($E564>0,"CLOSED",IF($D564<H$1,"ACTIVE","WAITING FOR OPEN")) -> ACTIVE | I564: =IF($E564>0,"CLOSED",IF($D564<I$1,"ACTIVE","WAITING FOR OPEN")) -> ACTIVE | J564: =IF($E564>0,"CLOSED",IF($D564<J$1,"ACTIVE","WAITING FOR OPEN")) -> ACTIVE | K564: =IF($E564>0,"CLOSED",IF($D564<K$1,"ACTIVE","WAITING FOR OPEN")) -> ACTIVE | L564: =IF($E564>0,"CLOSED",IF($D564<L$1,"ACTIVE","WAITING FOR OPEN")) -> ACTIVE | M564: =IF($E564>0,"CLOSED",IF($D564<M$1,"ACTIVE","WAITING FOR OPEN")) -> ACTIVE | ... Q564: =IF($E564>0,"CLOSED",IF($D564<Q$1,"ACTIVE","WAITING FOR OPEN")) -> ACTIVE
B565: 10UPNOBUD05 | C565: =VLOOKUP(B565,Master!B:C,2,0) -> 10UP5044 | D565: =VLOOKUP(B565,Master!B:L,11,0) -> 46060 | E565: =VLOOKUP(B565,Master!B:P,15,0) -> 0 | F565: =IF($E565>0,"CLOSED",IF($D565<F$1,"ACTIVE","WAITING FOR OPEN")) -> WAITING FOR OPEN | G565: =IF($E565>0,"CLOSED",IF($D565<G$1,"ACTIVE","WAITING FOR OPEN")) -> ACTIVE | H565: =IF($E565>0,"CLOSED",IF($D565<H$1,"ACTIVE","WAITING FOR OPEN")) -> ACTIVE | I565: =IF($E565>0,"CLOSED",IF($D565<I$1,"ACTIVE","WAITING FOR OPEN")) -> ACTIVE | J565: =IF($E565>0,"CLOSED",IF($D565<J$1,"ACTIVE","WAITING FOR OPEN")) -> ACTIVE | K565: =IF($E565>0,"CLOSED",IF($D565<K$1,"ACTIVE","WAITING FOR OPEN")) -> ACTIVE | L565: =IF($E565>0,"CLOSED",IF($D565<L$1,"ACTIVE","WAITING FOR OPEN")) -> ACTIVE | M565: =IF($E565>0,"CLOSED",IF($D565<M$1,"ACTIVE","WAITING FOR OPEN")) -> ACTIVE | ... Q565: =IF($E565>0,"CLOSED",IF($D565<Q$1,"ACTIVE","WAITING FOR OPEN")) -> ACTIVE
B566: 30CJ4992 | C566: =VLOOKUP(B566,Master!B:C,2,0) -> 30CJ4992 | D566: =VLOOKUP(B566,Master!B:L,11,0) -> 46044 | E566: =VLOOKUP(B566,Master!B:P,15,0) -> 0 | F566: =IF($E566>0,"CLOSED",IF($D566<F$1,"ACTIVE","WAITING FOR OPEN")) -> ACTIVE | G566: =IF($E566>0,"CLOSED",IF($D566<G$1,"ACTIVE","WAITING FOR OPEN")) -> ACTIVE | H566: =IF($E566>0,"CLOSED",IF($D566<H$1,"ACTIVE","WAITING FOR OPEN")) -> ACTIVE | I566: =IF($E566>0,"CLOSED",IF($D566<I$1,"ACTIVE","WAITING FOR OPEN")) -> ACTIVE | J566: =IF($E566>0,"CLOSED",IF($D566<J$1,"ACTIVE","WAITING FOR OPEN")) -> ACTIVE | K566: =IF($E566>0,"CLOSED",IF($D566<K$1,"ACTIVE","WAITING FOR OPEN")) -> ACTIVE | L566: =IF($E566>0,"CLOSED",IF($D566<L$1,"ACTIVE","WAITING FOR OPEN")) -> ACTIVE | M566: =IF($E566>0,"CLOSED",IF($D566<M$1,"ACTIVE","WAITING FOR OPEN")) -> ACTIVE | ... Q566: =IF($E566>0,"CLOSED",IF($D566<Q$1,"ACTIVE","WAITING FOR OPEN")) -> ACTIVE
B567: 30YTNOBUD01 | C567: =VLOOKUP(B567,Master!B:C,2,0) -> 30YT4982 | D567: =VLOOKUP(B567,Master!B:L,11,0) -> 46073 | E567: =VLOOKUP(B567,Master!B:P,15,0) -> 0 | F567: =IF($E567>0,"CLOSED",IF($D567<F$1,"ACTIVE","WAITING FOR OPEN")) -> WAITING FOR OPEN | G567: =IF($E567>0,"CLOSED",IF($D567<G$1,"ACTIVE","WAITING FOR OPEN")) -> ACTIVE | H567: =IF($E567>0,"CLOSED",IF($D567<H$1,"ACTIVE","WAITING FOR OPEN")) -> ACTIVE | I567: =IF($E567>0,"CLOSED",IF($D567<I$1,"ACTIVE","WAITING FOR OPEN")) -> ACTIVE | J567: =IF($E567>0,"CLOSED",IF($D567<J$1,"ACTIVE","WAITING FOR OPEN")) -> ACTIVE | K567: =IF($E567>0,"CLOSED",IF($D567<K$1,"ACTIVE","WAITING FOR OPEN")) -> ACTIVE | L567: =IF($E567>0,"CLOSED",IF($D567<L$1,"ACTIVE","WAITING FOR OPEN")) -> ACTIVE | M567: =IF($E567>0,"CLOSED",IF($D567<M$1,"ACTIVE","WAITING FOR OPEN")) -> ACTIVE | ... Q567: =IF($E567>0,"CLOSED",IF($D567<Q$1,"ACTIVE","WAITING FOR OPEN")) -> ACTIVE
B568: 2011005 | C568: =VLOOKUP(B568,Master!B:C,2,0) -> 2011005 | D568: =VLOOKUP(B568,Master!B:L,11,0) -> 45981 | E568: =VLOOKUP(B568,Master!B:P,15,0) -> 0 | F568: =IF($E568>0,"CLOSED",IF($D568<F$1,"ACTIVE","WAITING FOR OPEN")) -> ACTIVE | G568: =IF($E568>0,"CLOSED",IF($D568<G$1,"ACTIVE","WAITING FOR OPEN")) -> ACTIVE | H568: =IF($E568>0,"CLOSED",IF($D568<H$1,"ACTIVE","WAITING FOR OPEN")) -> ACTIVE | I568: =IF($E568>0,"CLOSED",IF($D568<I$1,"ACTIVE","WAITING FOR OPEN")) -> ACTIVE | J568: =IF($E568>0,"CLOSED",IF($D568<J$1,"ACTIVE","WAITING FOR OPEN")) -> ACTIVE | K568: =IF($E568>0,"CLOSED",IF($D568<K$1,"ACTIVE","WAITING FOR OPEN")) -> ACTIVE | L568: =IF($E568>0,"CLOSED",IF($D568<L$1,"ACTIVE","WAITING FOR OPEN")) -> ACTIVE | M568: =IF($E568>0,"CLOSED",IF($D568<M$1,"ACTIVE","WAITING FOR OPEN")) -> ACTIVE | ... Q568: =IF($E568>0,"CLOSED",IF($D568<Q$1,"ACTIVE","WAITING FOR OPEN")) -> ACTIVE
B569: TCHNEW004 | C569: =VLOOKUP(B569,Master!B:C,2,0) -> 1010115 | D569: =VLOOKUP(B569,Master!B:L,11,0) -> 46062 | E569: =VLOOKUP(B569,Master!B:P,15,0) -> 0 | F569: =IF($E569>0,"CLOSED",IF($D569<F$1,"ACTIVE","WAITING FOR OPEN")) -> WAITING FOR OPEN | G569: =IF($E569>0,"CLOSED",IF($D569<G$1,"ACTIVE","WAITING FOR OPEN")) -> ACTIVE | H569: =IF($E569>0,"CLOSED",IF($D569<H$1,"ACTIVE","WAITING FOR OPEN")) -> ACTIVE | I569: =IF($E569>0,"CLOSED",IF($D569<I$1,"ACTIVE","WAITING FOR OPEN")) -> ACTIVE | J569: =IF($E569>0,"CLOSED",IF($D569<J$1,"ACTIVE","WAITING FOR OPEN")) -> ACTIVE | K569: =IF($E569>0,"CLOSED",IF($D569<K$1,"ACTIVE","WAITING FOR OPEN")) -> ACTIVE | L569: =IF($E569>0,"CLOSED",IF($D569<L$1,"ACTIVE","WAITING FOR OPEN")) -> ACTIVE | M569: =IF($E569>0,"CLOSED",IF($D569<M$1,"ACTIVE","WAITING FOR OPEN")) -> ACTIVE | ... Q569: =IF($E569>0,"CLOSED",IF($D569<Q$1,"ACTIVE","WAITING FOR OPEN")) -> ACTIVE
B570: FCNEW002 | C570: =VLOOKUP(B570,Master!B:C,2,0) -> 1011821 | D570: =VLOOKUP(B570,Master!B:L,11,0) -> 46029 | E570: =VLOOKUP(B570,Master!B:P,15,0) -> 0 | F570: =IF($E570>0,"CLOSED",IF($D570<F$1,"ACTIVE","WAITING FOR OPEN")) -> ACTIVE | G570: =IF($E570>0,"CLOSED",IF($D570<G$1,"ACTIVE","WAITING FOR OPEN")) -> ACTIVE | H570: =IF($E570>0,"CLOSED",IF($D570<H$1,"ACTIVE","WAITING FOR OPEN")) -> ACTIVE | I570: =IF($E570>0,"CLOSED",IF($D570<I$1,"ACTIVE","WAITING FOR OPEN")) -> ACTIVE | J570: =IF($E570>0,"CLOSED",IF($D570<J$1,"ACTIVE","WAITING FOR OPEN")) -> ACTIVE | K570: =IF($E570>0,"CLOSED",IF($D570<K$1,"ACTIVE","WAITING FOR OPEN")) -> ACTIVE | L570: =IF($E570>0,"CLOSED",IF($D570<L$1,"ACTIVE","WAITING FOR OPEN")) -> ACTIVE | M570: =IF($E570>0,"CLOSED",IF($D570<M$1,"ACTIVE","WAITING FOR OPEN")) -> ACTIVE | ... Q570: =IF($E570>0,"CLOSED",IF($D570<Q$1,"ACTIVE","WAITING FOR OPEN")) -> ACTIVE
B571: 1011108 | C571: =VLOOKUP(B571,Master!B:C,2,0) -> 1011108 | D571: =VLOOKUP(B571,Master!B:L,11,0) -> 46036 | E571: =VLOOKUP(B571,Master!B:P,15,0) -> 0 | F571: =IF($E571>0,"CLOSED",IF($D571<F$1,"ACTIVE","WAITING FOR OPEN")) -> ACTIVE | G571: =IF($E571>0,"CLOSED",IF($D571<G$1,"ACTIVE","WAITING FOR OPEN")) -> ACTIVE | H571: =IF($E571>0,"CLOSED",IF($D571<H$1,"ACTIVE","WAITING FOR OPEN")) -> ACTIVE | I571: =IF($E571>0,"CLOSED",IF($D571<I$1,"ACTIVE","WAITING FOR OPEN")) -> ACTIVE | J571: =IF($E571>0,"CLOSED",IF($D571<J$1,"ACTIVE","WAITING FOR OPEN")) -> ACTIVE | K571: =IF($E571>0,"CLOSED",IF($D571<K$1,"ACTIVE","WAITING FOR OPEN")) -> ACTIVE | L571: =IF($E571>0,"CLOSED",IF($D571<L$1,"ACTIVE","WAITING FOR OPEN")) -> ACTIVE | M571: =IF($E571>0,"CLOSED",IF($D571<M$1,"ACTIVE","WAITING FOR OPEN")) -> ACTIVE | ... Q571: =IF($E571>0,"CLOSED",IF($D571<Q$1,"ACTIVE","WAITING FOR OPEN")) -> ACTIVE
B572: 1011716 | C572: =VLOOKUP(B572,Master!B:C,2,0) -> 1011716 | D572: =VLOOKUP(B572,Master!B:L,11,0) -> 46042 | E572: =VLOOKUP(B572,Master!B:P,15,0) -> 0 | F572: =IF($E572>0,"CLOSED",IF($D572<F$1,"ACTIVE","WAITING FOR OPEN")) -> ACTIVE | G572: =IF($E572>0,"CLOSED",IF($D572<G$1,"ACTIVE","WAITING FOR OPEN")) -> ACTIVE | H572: =IF($E572>0,"CLOSED",IF($D572<H$1,"ACTIVE","WAITING FOR OPEN")) -> ACTIVE | I572: =IF($E572>0,"CLOSED",IF($D572<I$1,"ACTIVE","WAITING FOR OPEN")) -> ACTIVE | J572: =IF($E572>0,"CLOSED",IF($D572<J$1,"ACTIVE","WAITING FOR OPEN")) -> ACTIVE | K572: =IF($E572>0,"CLOSED",IF($D572<K$1,"ACTIVE","WAITING FOR OPEN")) -> ACTIVE | L572: =IF($E572>0,"CLOSED",IF($D572<L$1,"ACTIVE","WAITING FOR OPEN")) -> ACTIVE | M572: =IF($E572>0,"CLOSED",IF($D572<M$1,"ACTIVE","WAITING FOR OPEN")) -> ACTIVE | ... Q572: =IF($E572>0,"CLOSED",IF($D572<Q$1,"ACTIVE","WAITING FOR OPEN")) -> ACTIVE
B573: 1011410 | C573: =VLOOKUP(B573,Master!B:C,2,0) -> 1011410 | D573: =VLOOKUP(B573,Master!B:L,11,0) -> 46044 | E573: =VLOOKUP(B573,Master!B:P,15,0) -> 0 | F573: =IF($E573>0,"CLOSED",IF($D573<F$1,"ACTIVE","WAITING FOR OPEN")) -> ACTIVE | G573: =IF($E573>0,"CLOSED",IF($D573<G$1,"ACTIVE","WAITING FOR OPEN")) -> ACTIVE | H573: =IF($E573>0,"CLOSED",IF($D573<H$1,"ACTIVE","WAITING FOR OPEN")) -> ACTIVE | I573: =IF($E573>0,"CLOSED",IF($D573<I$1,"ACTIVE","WAITING FOR OPEN")) -> ACTIVE | J573: =IF($E573>0,"CLOSED",IF($D573<J$1,"ACTIVE","WAITING FOR OPEN")) -> ACTIVE | K573: =IF($E573>0,"CLOSED",IF($D573<K$1,"ACTIVE","WAITING FOR OPEN")) -> ACTIVE | L573: =IF($E573>0,"CLOSED",IF($D573<L$1,"ACTIVE","WAITING FOR OPEN")) -> ACTIVE | M573: =IF($E573>0,"CLOSED",IF($D573<M$1,"ACTIVE","WAITING FOR OPEN")) -> ACTIVE | ... Q573: =IF($E573>0,"CLOSED",IF($D573<Q$1,"ACTIVE","WAITING FOR OPEN")) -> ACTIVE
B574: 50GL3601 | C574: =VLOOKUP(B574,Master!B:C,2,0) -> 50GL3601 | D574: =VLOOKUP(B574,Master!B:L,11,0) -> 45689 | E574: =VLOOKUP(B574,Master!B:P,15,0) -> 0 | F574: =IF($E574>0,"CLOSED",IF($D574<F$1,"ACTIVE","WAITING FOR OPEN")) -> ACTIVE | G574: =IF($E574>0,"CLOSED",IF($D574<G$1,"ACTIVE","WAITING FOR OPEN")) -> ACTIVE | H574: =IF($E574>0,"CLOSED",IF($D574<H$1,"ACTIVE","WAITING FOR OPEN")) -> ACTIVE | I574: =IF($E574>0,"CLOSED",IF($D574<I$1,"ACTIVE","WAITING FOR OPEN")) -> ACTIVE | J574: =IF($E574>0,"CLOSED",IF($D574<J$1,"ACTIVE","WAITING FOR OPEN")) -> ACTIVE | K574: =IF($E574>0,"CLOSED",IF($D574<K$1,"ACTIVE","WAITING FOR OPEN")) -> ACTIVE | L574: =IF($E574>0,"CLOSED",IF($D574<L$1,"ACTIVE","WAITING FOR OPEN")) -> ACTIVE | M574: =IF($E574>0,"CLOSED",IF($D574<M$1,"ACTIVE","WAITING FOR OPEN")) -> ACTIVE | ... Q574: =IF($E574>0,"CLOSED",IF($D574<Q$1,"ACTIVE","WAITING FOR OPEN")) -> ACTIVE
... B639: 10KKNOBUD13 | C639: =VLOOKUP(B639,Master!B:C,2,0) -> 10KK5063 | D639: =VLOOKUP(B639,Master!B:L,11,0) -> 46357 | E639: =VLOOKUP(B639,Master!B:P,15,0) -> 0 | F639: =IF($E639>0,"CLOSED",IF($D639<F$1,"ACTIVE","WAITING FOR OPEN")) -> WAITING FOR OPEN | G639: =IF($E639>0,"CLOSED",IF($D639<G$1,"ACTIVE","WAITING FOR OPEN")) -> WAITING FOR OPEN | H639: =IF($E639>0,"CLOSED",IF($D639<H$1,"ACTIVE","WAITING FOR OPEN")) -> WAITING FOR OPEN | I639: =IF($E639>0,"CLOSED",IF($D639<I$1,"ACTIVE","WAITING FOR OPEN")) -> WAITING FOR OPEN | J639: =IF($E639>0,"CLOSED",IF($D639<J$1,"ACTIVE","WAITING FOR OPEN")) -> WAITING FOR OPEN | K639: =IF($E639>0,"CLOSED",IF($D639<K$1,"ACTIVE","WAITING FOR OPEN")) -> WAITING FOR OPEN | L639: =IF($E639>0,"CLOSED",IF($D639<L$1,"ACTIVE","WAITING FOR OPEN")) -> WAITING FOR OPEN | M639: =IF($E639>0,"CLOSED",IF($D639<M$1,"ACTIVE","WAITING FOR OPEN")) -> WAITING FOR OPEN | ... Q639: =IF($E639>0,"CLOSED",IF($D639<Q$1,"ACTIVE","WAITING FOR OPEN")) -> ACTIVE
D640: No of stores | F640: =COUNTIFS(F3:F639,"ACTIVE") -> 561 | G640: =COUNTIFS(G3:G639,"ACTIVE") -> 568 | H640: =COUNTIFS(H3:H639,"ACTIVE") -> 570 | I640: =COUNTIFS(I3:I639,"ACTIVE") -> 587 | J640: =COUNTIFS(J3:J639,"ACTIVE") -> 602 | K640: =COUNTIFS(K3:K639,"ACTIVE") -> 610 | L640: =COUNTIFS(L3:L639,"ACTIVE") -> 618 | M640: =COUNTIFS(M3:M639,"ACTIVE") -> 622 | ... Q640: =COUNTIFS(Q3:Q639,"ACTIVE") -> 629

Sheet Sheet1

Sheet Lọc code mới
A1: Code from network + PMO | B1: Vlookup code master
A2: 2010704 | B2: =VLOOKUP(A2,Master!B:H,7,0) -> HN Nguyen Van Loc
A3: 2011001 | B3: =VLOOKUP(A3,Master!B:H,7,0) -> HN Xuan La
A4: 2010403 | B4: =VLOOKUP(A4,Master!B:H,7,0) -> HN Hao Nam
A5: 2050101 | B5: =VLOOKUP(A5,Master!B:H,7,0) -> HY Pho Truc Ecopark
A6: 2010309 | B6: =VLOOKUP(A6,Master!B:H,7,0) -> HN Vu Pham Ham
A7: 2010604 | B7: =VLOOKUP(A7,Master!B:H,7,0) -> HN Gamuda Gardens
A8: 1010712 | B8: =VLOOKUP(A8,Master!B:H,7,0) -> HCM Signature Crescent Mall
A9: 1011003 | B9: =VLOOKUP(A9,Master!B:H,7,0) -> HCM Cao Thang 2
A10: 2010402 | B10: =VLOOKUP(A10,Master!B:H,7,0) -> HN Thai Ha
A11: 1010311 | B11: =VLOOKUP(A11,Master!B:H,7,0) -> UT HCM 71 Hoang Van Thai
A12: 1011410 | B12: =VLOOKUP(A12,Master!B:H,7,0) -> UT HCM 141-143 Tan Son Nhi
A13: 1011715 | B13: =VLOOKUP(A13,Master!B:H,7,0) -> Utea Phan Huy Ích
... A637: 10KKNOBUD13 | B637: =VLOOKUP(A637,Master!B:H,7,0) -> Kichi Kichi

Sheet TCH (append)
A1: 1. Miền | B1: Mã code chính dự án | C1: Code budget | D1: 2. Tên dự án | E1: Công việc | F1: 3. Brand | G1: 4. Loại hình dự án | H1: 5. Vị trí | I1: Trạng thái thiết kế | J1: Tình trạng lập dự toán | K1: Tình trạng đấu thầu thi công | L1: Ngày kết thúc thi công theo kế hoạch | M1: Ngày bắt đầu thi công thực tế | N1: Ngày kết thúc thi công thực tế | O1: Tỉ lệ % hoàn thành thi công | P1: Tình trạng thi công
A2: NS | B2: TCH0001 | C2: 2010704 | D2: TCH + Flychef Nguyễn Văn Lộc | F2: TCH | G2: Convert | H2: Shophouse | I2: Completed | J2: Completed | K2: Completed | L2: 45976 | M2: 45933 | N2: 45991 | O2: 1 | P2: Completed
A3: NS | B3: TCH0002 | C3: 2011001 | D3: TCH HNI Can 8 Khu nha N1 Du An Xuan La Xuan Dinh | F3: TCH | G3: Reno | H3: Chân đế | I3: Completed | J3: Completed | K3: Completed | L3: 45966 | M3: 45923 | N3: 45966 | O3: 1 | P3: Completed
A4: NS | B4: TCH0003 | C4: 2010403 | D4: TCH HNI 30 Hao Nam | F4: TCH | G4: Reno | H4: Shophouse | I4: Completed | J4: Completed | K4: Completed | L4: 46002 | M4: 45980 | N4: 46002 | O4: 1 | P4: Completed
A5: NS | B5: TCH0004 | C5: 2050101 | D5: TCH HYN B65 Pho Truc | F5: TCH | G5: Reno | H5: Shophouse | I5: Completed | J5: Completed | K5: Completed | L5: 46016 | M5: 45986 | N5: 46016 | O5: 1 | P5: Completed
A6: NS | B6: TCH0005 | C6: 2010309 | D6: TCH HNI 60 Vu Pham Ham | F6: TCH | G6: Reno | H6: Shophouse | I6: Completed | J6: Completed | K6: Completed | L6: 46016 | M6: 45987 | N6: 46014 | O6: 1 | P6: Completed
A7: NS | B7: TCH0006 | C7: 2010604 | D7: TCH HNI CT1-A-01 Gamuda Gardens | F7: TCH | G7: Reno | H7: Chân đế | I7: Completed | J7: Completed | K7: Completed | L7: 46051 | M7: 46021 | N7: 46050 | O7: 1 | P7: Completed
A8: SS | B8: TCH0007 | C8: 1010712 | D8: TCH Sig 101 Ton Dat Tien (Crescent Mall) | E8: Linh báo tạm ngưng đến khi có thông tin | F8: TCH(K) & UP | G8: Convert | H8: Mall | I8: Completed | J8: Completed | K8: Completed | P8: On Hold
A9: SS | B9: TCH0008 | C9: 1011003 | D9: TCH HCM 175B Cao Thang noi dai | F9: TCH & UP | G9: Convert | H9: Shophouse | I9: Completed | J9: Not Planned | K9: On Hold | P9: On Hold
A10: NS | B10: TCH0009 | C10: 2010402 | D10: TCH HNI So 1-2 Thai Ha | F10: UP | G10: Convert | H10: Chân đế | I10: Cancelled | J10: Cancelled | K10: Cancelled | P10: On Hold
A11: SS | B11: TCH0010 | C11: 1010311 | D11: TCH HCM 71 Hoang Van Thai | F11: UT | G11: Convert | H11: Shophouse | I11: Completed | J11: Completed | K11: On Hold | P11: On Hold
A12: SS | B12: TCH0011 | C12: 1011410 | D12: TCH HCM 141-143 Tan Son Nhi | F12: UT | G12: Convert | H12: Shophouse | I12: Completed | J12: Completed | K12: Completed | L12: 46042 | M12: 46009 | N12: 46042 | O12: 1 | P12: Completed
A13: SS | B13: TCH0012 | C13: 1011715 | D13: TCH HCM 403 Phan Huy Ich | F13: UT | G13: Convert | H13: Shophouse | I13: Completed | J13: Completed | K13: Completed | L13: 46002 | M13: 45974 | N13: 46002 | O13: 1 | P13: Completed
A14: SS | B14: TCH0013 | C14: 1011716 | D14: TCH HCM 771 Phan Van Tri | F14: UT | G14: Convert | H14: Shophouse | I14: Completed | J14: Completed | K14: Completed | L14: 46039 | M14: 46008 | N14: 46039 | O14: 1 | P14: Completed
A15: SS | B15: TCH0014 | C15: 1011820 | D15: TCH HCM 75 duong D1 UT 75 NGUYỄN VĂN THƯƠNG (D1) | F15: UT | G15: Convert | H15: Shophouse | I15: Completed | J15: Completed | K15: In Progress
A16: SS | B16: TCH0015 | C16: 1011108 | D16: TCH HCM 45 Duong So 5 - Cu xa Binh Thoi | F16: UT | G16: Convert | H16: Shophouse | I16: Completed | J16: Completed | K16: Completed | L16: 46032 | M16: 46007 | N16: 46031 | O16: 1 | P16: Completed
A17: SS | B17: TCH0016 | C17: 1011819 | D17: TCH HCM 14B1 Ngo Tat To | F17: UT | G17: Convert | H17: Shophouse | I17: Cancelled | J17: Completed | K17: Cancelled | P17: Cancelled
A18: SS | B18: TCH0017 | C18: 1010211 | D18: TCH HCM 670 Nguyen Duy Trinh | F18: UT | G18: Convert | H18: Shophouse | I18: Completed | J18: Completed | K18: Completed | L18: 46010 | M18: 45975 | N18: 46008 | O18: 1 | P18: Completed
A19: SS | B19: TCH0018 | C19: 1010201 | D19: TCH HCM 57 Xuan Thuy | F19: TCH(K) & UP | G19: Convert | H19: Shophouse | I19: Completed | J19: Completed | K19: Completed | L19: 46044 | M19: 45996 | N19: 46044 | O19: 1 | P19: Completed
A20: SS | B20: TCH0019 | C20: 1011107 | D20: TCH HCM 64A Lu Gia | F20: TCH | G20: Cosmetic | H20: Shophouse | I20: Completed | J20: Completed | K20: Completed | L20: 46068 | M20: 46051 | N20: 46060 | O20: 1 | P20: Completed
A21: SS | B21: TCH0020 | C21: 1011007 | D21: TCH HCM 25A duong Dong Nai | F21: TCH | G21: Cosmetic | H21: Shophouse | I21: Completed | J21: Not Planned | K21: On Hold | P21: On Hold
A22: SS | B22: TCH0021 | C22: 1010703 | D22: TCH HCM 492 Nguyen Thi Thap | E22: Đang chờ duyệt phát sinh, dự kiến tiến độ bàn giao qua tết | F22: TCH | G22: Cosmetic | H22: Shophouse | I22: Completed | J22: Not Planned | K22: Completed | L22: 46071 | M22: 46041 | N22: 46063 | O22: 1 | P22: Completed
A23: SS | B23: TCH0022 | C23: 1011310 | D23: TCH HCM 4-6 Ap Bac | F23: TCH | G23: Cosmetic | H23: Shophouse | I23: Completed | J23: Not Planned | K23: Completed | L23: 46064 | M23: 46039 | N23: 46064 | O23: 1 | P23: Completed
A24: SS | B24: TCH0023 | C24: 1011313 | D24: TCH HCM 51 Le Trung Nghia | F24: TCH | G24: Cosmetic | H24: Shophouse | I24: Completed | J24: Completed | K24: Completed | L24: 46058 | M24: 46027 | N24: 46058 | O24: 1 | P24: Completed
A25: SS | B25: TCH0024 | C25: 1011705 | D25: TCH HCM 190B1 Phan Van Tri | E25: Nhà hàng bàn giao MB ngày 20/1/26 | F25: TCH | G25: Cosmetic | H25: Shophouse | I25: Completed | J25: Not Planned | K25: Completed | L25: 46067 | M25: 46042 | N25: 46067 | O25: 1 | P25: Completed
A26: SS | B26: TCH0025 | C26: 1011301 | D26: TCH HCM 02 Dong Da | F26: TCH | G26: Cosmetic | H26: Shophouse | I26: Completed | J26: Completed | K26: Completed | L26: 46053 | M26: 46027 | O26: 1 | P26: Completed
A27: SS | B27: TCH0026 | C27: 1010209 | D27: TCH HCM Homyland Riverside | F27: TCH | G27: Cosmetic | H27: Chân đế | I27: Completed | J27: Completed | K27: Completed | L27: 46058 | M27: 46043 | O27: 1 | P27: Completed
A28: SS | B28: TCH0027 | C28: 1010601 | D28: TCH HCM 178 Hau Giang | E28: ĐTXD thông báo 14/1/26, đầu tuần nhà thầu báo lại tiến độ | F28: TCH | G28: Cosmetic | H28: Shophouse | I28: Completed | J28: Not Planned | K28: Completed | L28: 46063 | M28: 46051 | N28: 46063 | O28: 1 | P28: Completed
A29: SS | B29: TCH0028 | C29: 1010304 | D29: TCH HCM 6A Ngo Thoi Nhiem | F29: TCH | G29: Reno | H29: Shophouse | I29: Completed | J29: Completed | K29: Completed | L29: 46062 | M29: 46035 | N29: 46061 | O29: 1 | P29: Completed
A30: SS | B30: TCH0029 | C30: 1010207 | D30: TCH HCM 17 Mai Chi Tho | E30: dự kiến tuần này xin phép xong | F30: TCH | G30: Cosmetic | H30: Chân đế | I30: Completed | J30: Not Planned | K30: Completed | L30: 46075 | M30: 46048 | N30: 46067 | O30: 1 | P30: Completed
A31: SS | B31: TCH0030 | C31: 1010901 | D31: TCH HCM 359 Do Xuan Hop | E31: 7/2/26 inox mới bàn giao | F31: TCH | G31: Cosmetic | H31: Shophouse | I31: Completed | J31: Completed | K31: Completed | L31: 46057 | M31: 46021 | N31: 46059 | O31: 1 | P31: Completed
A32: SS | B32: TCH0031 | C32: 3060101 | D32: TCH TNH 295 Duong 30/4 | F32: TCH | G32: Cosmetic | H32: Shophouse | I32: Completed | J32: Not Planned | K32: In Progress
A33: SS | B33: TCH0032 | C33: 1010603 | D33: TCH HCM 111-113 Binh Phu | E33: ĐTXD thông báo thầu 11/3, qua tuần họp kickoff sẽ báo lại tiến độ | F33: TCH | G33: Cosmetic | H33: Shophouse | I33: Completed | J33: Not Planned | K33: Completed | L33: 46139 | O33: 0 | P33: In Progress
A34: SS | B34: TCH0033 | C34: 1011603 | D34: TCH HCM 68 Huynh Van Banh | F34: TCH | G34: Cosmetic | H34: Shophouse | I34: Completed | J34: Not Planned | K34: Cancelled | P34: Cancelled
A35: SS | B35: TCH0034 | C35: 3020101 | D35: TCH BRU 5 Ba Cu | F35: TCH | G35: Cosmetic | H35: Shophouse | I35: Completed | J35: Not Planned | K35: Completed | P35: In Progress
A36: SS | B36: TCH0035 | C36: 4030101 | D36: TCH KHA 44 Tran Phu | F36: TCH | G36: Cosmetic | I36: Completed | J36: Not Planned | K36: In Progress
A37: SS | B37: TCH0036 | C37: 1011605 | D37: TCH HCM So 1 Hoa Su | F37: TCH | G37: Cosmetic | H37: Shophouse | I37: Completed | J37: Completed | K37: Completed | L37: 46056 | M37: 46021 | O37: 1 | P37: Completed
A38: SS | B38: TCH0037 | C38: 1011904 | D38: TCH HCM 66E Hoang Dieu 2 | F38: TCH | G38: Cosmetic | H38: Shophouse | I38: Completed | J38: Completed | K38: Completed | L38: 46056 | M38: 46021 | O38: 1 | P38: Completed
A39: SS | B39: TCH0038 | C39: 1012001 | D39: TCH HCM 114 Duong 9A - Trung Son | E39: Đã họp Kickoff, hiện đang tiến hành trình duyệt phát sinh theo y/c TK, Ops, AMM, thực tế,.... Tiến độ dự kiến báo lại sau, NCC báo duyệt phát sinh mới tiến hành làm và gửi tiến độ thi công cụ thể | F39: TCH | G39: Cosmetic | H39: Shophouse | I39: Completed | J39: Not Planned | K39: Completed | L39: 46119 | M39: 46098 | O39: 0.1 | P39: In Progress
A40: SS | B40: TCH0039 | C40: 3010102 | D40: TCH DNI R132 Vo Thi Sau | E40: Chưa nhận được thông báo thầu | F40: TCH | G40: Cosmetic | I40: Completed | J40: Not Planned | K40: Completed
A41: SS | B41: TCH0040 | C41: 3040101 | D41: TCH BDG Hikari Binh Duong | F41: TCH | G41: Cosmetic | H41: Mall | I41: Completed | J41: Not Planned | K41: Completed
A42: SS | B42: TCH0041 | C42: 1010401 | D42: TCH HCM 35-37 Duong 41 | F42: TCH | G42: Cosmetic | H42: Shophouse | I42: Completed | J42: Completed | K42: Completed | L42: 46060 | M42: 46027 | N42: 46060 | O42: 1 | P42: Completed
A43: SS | B43: TCH0042 | C43: 1010208 | D43: TCH HCM 116-118 Duong So 51 | E43: ĐTXD thông báo thầu 12/3, qua tuần họp kickoff sẽ báo lại tiến độ | F43: TCH | G43: Cosmetic | H43: Shophouse | I43: Completed | J43: Completed | K43: Completed | L43: 46133 | O43: 0 | P43: In Progress
A44: SS | B44: TCH0043 | C44: 1012101 | D44: TCH HCM 93/5B Nguyen Anh Thu | F44: TCH | G44: Cosmetic | H44: Shophouse | I44: Completed | J44: Not Planned | K44: Completed
A45: SS | B45: TCH0044 | C45: 1011305 | D45: TCH HCM 281 Le van Sy | F45: UT | G45: Flagship | H45: Shophouse | I45: Cancelled | J45: Not Planned | K45: Cancelled | P45: Cancelled
A46: SS | B46: TCH0045 | C46: 1011002 | D46: TCH HCM 798 Su Van Hanh | E46: Chưa nhận được thông báo thầu | F46: UT | G46: Flagship | H46: Shophouse | I46: Completed | J46: Not Planned | K46: Completed
A47: SS | B47: TCH0046 | C47: 1011502 | D47: TCH HCM 9-11 Duong so 22 | E47: Chưa có thiết kế | F47: TCH & UP | G47: Flagship | H47: Mall | I47: Completed | J47: Not Planned
A48: SS | B48: TCH0047 | C48: 4030102 | D48: TCH KHA 01 Tran Hung Dao | F48: TCH | G48: Flagship | H48: Mall | I48: Completed | J48: Not Planned | K48: In Progress
A49: NS | B49: TCH0048 | C49: 2020301 | D49: TCH HPG AEON Le Chan | E49: Thi công Phá dỡ, hoàn trả mặt bằng. Tiến độ thực hiện: 10 ngày từ 28/02 - 10/03/2026 (Chỉ thi công ban đêm từ 23h00 đến 07h00 sáng hôm sau, không được phép thi công ban ngày) | F49: TCH | G49: Cosmetic | H49: Mall | I49: Cancelled | J49: Not Planned | K49: Completed | L49: 46091 | M49: 46082 | O49: 1 | P49: Completed
A50: NS | B50: TCH0049 | C50: 2020101 | D50: TCH HPG So 15 Tran Phu | F50: TCH | G50: Cosmetic | H50: Shophouse | I50: Completed | J50: Not Planned | K50: Completed | L50: 46134 | O50: 0 | P50: In Progress
A51: NS | B51: TCH0050 | C51: 2010203 | D51: TCH HNI The Five Residences 345 Doi Can | F51: TCH | G51: Cosmetic | H51: Chân đế | I51: Completed | J51: Completed | K51: Completed | L51: 46025 | M51: 46006 | N51: 46025 | O51: 1 | P51: Completed
A52: NS | B52: TCH0051 | C52: 2010501 | D52: TCH HNI Tang 1 458 Minh Khai | F52: TCH | G52: Cosmetic | I52: Completed | J52: Not Planned | K52: Completed | L52: 46067 | M52: 46041 | N52: 46067 | O52: 1 | P52: Completed
A53: NS | B53: TCH0052 | C53: 2010507 | D53: TCH HNI 92 Le Thanh Nghi | F53: TCH | G53: Cosmetic | H53: Shophouse | I53: Completed | J53: Not Planned | K53: Completed | L53: 46118 | M53: 46091 | O53: 0 | P53: In Progress
A54: NS | B54: TCH0053 | C54: 2011201 | D54: TCH HNI Vincom Mega Mall Ocean Park | F54: TCH | G54: Cosmetic | H54: Mall | I54: Completed | J54: Not Planned | K54: On Hold | M54: 46091 | P54: On Hold
A55: NS | B55: TCH0054 | C55: 2011104 | D55: TCH HNI Vincom Mega Mall Smart City | F55: TCH | G55: Cosmetic | I55: Completed | J55: Not Planned | K55: In Progress | M55: 46091
A56: NS | B56: TCH0055 | C56: 2010601 | D56: TCH HNI Rice City Linh Dam | F56: TCH | G56: Cosmetic | H56: Chân đế | I56: Completed | J56: Not Planned | K56: Completed | L56: 46118 | M56: 46092 | O56: 0 | P56: In Progress
A57: NS | B57: TCH0056 | C57: 2010312 | D57: TCH HNI 17T3 Hoang Dao Thuy | F57: TCH | G57: Cosmetic | H57: Shophouse | I57: Completed | J57: Not Planned | K57: Completed | L57: 46129 | M57: 46091 | O57: 0.15 | P57: In Progress
A58: NS | B58: TCH0057 | C58: 2010310 | D58: TCH HNI Discovery Complex 302 Cau Giay | F58: TCH | G58: Cosmetic | H58: Shophouse | I58: Completed | J58: Not Planned | K58: In Progress
A59: NS | B59: TCH0058 | C59: 2010602 | D59: TCH HNI 72 Tran Nguyen Dan | F59: TCH | G59: Cosmetic | H59: Shophouse | I59: Completed | J59: Not Planned | K59: Completed | L59: 46058 | M59: 46033 | N59: 46057 | O59: 1 | P59: Completed
A60: NS | B60: TCH0059 | C60: 2010701 | D60: TCH HNI V3-Van Phu Victoria-CT9 | F60: TCH | G60: Cosmetic | H60: Chân đế | I60: Completed | J60: Not Planned | K60: Completed | L60: 46065 | M60: 46044 | N60: 46065 | O60: 1 | P60: Completed
A61: NS | B61: TCH0060 | C61: 2010804 | D61: TCH HNI 349 Vu Tong Phan | F61: TCH | G61: Cosmetic | H61: Chân đế | I61: Completed | J61: Not Planned | K61: Completed | L61: 46115 | M61: 46092 | O61: 0 | P61: In Progress
A62: NS | B62: TCH0061 | C62: 2010313 | D62: TCH HNI Chelsea Residences | F62: TCH | G62: Cosmetic | H62: Chân đế | I62: Completed | J62: Not Planned | K62: Completed | L62: 46125 | M62: 46091 | O62: 0 | P62: In Progress
A63: NS | B63: TCH0062 | C63: 2010303 | D63: TCH HNI Khu DTM Trung Yen | F63: TCH | G63: Flagship | H63: Shophouse | I63: Completed | J63: Completed | K63: Completed | L63: 46048 | M63: 46004 | N63: 46048 | O63: 1 | P63: Completed
A64: SS | B64: TCH0063 | C64: 1010101 | D64: TCH HCM 141 Nguyễn Thái Bình | F64: TCH & FC | G64: Flagship | H64: Shophouse | I64: Completed | J64: Completed | K64: Completed | L64: 46021 | M64: 45981 | N64: 46021 | O64: 1 | P64: Completed
A65: NS | B65: TCH0064 | C65: 2010315 | D65: TCH HNI NO2-D12 The Park Home | F65: TCH | G65: Flagship | H65: Shophouse | I65: Completed | J65: Completed | K65: Completed | P65: In Progress
A66: SS | B66: TCH0065 | C66: 1011804 | D66: TCH HCM 469 Dien Bien Phu | E66: TCH + FC + Mama | F66: TCH & FC | G66: Flagship | H66: Shophouse | I66: Completed | J66: Completed | K66: Completed | L66: 46014 | M66: 45964 | N66: 46014 | O66: 1 | P66: Completed
A67: SS | B67: TCH0066 | C67: 4030103 | D67: TCH KHA Big C Go Nha Trang | F67: TCH | G67: Reno | H67: Mall | I67: Completed | J67: Completed | K67: In Progress
A68: SS | B68: TCH0067 | C68: 1010502 | D68: TCH HCM 682 Tran Hung Dao | F68: TCH | G68: Cosmetic | H68: Shophouse | I68: Completed | J68: Completed | K68: Completed | L68: 46058 | M68: 46027 | N68: 46058 | O68: 1 | P68: Completed
A69: SS | B69: TCH0068 | C69: 1011303 | D69: TCH HCM 16/3 Hoang Viet (Út Tịch) | F69: TCH | G69: Cosmetic | H69: Shophouse | I69: Completed | J69: Not Planned | K69: In Progress
A70: SS | B70: TCH0069 | C70: 1011304 | D70: TCH HCM 18 Hong Ha | E70: OPS bàn giao MB 26/03/26 | F70: TCH | G70: Cosmetic | H70: Shophouse | I70: Completed | J70: Not Planned | K70: Completed | L70: 46142 | O70: 0 | P70: In Progress
A71: NS | B71: TCH0070 | C71: 2010101 | D71: TCH HNI 23M Hai Ba Trung | F71: TCH | G71: Flagship | H71: Shophouse | I71: Completed | J71: Not Planned | K71: In Progress | P71: In Progress
A72: SS | B72: TCH0071 | C72: 1011701 | D72: TCH HCM 258 Nguyen Van Luong | F72: TCH | G72: Reno | H72: Shophouse | I72: Completed | J72: Not Planned | K72: Completed | L72: 46068 | M72: 46027 | N72: 46068 | O72: 1 | P72: Completed
A73: SS | B73: TCH0072 | C73: 1010306 | D73: TCH HCM 223 Vo Van Tan | E73: nhà thầu Tân Sao Mộc không đảm bảo tiến độ, ảnh hưởng đến tiến độ chung | F73: TCH | G73: Reno | H73: Shophouse | I73: Completed | J73: Completed | K73: Completed | L73: 46054 | M73: 46020 | N73: 46061 | O73: 1 | P73: Completed
A74: SS | B74: TCH0073 | C74: 1010602 | D74: TCH HCM 1056 Hau Giang | E74: ĐTXD thông báo thầu 16/3, họp kickoff sẽ báo lại tiến độ | F74: TCH | G74: Reno | H74: Shophouse | I74: Completed | J74: Completed | K74: Completed | L74: 46139 | O74: 0 | P74: In Progress
A75: SS | B75: TCH0074 | C75: 1011406 | D75: TCH HCM 184 To Hieu | F75: TCH | G75: Cosmetic | H75: Shophouse | I75: Completed | J75: Not Planned | K75: Completed | L75: 46065 | M75: 46035 | N75: 46065 | O75: 1 | P75: Completed
A76: NS | B76: TCH0075 | C76: 2010306 | D76: TCH HNI 02 Ho Tung Mau | F76: TCH | G76: Reno | I76: Completed | J76: Completed | K76: Completed | L76: 45998 | M76: 45976 | N76: 45998 | O76: 1 | P76: Completed
A77: SS | B77: TCH0076 | C77: 1011905 | D77: TCH HCM 116 To Ngoc Van | E77: ĐTXD thông báo 17/1/26, đã họp kickoff chờ báo lại tiến độ | F77: TCH | G77: Cosmetic | H77: Shophouse | I77: Completed | J77: Completed | K77: Completed | L77: 46067 | M77: 46049 | N77: 46067 | O77: 1 | P77: Completed
A78: SS | B78: TCH0077 | C78: 1010708 | D78: TCH HCM R1-72 Khu R20 Sky Garden | F78: TCH & FC | G78: Reno | I78: Completed | J78: Completed | K78: Completed | L78: 46064 | M78: 46027 | N78: 46060 | O78: 1 | P78: Completed
A79: SS | B79: TCH0078 | C79: 1011405 | D79: TCH HCM 46 Le Thiet | F79: TCH | G79: Cosmetic | H79: Shophouse | I79: Completed | J79: Completed | K79: Completed | L79: 46038 | M79: 46013 | N79: 46037 | O79: 1 | P79: Completed
A80: SS | B80: TCH0079 | C80: TCHNEW004 | D80: TCH Mạc Đĩnh Chi | G80: Reno | H80: Shophouse | I80: Completed | J80: Completed | K80: Completed | L80: 46060 | M80: 46028 | N80: 46060 | O80: 1 | P80: Completed
A81: SS | B81: TCH0080 | C81: 4050101 | D81: TCH Đà Lạt | F81: TCH | G81: Flagship | H81: Shophouse | I81: Completed | J81: Completed | K81: Completed | L81: 46004 | M81: 45950 | N81: 46002 | O81: 1 | P81: Completed
A82: NS | B82: TCH0081 | C82: 6060102 | D82: TCH Toko Bắc Ninh | F82: TCH | G82: New | I82: Completed | J82: Completed | K82: Completed | O82: 1 | P82: Completed
A83: NS | B83: TCH0082 | C83: TCHNEW002 | D83: The Coffee House Goldmark Hồ Tùng Mậu | F83: TCH | G83: New | H83: Chân đế | I83: Completed | J83: Completed | K83: Cancelled | P83: Cancelled
A84: SS | B84: TCH0083 | C84: TCHNEW003 | D84: TCH Nguyễn Tri Phương | E84: thi công 2 giai đoạn, tổng tiến độ 36 ngày bao gồm nghỉ tết | F84: TCH | G84: Reno | I84: Completed | K84: Completed | L84: 46081 | M84: 46044 | N84: 46081 | O84: 1 | P84: Completed
A85: SS | B85: TCH0084 | C85: 1010906 | D85: TCH Grand Park Q9 | E85: BQL yêu cầu ngừng thi công từ 13/3 tới hôm nay 19/3 vẫn chưa cho thi công lại. Lý do: Chưa duyệt xong hồ sơ PCCC. Ngày 18/03 TCB đã gửi hồ sơ PCCC của TCB và TCH cho BQL, đang chờ BQL phản hồi để GGG vào thi công. | F85: TCH | G85: New | K85: Completed | L85: 46122 | M85: 46091 | O85: 0.05 | P85: In Progress
A86: NS | B86: TCH0085 | C86: 2010409 | D86: TCH Peal View Hoàng Câu | F86: TCH | G86: Reno | I86: Completed | J86: Completed | K86: Completed | L86: 45952 | M86: 46093 | N86: 45952 | O86: 1 | P86: Completed
A87: SS | B87: TCH0086 | C87: 1011001 | D87: TCH 3 thang 2 Q11 | E87: Mở mới | F87: TCH | G87: New | H87: Shophouse
A88: SS | B88: TCH0087 | C88: 4030102 | D88: TCH GOLDCOAST NHA TRANG | G88: New | I88: Completed | J88: Completed | K88: Completed | L88: 46128 | M88: 46093 | O88: 0.1 | P88: In Progress
B89: TCH0088 | D89: TCH TRƯƠNG CÔNG ĐỊNH
B90: TCH0089 | D90: TCH EZY BIÊN HÒA ĐỒNG NAI
B91: TCH0090 | D91: TCH Vạn Hạnh Mall | E91: Đề xuất outsource thiết kế | H91: Mall | I91: In Progress
B92: TCH0091 | D92: TCH Hoàng Văn Thái | E92: Đề xuất outsource thiết kế | I92: In Progress
B93: TCH0092 | D93: TCH Ngô Tất Tố | E93: Đề xuất outsource thiết kế | I93: In Progress
B94: TCH0093 | D94: TCH Nguyễn Văn Thương | E94: Đề xuất outsource thiết kế. BU kỳ vọng thi công trong tháng 4/2026 | I94: In Progress
B95: TCH0094 | C95: 10IP4838 | D95: TCH Lê Thái Tổ | E95: Mặt tiền. Bắt đầu từ 2025 | G95: Cosmetic | H95: Shophouse | I95: In Progress
A96: NS | B96: DA0128 | C96: 10DN4929 | D96: Dao Niu Guo Lê Đức Thọ | F96: Dao Niu Guo | G96: Convert | H96: Chân đế | I96: Completed | J96: Completed | K96: Completed | P96: Completed
A97: SS | B97: DA0005 | C97: 30DN4959 | D97: Dao Niu Guo Tân Phú | F97: Dao Niu Guo | G97: Convert | H97: Mall | I97: Completed | J97: On Hold | K97: Not Planned | P97: Not Planned
A98: SS | B98: DA0006 | C98: 30DN4960 | D98: Dao Niu Guo Diamond Plaza | F98: Dao Niu Guo | G98: Convert | H98: Mall | I98: Completed | J98: Completed | K98: Completed | L98: 46014 | M98: 45986 | N98: 46014 | O98: 1 | P98: Completed
A99: SS | B99: DA0007 | C99: 30DN4958 | D99: Dao Niu Guo Vạn Hạnh Mall | F99: Dao Niu Guo | G99: Convert | H99: Mall | I99: Completed | J99: Completed | K99: Completed | L99: 46014 | M99: 45989 | N99: 46014 | O99: 1 | P99: Completed
A100: SS | B100: DA0008 | D100: Dao Niu Guo Trương Công Định | E100: Convert từ Cloud Pot | F100: Dao Niu Guo | G100: Convert | H100: Shophouse | I100: On Hold | J100: Not Planned | K100: Not Planned | P100: Not Planned
...

Sheet Sheet3
C3: Master hiện tại
C4: Plan NSO theo budget - code budget lấy theo budget - code PC lookup sang file tracking CAPEX

Sheet Plan 2026
A1: ID | B1: Code Budget | C1: Tên brand | D1: BU See | E1: Năm offer MB | F1: Quý offer MB | G1: Tháng offer MB | H1: Tháng Khai trương dự kiến | I1: Tháng Khai trương thực tế | J1: Vùng | K1: Miền | L1: Tỉnh, TP | M1: Mã tỉnh 2024 | N1: Quận, huyện | O1: Phường, xã | P1: Trục đường chính | Q1: Loại hình | R1: Mặt tiền (m) | S1: Mặt tiền (chuẩn hóa) | T1: Diện tích (m2) | U1: Diện tích (chuẩn hóa) | V1: Số lượng site plan | W1: Plan/out of plan | X1: Tên mall/site | Y1: Tên mall (chuẩn hóa) | Z1: Giá thuê lấy từ std format | AA1: Giá thuê mong muốn | AB1: New/Convert/Share | AC1: Tình trạng | AD1: Ngày ký HĐ | AE1: Count | AF1: Ghi chú | AG1: Phường tự thêm | AH1: Viết tắt brand | AI1: Date | AJ1: Tháng offer | AK1: Address | AL1: Địa chỉ đầy đủ | AM1: Mã phường 2024 | AN1: Brand and Type format | AO1: Key | AP1: Mật độ tầng lớp tiêu dùng người/km2 | AQ1: Ranking phường theo tỉnh 2024 | AR1: Ranking phường toàn quốc 2024 | AS1: Số lượng cửa hàng hoạt động | AT1: Ranking theo brands | AU1: Daily Sales forecast (mil) - NW | AV1: Giá thuê | AW1: Tên site
A2: 1 | B2: 30GGNEW64 | C2: Gogi House | D2: Võ Đang Nhị Hiệp Trần Tuấn Sĩ Lương Anh Lộc Võ Hoàng Dũng Nguyễn Thị Phượng | E2: 2026 | F2: 3 | G2: 8 | H2: 12 | J2: SBU.MN | K2: Nam | L2: An Giang | M2: VNM.1_1 | N2: Châu Đốc | O2: Châu Phú B | Q2: Shophouse | R2: 8 | S2: 6 - 8 | T2: 220 - 240 | U2: 200 - 300 | V2: 1 | W2: UT1 | X2: Trưng Nữ Vương-Châu Đốc-AG | Z2: - | AB2: New | AC2: Reject | AE2: 0 | AF2: Đất nông nghiệp, đang phải tìm site mới | AH2: GG | AI2: 46235 | AJ2: 8 | AK2: Châu Phú B, Châu Đốc, An Giang | AL2: Châu Phú B, Châu Đốc, An Giang | AM2: VNM.1.3.2_1 | AN2: Gogi House Shophouse | AO2: Gogi House|Châu Phú B, Châu Đốc, An Giang | AP2: 580 | AQ2: 15/156 | AR2: 1360/11159 | AS2: 144 | AT2: 139/144 | AW2: =Plan_2026[[#This Row],[Tên brand]]&" "&Plan_2026[[#This Row],[Trục đường chính]]&Plan_2026[[#This Row],[Tên mall (chuẩn hóa)]]&Plan_2026[[#This Row],[Địa chỉ đầy đủ]] -> Gogi House Châu Phú B, Châu Đốc, An Giang
A3: 2 | B3: 30CDNOBUD2 | C3: CloudPot | D3: Lê Thị Như Bích | E3: 2026 | F3: 3 | G3: 7 | H3: 11 | J3: SBU.MN | K3: Nam | L3: An Giang | M3: VNM.1_1 | N3: Long Xuyên | O3: Mỹ Bình | P3: Số 1242, Đường Trần Hưng Đạo | Q3: Mall | R3: 6 | S3: <= 6 | T3: 200 - 240 | U3: 200 - 300 | V3: 1 | W3: UT2 | X3: Vincom An Giang | Y3: Vincom Plaza Long Xuyên | Z3: 180 | AB3: New | AC3: Chưa có | AE3: 0 | AF3: NWS có sẽ offer | AH3: CD | AI3: 46204 | AJ3: 7 | AK3: Mỹ Bình, Long Xuyên, An Giang | AL3: Số 1242, Đường Trần Hưng Đạo, Mỹ Bình, Long Xuyên, An Giang | AM3: VNM.1.6.4_1 | AN3: CloudPot Mall | AO3: CloudPot|Vincom Plaza Long Xuyên | AP3: 5022 | AQ3: 4/156 | AR3: 511/11159 | AS3: 17 | AT3: 13/17 | AW3: =Plan_2026[[#This Row],[Tên brand]]&" "&Plan_2026[[#This Row],[Trục đường chính]]&Plan_2026[[#This Row],[Tên mall (chuẩn hóa)]]&Plan_2026[[#This Row],[Địa chỉ đầy đủ]] -> CloudPot Số 1242, Đường Trần Hưng ĐạoVincom Plaza Long XuyênSố 1242, Đường Trần Hưng Đạo, Mỹ Bình, Long Xuyên, An Giang
A4: 3 | B4: 30SSNOBUD01 | C4: Isushi | D4: Nguyễn Thế Nguyên Nguyễn Thị Kim Luyện | E4: 2026 | F4: 3 | G4: 7 | H4: 11 | J4: SBU.MN | K4: Nam | L4: An Giang | M4: VNM.1_1 | N4: Long Xuyên | O4: Mỹ Bình | P4: 1242 Trần Hưng Đạo | Q4: Mall | R4: 8 - 12 | S4: 8 - 12 | T4: 200 - 300 | U4: 200 - 300 | V4: 1 | W4: UT2 | X4: Vincom Plaza Long Xuyên | Y4: Vincom Plaza Long Xuyên | Z4: 300 | AB4: New | AC4: Chưa có | AE4: 0 | AH4: SS | AI4: 46204 | AJ4: 7 | AK4: Mỹ Bình, Long Xuyên, An Giang | AL4: 1242 Trần Hưng Đạo, Mỹ Bình, Long Xuyên, An Giang | AM4: VNM.1.6.4_1 | AN4: Isushi Mall | AO4: Isushi|Vincom Plaza Long Xuyên | AP4: 5022 | AQ4: 4/156 | AR4: 511/11159 | AS4: 25 | AT4: 17/25 | AW4: =Plan_2026[[#This Row],[Tên brand]]&" "&Plan_2026[[#This Row],[Trục đường chính]]&Plan_2026[[#This Row],[Tên mall (chuẩn hóa)]]&Plan_2026[[#This Row],[Địa chỉ đầy đủ]] -> Isushi 1242 Trần Hưng ĐạoVincom Plaza Long Xuyên1242 Trần Hưng Đạo, Mỹ Bình, Long Xuyên, An Giang
A5: 377 | B5: 30DNNOBUD06 | C5: Dao Niu Guo | D5: Lê Thị Như Bích | E5: 2026 | F5: 1 | G5: 2 | H5: 6 | J5: SBU.MN | K5: Nam | L5: Bà Rịa - Vũng Tàu | M5: VNM.7_1 | N5: Vũng Tàu | O5: Phường 8 | P5: 251 – 251A Thống Nhất Mới. | Q5: Shophouse | R5: 8 - 12 | S5: 8 - 12 | T5: 300 | U5: 300 - 500 | V5: 1 | W5: UT2 | Z5: 160 | AB5: Convert | AC5: Đã ký | AE5: 1 | AF5: Convert từ Kpub | AH5: DN | AI5: 46054 | AJ5: 2 | AK5: Phường 8, Vũng Tàu, Bà Rịa - Vũng Tàu | AM5: VNM.7.6.12_1 | AN5: Dao Niu Guo Shophouse | AO5: Dao Niu Guo|Phường 8, Vũng Tàu, Bà Rịa - Vũng Tàu | AP5: 7919 | AQ5: 4/82 | AR5: 359/11159 | AS5: 6 | AT5: 4/6 | AW5: =Plan_2026[[#This Row],[Tên brand]]&" "&Plan_2026[[#This Row],[Trục đường chính]]&Plan_2026[[#This Row],[Tên mall (chuẩn hóa)]]&Plan_2026[[#This Row],[Địa chỉ đầy đủ]] -> Dao Niu Guo 251 – 251A Thống Nhất Mới.
A6: 4 | B6: 10MWNEW18 | C6: Manwah | D6: Nguyễn Tuấn Dũng | E6: 2025 | F6: 4 | G6: 10 | H6: 2 | I6: 2 | J6: SBU.MB | K6: Bắc | L6: Bắc Giang | M6: VNM.3_1 | N6: Bắc Giang | O6: Ngô Quyền | Q6: Shophouse | R6: 8 - 12 | S6: 8 - 12 | T6: 200 - 300 | U6: 200 - 300 | V6: 1 | W6: UT1 | Z6: 200 | AB6: Convert | AC6: Hủy bỏ | AE6: 0 | AF6: Convert từ Hutong | AH6: MW | AI6: 45931 | AJ6: 10 | AK6: Ngô Quyền, Bắc Giang, Bắc Giang | AL6: Ngô Quyền, Bắc Giang, Bắc Giang | AM6: VNM.3.1.8_1 | AN6: Manwah Shophouse | AO6: Manwah|Ngô Quyền, Bắc Giang, Bắc Giang | AP6: 8350 | AQ6: 1/232 | AR6: 344/11159 | AS6: 55 | AT6: 30/55 | AW6: =Plan_2026[[#This Row],[Tên brand]]&" "&Plan_2026[[#This Row],[Trục đường chính]]&Plan_2026[[#This Row],[Tên mall (chuẩn hóa)]]&Plan_2026[[#This Row],[Địa chỉ đầy đủ]] -> Manwah Ngô Quyền, Bắc Giang, Bắc Giang
A7: 5 | B7: TCHNEW066 | C7: The Coffee House | D7: Nguyễn Thị Thanh | E7: 2026 | F7: 2 | G7: 6 | H7: 10 | J7: SBU.MB | K7: Bắc | L7: Bắc Giang | M7: VNM.3_1 | N7: Bắc Giang | O7: Ngô Quyền | P7: Ngô Gia Tự, Hùng Vương | Q7: Shophouse | R7: 8 - 12 | S7: 8 - 12 | T7: 150 - 200 | U7: 150 - 200 | V7: 1 | W7: UT1 | Z7: 132 | AB7: New | AC7: Chưa có | AE7: 0 | AF7: Khu vực TT TP Ngô Gia Tự, Hùng Vương (shop house, chân đế, mall) | AH7: TCH | AI7: 46174 | AJ7: 6 | AK7: Ngô Quyền, Bắc Giang, Bắc Giang | AL7: Ngô Gia Tự, Hùng Vương, Ngô Quyền, Bắc Giang, Bắc Giang | AM7: VNM.3.1.8_1 | AN7: The Coffee House Shophouse | AO7: The Coffee House|Ngô Quyền, Bắc Giang, Bắc Giang | AP7: 8350 | AQ7: 1/232 | AR7: 344/11159 | AS7: 81 | AT7: 52/81 | AW7: =Plan_2026[[#This Row],[Tên brand]]&" "&Plan_2026[[#This Row],[Trục đường chính]]&Plan_2026[[#This Row],[Tên mall (chuẩn hóa)]]&Plan_2026[[#This Row],[Địa chỉ đầy đủ]] -> The Coffee House Ngô Gia Tự, Hùng VươngNgô Gia Tự, Hùng Vương, Ngô Quyền, Bắc Giang, Bắc Giang
A8: 6 | B8: TCHNEW058 | C8: The Coffee House | D8: Nguyễn Thị Thanh | E8: 2026 | F8: 2 | G8: 5 | H8: 9 | J8: SBU.MB | K8: Bắc | L8: Bắc Ninh | M8: VNM.5_1 | N8: Từ Sơn | O8: Đông Ngàn | Q8: Mall | R8: 6 - 8 | S8: 6 - 8 | T8: 100 - 150 | U8: 100 - 150 | V8: 1 | W8: UT1 | X8: Go Từ Sơn | Y8: Go! Từ Sơn | Z8: 132 | AB8: New | AC8: Chưa có | AE8: 0 | AH8: TCH | AI8: 46143 | AJ8: 5 | AK8: Đông Ngàn, Từ Sơn, Bắc Ninh | AL8: Đông Ngàn, Từ Sơn, Bắc Ninh | AM8: VNM.5.5.5_1 | AN8: The Coffee House Mall | AO8: The Coffee House|Go! Từ Sơn | AP8: 3923 | AQ8: 6/126 | AR8: 608/11159 | AS8: 81 | AT8: 65/81 | AW8: =Plan_2026[[#This Row],[Tên brand]]&" "&Plan_2026[[#This Row],[Trục đường chính]]&Plan_2026[[#This Row],[Tên mall (chuẩn hóa)]]&Plan_2026[[#This Row],[Địa chỉ đầy đủ]] -> The Coffee House Go! Từ SơnĐông Ngàn, Từ Sơn, Bắc Ninh
A9: 7 | B9: TCHNEW005 | C9: The Coffee House | D9: Nguyễn Thị Thanh | E9: 2025 | F9: 4 | G9: 12 | H9: 4 | J9: SBU.MB | K9: Bắc | L9: Bắc Ninh | M9: VNM.5_1 | N9: Bắc Ninh | O9: Đại Phúc | P9: Lý Thái Tổ (gần Vincom) | Q9: Chân đế | R9: 6 - 8 | S9: 6 - 8 | T9: 100 - 150 | U9: 100 - 150 | V9: 1 | W9: UT2 | Z9: 132 | AB9: New | AC9: Chưa có | AE9: 0 | AH9: TCH | AI9: 45992 | AJ9: 12 | AK9: Đại Phúc, Bắc Ninh, Bắc Ninh | AL9: Lý Thái Tổ (gần Vincom), Đại Phúc, Bắc Ninh, Bắc Ninh | AM9: VNM.5.1.1_1 | AN9: The Coffee House Chân đế | AO9: The Coffee House|Đại Phúc, Bắc Ninh, Bắc Ninh | AP9: 2191 | AQ9: 9/126 | AR9: 803/11159 | AS9: 81 | AT9: 73/81 | AW9: =Plan_2026[[#This Row],[Tên brand]]&" "&Plan_2026[[#This Row],[Trục đường chính]]&Plan_2026[[#This Row],[Tên mall (chuẩn hóa)]]&Plan_2026[[#This Row],[Địa chỉ đầy đủ]] -> The Coffee House Lý Thái Tổ (gần Vincom)Lý Thái Tổ (gần Vincom), Đại Phúc, Bắc Ninh, Bắc Ninh
A10: 8 | B10: 10KKNOBUD01 | C10: Kichi Kichi | D10: Phan Văn Thủy Hà Mỹ Phượng | E10: 2026 | F10: 3 | G10: 8 | H10: 12 | J10: SBU.MB | K10: Bắc | L10: Bắc Ninh | M10: VNM.5_1 | N10: Bắc Ninh | O10: Tiền An | Q10: Chân đế | R10: 8 - 12 | S10: 8 - 12 | T10: 180 - 200 | U10: 150 - 200 | V10: 1 | W10: UT2 | Z10: - | AB10: New | AC10: Chưa có | AE10: 0 | AF10: Tránh khu Ng Đăng Đạo | AH10: KK | AI10: 46235 | AJ10: 8 | AK10: Tiền An, Bắc Ninh, Bắc Ninh | AL10: Tiền An, Bắc Ninh, Bắc Ninh | AM10: VNM.5.1.14_1 | AN10: Kichi Kichi Chân đế | AO10: Kichi Kichi|Tiền An, Bắc Ninh, Bắc Ninh | AP10: 10189 | AQ10: 1/126 | AR10: 287/11159 | AS10: 107 | AT10: 36/107 | AW10: =Plan_2026[[#This Row],[Tên brand]]&" "&Plan_2026[[#This Row],[Trục đường chính]]&Plan_2026[[#This Row],[Tên mall (chuẩn hóa)]]&Plan_2026[[#This Row],[Địa chỉ đầy đủ]] -> Kichi Kichi Tiền An, Bắc Ninh, Bắc Ninh
A11: 376 | B11: 10DNNOBUD07 | C11: Dao Niu Guo | D11: Nguyễn Ngọc Hà | E11: 2026 | F11: 1 | G11: 2 | H11: 6 | J11: SBU.MB | K11: Bắc | L11: Bắc Ninh | M11: VNM.5_1 | N11: Bắc Ninh | O11: Tiền An | Q11: Shophouse | R11: 8 - 12 | S11: 8 - 12 | T11: 300 | U11: 300 - 500 | V11: 1 | W11: UT2 | Z11: 160 | AB11: Convert | AC11: Đã ký | AE11: 1 | AF11: Convert từ Shogun | AH11: DN | AI11: 46054 | AJ11: 2 | AK11: Tiền An, Bắc Ninh, Bắc Ninh | AM11: VNM.5.1.14_1 | AN11: Dao Niu Guo Shophouse | AO11: Dao Niu Guo|Tiền An, Bắc Ninh, Bắc Ninh | AP11: 10189 | AQ11: 1/126 | AR11: 287/11159 | AS11: 6 | AT11: 3/6 | AW11: =Plan_2026[[#This Row],[Tên brand]]&" "&Plan_2026[[#This Row],[Trục đường chính]]&Plan_2026[[#This Row],[Tên mall (chuẩn hóa)]]&Plan_2026[[#This Row],[Địa chỉ đầy đủ]] -> Dao Niu Guo
A12: 9 | B12: TCHNOBUD02 | C12: The Coffee House | D12: Phạm Thanh Trúc | E12: 2026 | F12: 3 | G12: 7 | H12: 11 | J12: SBU.MN | K12: Nam | L12: Bình Định | M12: VNM.8_1 | N12: Qui Nhơn | O12: Lê Lợi | P12: Nguyễn Tất Thành/Nguyễn Trãi/Lê Lợi | Q12: Shophouse | R12: 8 - 12 | S12: 8 - 12 | T12: 150 - 200 | U12: 150 - 200 | V12: 1 | W12: UT2 | Z12: 132 | AB12: New | AC12: Chưa có | AE12: 0 | AH12: TCH | AI12: 46204 | AJ12: 7 | AK12: Lê Lợi, Qui Nhơn, Bình Định | AL12: Nguyễn Tất Thành/Nguyễn Trãi/Lê Lợi, Lê Lợi, Qui Nhơn, Bình Định | AM12: VNM.8.7.6_1 | AN12: The Coffee House Shophouse | AO12: The Coffee House|Lê Lợi, Qui Nhơn, Bình Định | AP12: 8740 | AQ12: 2/159 | AR12: 334/11159 | AS12: 81 | AT12: 52/81 | AW12: =Plan_2026[[#This Row],[Tên brand]]&" "&Plan_2026[[#This Row],[Trục đường chính]]&Plan_2026[[#This Row],[Tên mall (chuẩn hóa)]]&Plan_2026[[#This Row],[Địa chỉ đầy đủ]] -> The Coffee House Nguyễn Tất Thành/Nguyễn Trãi/Lê LợiNguyễn Tất Thành/Nguyễn Trãi/Lê Lợi, Lê Lợi, Qui Nhơn, Bình Định
A13: 10 | B13: 30WYNOBUD05 | C13: Wow!Yakiniku | D13: Bùi Hồng Gấm | E13: 2026 | F13: 2 | G13: 4 | H13: 8 | J13: SBU.MN | K13: Nam | L13: Bình Dương | M13: VNM.9_1 | N13: Thuận An | O13: Thuận Giao | P13: Thuận Giao | Q13: Mall | R13: 8 - 12 | S13: 8 - 12 | T13: 150 - 200 | U13: 150 - 200 | V13: 1 | W13: UT2 | X13: Aeon Bình Dương | Y13: Aeon Mall Bình Dương Canary | Z13: - | AB13: Share | AC13: Đã ký | AE13: 1 | AF13: Share với Sumo check lại thời gian tái ký gia hạn sửa chữa, áp concept | AH13: WY | AI13: 46113 | AJ13: 4 | AK13: Thuận Giao, Thuận An, Bình Dương | AL13: Thuận Giao, Thuận Giao, Thuận An, Bình Dương | AM13: VNM.9.9.9_1 | AN13: Wow!Yakiniku Mall | AO13: Wow!Yakiniku|Aeon Mall Bình Dương Canary | AP13: 928 | AQ13: 23/91 | AR13: 1111/11159 | AS13: 2 | AT13: 3/2 | AW13: =Plan_2026[[#This Row],[Tên brand]]&" "&Plan_2026[[#This Row],[Trục đường chính]]&Plan_2026[[#This Row],[Tên mall (chuẩn hóa)]]&Plan_2026[[#This Row],[Địa chỉ đầy đủ]] -> Wow!Yakiniku Thuận GiaoAeon Mall Bình Dương CanaryThuận Giao, Thuận Giao, Thuận An, Bình Dương
A14: 11 | B14: 30MWNOBUD01 | C14: Manwah | D14: Nguyễn Văn Bạch Long | E14: 2026 | F14: 1 | G14: 1 | H14: 5 | J14: SBU.MN | K14: Nam | L14: Bình Dương | M14: VNM.9_1 | N14: Dĩ An | O14: Đông Hòa | P14: Thống Nhất | Q14: Chân đế | R14: 8 - 12 | S14: 8 - 12 | T14: 200 - 300 | U14: 200 - 300 | V14: 1 | W14: UT1 | Z14: 200 | AB14: New | AC14: Chưa có | AE14: 0 | AF14: Phức hợp Bcon Làng đại hoc - New building | AH14: MW | AI14: 46023 | AJ14: 1 | AK14: Đông Hòa, Dĩ An, Bình Dương | AL14: Thống Nhất, Đông Hòa, Dĩ An, Bình Dương | AM14: VNM.9.5.5_1 | AN14: Manwah Chân đế | AO14: Manwah|Đông Hòa, Dĩ An, Bình Dương | AP14: 2696 | AQ14: 8/91 | AR14: 722/11159 | AS14: 55 | AT14: 44/55 | AW14: =Plan_2026[[#This Row],[Tên brand]]&" "&Plan_2026[[#This Row],[Trục đường chính]]&Plan_2026[[#This Row],[Tên mall (chuẩn hóa)]]&Plan_2026[[#This Row],[Địa chỉ đầy đủ]] -> Manwah Thống NhấtThống Nhất, Đông Hòa, Dĩ An, Bình Dương
A15: 12 | B15: 30YT4995 | C15: Yutang | D15: Võ Hoàng Dũng | E15: 2025 | F15: 4 | G15: 10 | H15: 2 | J15: SBU.MN | K15: Nam | L15: Bình Dương | M15: VNM.9_1 | N15: Dĩ An | O15: Đông Hòa | P15: Thống Nhất | Q15: Chân đế | R15: 8 | S15: 6 - 8 | T15: 120 - 150 | U15: 100 - 150 | V15: 1 | W15: UT2 | X15: Bcons Bình Dương | Z15: - | AB15: New | AC15: Đã ký | AE15: 1 | AH15: YT | AI15: 45931 | AJ15: 10 | AK15: Đông Hòa, Dĩ An, Bình Dương | AL15: Thống Nhất, Đông Hòa, Dĩ An, Bình Dương | AM15: VNM.9.5.5_1 | AN15: Yutang Chân đế | AO15: Yutang|Đông Hòa, Dĩ An, Bình Dương | AP15: 2696 | AQ15: 8/91 | AR15: 722/11159 | AS15: 10 | AT15: 6/10 | AW15: =Plan_2026[[#This Row],[Tên brand]]&" "&Plan_2026[[#This Row],[Trục đường chính]]&Plan_2026[[#This Row],[Tên mall (chuẩn hóa)]]&Plan_2026[[#This Row],[Địa chỉ đầy đủ]] -> Yutang Thống NhấtThống Nhất, Đông Hòa, Dĩ An, Bình Dương
A16: 13 | B16: TCHNOBUD03 | C16: The Coffee House | D16: Phạm Thanh Trúc | E16: 2026 | F16: 3 | G16: 7 | H16: 11 | J16: SBU.MN | K16: Nam | L16: Bình Dương | M16: VNM.9_1 | N16: Dĩ An | O16: Đông Hòa | P16: Đường Thống Nhất | Q16: Shophouse | R16: 8 - 12 | S16: 8 - 12 | T16: 150 - 200 | U16: 150 - 200 | V16: 1 | W16: UT2 | X16: Bcons Bình Dương | Z16: 132 | AB16: New | AC16: Chưa có | AE16: 0 | AF16: Cuối năm 2026 mới lấy được site site: 50 tr - 130m2 | AH16: TCH | AI16: 46204 | AJ16: 7 | AK16: Đông Hòa, Dĩ An, Bình Dương | AL16: Đường Thống Nhất, Đông Hòa, Dĩ An, Bình Dương | AM16: VNM.9.5.5_1 | AN16: The Coffee House Shophouse | AO16: The Coffee House|Đông Hòa, Dĩ An, Bình Dương | AP16: 2696 | AQ16: 8/91 | AR16: 722/11159 | AS16: 81 | AT16: 67/81 | AW16: =Plan_2026[[#This Row],[Tên brand]]&" "&Plan_2026[[#This Row],[Trục đường chính]]&Plan_2026[[#This Row],[Tên mall (chuẩn hóa)]]&Plan_2026[[#This Row],[Địa chỉ đầy đủ]] -> The Coffee House Đường Thống NhấtĐường Thống Nhất, Đông Hòa, Dĩ An, Bình Dương
A17: 14 | B17: 30GGNOBUD07 | C17: Gogi House | D17: Võ Đang Nhị Hiệp Trần Tuấn Sĩ Lương Anh Lộc Võ Hoàng Dũng Nguyễn Thị Phượng | E17: 2026 | F17: 3 | G17: 7 | H17: 11 | J17: SBU.MN | K17: Nam | L17: Bình Dương | M17: VNM.9_1 | N17: Tân Uyên | O17: Khánh Bình | Q17: Shophouse | R17: 8 | S17: 6 - 8 | T17: 200-220 | U17: 200 - 300 | V17: 1 | W17: UT2 | X17: Đường 13 Tân Uyên Bình Dương | Z17: - | AA17: 40-60tr | AB17: New | AC17: Reject | AE17: 0 | AF17: Chê MB nhỏ, muốn đi chung vs Gogi, KK chung Thủ Dầu Một, giáp Bình Chuẩn, Tân Phúc Khanh mặt tiền rộng, bãi đỗ xe MB kết hợp vs Gogi, Kichi, thành cụm | AH17: GG | AI17: 46204 | AJ17: 7 | AK17: Khánh Bình, Tân Uyên, Bình Dương | AL17: Khánh Bình, Tân Uyên, Bình Dương | AM17: VNM.9.7.3_1 | AN17: Gogi House Shophouse | AO17: Gogi House|Khánh Bình, Tân Uyên, Bình Dương | AP17: 175 | AQ17: 46/91 | AR17: 2766/11159 | AS17: 144 | AT17: 145/144 | AW17: =Plan_2026[[#This Row],[Tên brand]]&" "&Plan_2026[[#This Row],[Trục đường chính]]&Plan_2026[[#This Row],[Tên mall (chuẩn hóa)]]&Plan_2026[[#This Row],[Địa chỉ đầy đủ]] -> Gogi House Khánh Bình, Tân Uyên, Bình Dương
A18: 15 | B18: 30KKNEW13 | C18: Kichi Kichi | D18: Phan Văn Thủy Hà Mỹ Phượng | E18: 2025 | F18: 4 | G18: 12 | H18: 4 | J18: SBU.MN | K18: Nam | L18: Bình Dương | M18: VNM.9_1 | N18: Tân Uyên | O18: Tân Phước Khánh | Q18: Shophouse | R18: 6 - 8 | S18: 6 - 8 | T18: 160 - 180 | U18: 200 - 300 | V18: 1 | W18: UT1 | Z18: - | AB18: New | AC18: Chưa có | AE18: 0 | AF18: mini | AG18: Tự thêm phường | AH18: KK | AI18: 45992 | AJ18: 12 | AK18: Tân Phước Khánh, Tân Uyên, Bình Dương | AL18: Tân Phước Khánh, Tân Uyên, Bình Dương | AM18: VNM.9.7.6_1 | AN18: Kichi Kichi Shophouse | AO18: Kichi Kichi|Tân Phước Khánh, Tân Uyên, Bình Dương | AP18: 742 | AQ18: 27/91 | AR18: 1225/11159 | AS18: 107 | AT18: 100/107 | AW18: =Plan_2026[[#This Row],[Tên brand]]&" "&Plan_2026[[#This Row],[Trục đường chính]]&Plan_2026[[#This Row],[Tên mall (chuẩn hóa)]]&Plan_2026[[#This Row],[Địa chỉ đầy đủ]] -> Kichi Kichi Tân Phước Khánh, Tân Uyên, Bình Dương
A19: 16 | B19: TCHNOBUD04 | C19: The Coffee House | D19: Phạm Thanh Trúc | E19: 2026 | F19: 1 | G19: 1 | H19: 5 | J19: SBU.MN | K19: Nam | L19: Bình Dương | M19: VNM.9_1 | N19: Thủ Dầu Một | O19: Hiệp Thành | Q19: Shophouse | R19: 8 - 12 | S19: 8 - 12 | T19: 150 - 200 | U19: 150 - 200 | V19: 1 | W19: UT1 | Z19: 132 | AB19: New | AC19: Chưa có | AE19: 0 | AG19: Tự thêm phường | AH19: TCH | AI19: 46023 | AJ19: 1 | AK19: Hiệp Thành, Thủ Dầu Một, Bình Dương | AL19: Hiệp Thành, Thủ Dầu Một, Bình Dương | AM19: VNM.9.8.5_1 | AN19: The Coffee House Shophouse | AO19: The Coffee House|Hiệp Thành, Thủ Dầu Một, Bình Dương | AP19: 5407 | AQ19: 2/91 | AR19: 482/11159 | AS19: 81 | AT19: 57/81 | AW19: =Plan_2026[[#This Row],[Tên brand]]&" "&Plan_2026[[#This Row],[Trục đường chính]]&Plan_2026[[#This Row],[Tên mall (chuẩn hóa)]]&Plan_2026[[#This Row],[Địa chỉ đầy đủ]] -> The Coffee House Hiệp Thành, Thủ Dầu Một, Bình Dương
A20: 17 | B20: 30KKNOBUD06 | C20: Kichi Kichi | D20: Phan Văn Thủy Hà Mỹ Phượng | E20: 2026 | F20: 3 | G20: 7 | H20: 11 | J20: SBU.MN | K20: Nam | L20: Bình Phước | M20: VNM.10_1 | N20: Đồng Xoài | O20: Tân Phú | Q20: Shophouse | R20: 8 - 12 | S20: 8 - 12 | T20: 200 | U20: 150 - 200 | V20: 1 | W20: UT2 | Z20: - | AB20: New | AC20: Chưa có | AE20: 0 | AG20: Tự thêm quận, phường | AH20: KK | AI20: 46204 | AJ20: 7 | AK20: Tân Phú, Đồng Xoài, Bình Phước | AL20: Tân Phú, Đồng Xoài, Bình Phước | AM20: VNM.10.7.3_1 | AN20: Kichi Kichi Shophouse | AO20: Kichi Kichi|Tân Phú, Đồng Xoài, Bình Phước | AP20: 1522 | AQ20: 1/111 | AR20: 937/11159 | AS20: 107 | AT20: 96/107 | AW20: =Plan_2026[[#This Row],[Tên brand]]&" "&Plan_2026[[#This Row],[Trục đường chính]]&Plan_2026[[#This Row],[Tên mall (chuẩn hóa)]]&Plan_2026[[#This Row],[Địa chỉ đầy đủ]] -> Kichi Kichi Tân Phú, Đồng Xoài, Bình Phước
A21: 18 | B21: 30SSNOBUD02 | C21: Isushi | D21: Nguyễn Thế Nguyên Nguyễn Thị Kim Luyện | E21: 2026 | F21: 3 | G21: 7 | H21: 11 | J21: SBU.MN | K21: Nam | L21: Cà Mau | M21: VNM.13_1 | N21: Cà Mau | O21: Phường 5 | Q21: Shophouse | R21: 8 - 12 | S21: 8 - 12 | T21: 200 - 300 | U21: 200 - 300 | V21: 1 | W21: UT2 | Z21: 300 | AB21: New | AC21: Chưa có | AE21: 0 | AF21: tính vào Sense City nhưng hiện đang full MB shophouse hoặc mall đều được | AH21: SS | AI21: 46204 | AJ21: 7 | AK21: Phường 5, Cà Mau, Cà Mau | AL21: Phường 5, Cà Mau, Cà Mau | AM21: VNM.13.1.9_1 | AN21: Isushi Shophouse | AO21: Isushi|Phường 5, Cà Mau, Cà Mau | AP21: 3830 | AQ21: 3/101 | AR21: 613/11159 | AS21: 25 | AT21: 20/25 | AW21: =Plan_2026[[#This Row],[Tên brand]]&" "&Plan_2026[[#This Row],[Trục đường chính]]&Plan_2026[[#This Row],[Tên mall (chuẩn hóa)]]&Plan_2026[[#This Row],[Địa chỉ đầy đủ]] -> Isushi Phường 5, Cà Mau, Cà Mau
A22: 19 | B22: 30MWNOBUD06 | C22: Manwah | D22: Nguyễn Văn Bạch Long | E22: 2025 | F22: 4 | G22: 10 | H22: 2 | J22: SBU.MN | K22: Nam | L22: Cà Mau | M22: VNM.13_1 | N22: Cà Mau | O22: Phường 5 | P22: Trần Hưng Đạo | Q22: Shophouse | R22: 8 - 12 | S22: 8 - 12 | T22: 200 - 300 | U22: 200 - 300 | V22: 1 | W22: UT2 | X22: 55 Trần Hưng Đạo-CM | Z22: 200 | AB22: New | AC22: Đang offer | AE22: 1 | AF22: Đang chờ BU Master khảo sát | AH22: MW | AI22: 45931 | AJ22: 10 | AK22: Phường 5, Cà Mau, Cà Mau | AL22: Trần Hưng Đạo, Phường 5, Cà Mau, Cà Mau | AM22: VNM.13.1.9_1 | AN22: Manwah Shophouse | AO22: Manwah|Phường 5, Cà Mau, Cà Mau | AP22: 3830 | AQ22: 3/101 | AR22: 613/11159 | AS22: 55 | AT22: 41/55 | AW22: =Plan_2026[[#This Row],[Tên brand]]&" "&Plan_2026[[#This Row],[Trục đường chính]]&Plan_2026[[#This Row],[Tên mall (chuẩn hóa)]]&Plan_2026[[#This Row],[Địa chỉ đầy đủ]] -> Manwah Trần Hưng ĐạoTrần Hưng Đạo, Phường 5, Cà Mau, Cà Mau
A23: 20 | B23: 30GGNOBUD08 | C23: Gogi House | D23: Võ Đang Nhị Hiệp Trần Tuấn Sĩ Lương Anh Lộc Võ Hoàng Dũng Nguyễn Thị Phượng | E23: 2026 | F23: 3 | G23: 7 | H23: 11 | J23: SBU.MN | K23: Nam | L23: Cần Thơ | M23: VNM.12_1 | N23: Ô Môn | O23: Châu Văn Liêm | Q23: Shophouse | R23: 8 | S23: 6 - 8 | T23: 220 - 240 | U23: 200 - 300 | V23: 1 | W23: UT2 | X23: Châu Văn Liêm, Ô Môn, Cần Thơ | Z23: - | AB23: New | AC23: Đang offer | AE23: 1 | AF23: Đang theo dõi tới tháng 6 hoặc cuối năm nay, bới bên hiện hữu vẫn đang KD | AH23: GG | AI23: 46204 | AJ23: 7 | AK23: Châu Văn Liêm, Ô Môn, Cần Thơ | AL23: Châu Văn Liêm, Ô Môn, Cần Thơ | AM23: VNM.12.5.1_1 | AN23: Gogi House Shophouse | AO23: Gogi House|Châu Văn Liêm, Ô Môn, Cần Thơ | AP23: 644 | AQ23: 22/85 | AR23: 1295/11159 | AS23: 144 | AT23: 138/144 | AW23: =Plan_2026[[#This Row],[Tên brand]]&" "&Plan_2026[[#This Row],[Trục đường chính]]&Plan_2026[[#This Row],[Tên mall (chuẩn hóa)]]&Plan_2026[[#This Row],[Địa chỉ đầy đủ]] -> Gogi House Châu Văn Liêm, Ô Môn, Cần Thơ
A24: 21 | B24: 30GGNEW10 | C24: Gogi House | D24: Võ Đang Nhị Hiệp Trần Tuấn Sĩ Lương Anh Lộc Võ Hoàng Dũng Nguyễn Thị Phượng | E24: 2026 | F24: 1 | G24: 2 | H24: 6 | J24: SBU.MN | K24: Nam | L24: Cần Thơ | M24: VNM.12_1 | N24: Bình Thuỷ | O24: Long Hòa | P24: Võ Văn Kiệt và Lê Phước Thọ | Q24: Mall | R24: 6 | S24: <= 6 | T24: 180 - 250 | U24: 200 - 300 | V24: 1 | W24: UT2 | X24: Aeon Mall Cần Thơ | Y24: Aeon Mall Cần Thơ | Z24: - | AB24: New | AC24: Chưa có | AE24: 0 | AF24: chưa xây xong năm 2027 | AH24: GG | AI24: 46054 | AJ24: 2 | AK24: Long Hòa, Bình Thuỷ, Cần Thơ | AL24: Võ Văn Kiệt và Lê Phước Thọ, Long Hòa, Bình Thuỷ, Cần Thơ | AM24: VNM.12.1.4_1 | AN24: Gogi House Mall | AO24: Gogi House|Aeon Mall Cần Thơ | AP24: 302 | AQ24: 25/85 | AR24: 1891/11159 | AS24: 144 | AT24: 143/144 | AW24: =Plan_2026[[#This Row],[Tên brand]]&" "&Plan_2026[[#This Row],[Trục đường chính]]&Plan_2026[[#This Row],[Tên mall (chuẩn hóa)]]&Plan_2026[[#This Row],[Địa chỉ đầy đủ]] -> Gogi House Võ Văn Kiệt và Lê Phước ThọAeon Mall Cần ThơVõ Văn Kiệt và Lê Phước Thọ, Long Hòa, Bình Thuỷ, Cần Thơ
A25: 22 | B25: 30YTNOBUD01 | C25: Yutang | D25: Võ Hoàng Dũng | E25: 2025 | F25: 4 | G25: 10 | H25: 2 | J25: SBU.MN | K25: Nam | L25: Cần Thơ | M25: VNM.12_1 | N25: Ninh Kiều | O25: An Phú | Q25: Shophouse | R25: 8 | S25: 6 - 8 | T25: 120 - 150 | U25: 100 - 150 | V25: 1 | W25: UT2 | Z25: - | AB25: Convert | AC25: Đã ký | AE25: 1 | AF25: Convert từ Hàng Cuốn Cần Thơ | AH25: YT | AI25: 45931 | AJ25: 10 | AK25: An Phú, Ninh Kiều, Cần Thơ | AL25: An Phú, Ninh Kiều, Cần Thơ | AM25: VNM.12.4.8_1 | AN25: Yutang Shophouse | AO25: Yutang|An Phú, Ninh Kiều, Cần Thơ | AP25: 12373 | AQ25: 2/85 | AR25: 241/11159 | AS25: 10 | AT25: 3/10 | AW25: =Plan_2026[[#This Row],[Tên brand]]&" "&Plan_2026[[#This Row],[Trục đường chính]]&Plan_2026[[#This Row],[Tên mall (chuẩn hóa)]]&Plan_2026[[#This Row],[Địa chỉ đầy đủ]] -> Yutang An Phú, Ninh Kiều, Cần Thơ
A26: 23 | B26: 30KKNOBUD04 | C26: Kichi Kichi | D26: Phan Văn Thủy Hà Mỹ Phượng | E26: 2026 | F26: 1 | G26: 1 | H26: 5 | J26: SBU.MN | K26: Nam | L26: Cần Thơ | M26: VNM.12_1 | N26: Ô Môn | O26: Châu Văn Liêm | Q26: Shophouse | R26: 6 - 8 | S26: 6 - 8 | T26: 160 - 180 | U26: 150 - 200 | V26: 1 | W26: UT2 | X26: Ô Môn, Cần Thơ | Z26: - | AB26: New | AC26: Đang offer | AE26: 1 | AF26: Giống GG, do bên thuê hiện tại chưa thoát ra | AG26: Tự thêm phường | AH26: KK | AI26: 46023 | AJ26: 1 | AK26: Châu Văn Liêm, Ô Môn, Cần Thơ | AL26: Châu Văn Liêm, Ô Môn, Cần Thơ | AM26: VNM.12.5.1_1 | AN26: Kichi Kichi Shophouse | AO26: Kichi Kichi|Châu Văn Liêm, Ô Môn, Cần Thơ | AP26: 644 | AQ26: 22/85 | AR26: 1295/11159 | AS26: 107 | AT26: 101/107 | AW26: =Plan_2026[[#This Row],[Tên brand]]&" "&Plan_2026[[#This Row],[Trục đường chính]]&Plan_2026[[#This Row],[Tên mall (chuẩn hóa)]]&Plan_2026[[#This Row],[Địa chỉ đầy đủ]] -> Kichi Kichi Châu Văn Liêm, Ô Môn, Cần Thơ
A27: 24 | B27: TCHNOBUD05 | C27: The Coffee House | D27: Phạm Thanh Trúc | E27: 2026 | F27: 1 | G27: 1 | H27: 5 | J27: SBU.MN | K27: Trung | L27: Đà Nẵng | M27: VNM.19_1 | N27: Thanh Khê | O27: Chính Gián | P27: Điện Biên Phủ (gần Aeon mall) | Q27: Shophouse | R27: 8 - 12 | S27: 8 - 12 | T27: 150 - 200 | U27: 150 - 200 | V27: 1 | W27: UT2 | Z27: 132 | AB27: New | AC27: Chưa có | AE27: 0 | AF27: khúc có AEON | AH27: TCH | AI27: 46023 | AJ27: 1 | AK27: Chính Gián, Thanh Khê, Đà Nẵng | AL27: Điện Biên Phủ (gần Aeon mall), Chính Gián, Thanh Khê, Đà Nẵng | AM27: VNM.19.7.2_1 | AN27: The Coffee House Shophouse | AO27: The Coffee House|Chính Gián, Thanh Khê, Đà Nẵng | AP27: 9351 | AQ27: 6/56 | AR27: 308/11159 | AS27: 81 | AT27: 48/81 | AW27: =Plan_2026[[#This Row],[Tên brand]]&" "&Plan_2026[[#This Row],[Trục đường chính]]&Plan_2026[[#This Row],[Tên mall (chuẩn hóa)]]&Plan_2026[[#This Row],[Địa chỉ đầy đủ]] -> The Coffee House Điện Biên Phủ (gần Aeon mall)Điện Biên Phủ (gần Aeon mall), Chính Gián, Thanh Khê, Đà Nẵng
A28: 25 | B28: 30CDNEW13 | C28: CloudPot | D28: Lê Thị Như Bích | E28: 2026 | F28: 3 | G28: 7 | H28: 11 | J28: SBU.MN | K28: Trung | L28: Đà Nẵng | M28: VNM.19_1 | N28: Thanh Khê | O28: Chính Gián | P28: 46 Điện Biên Phủ | Q28: Mall | R28: 6 | S28: <= 6 | T28: 200 - 240 | U28: 200 - 300 | V28: 1 | W28: UT1 | X28: Aeon Mall Đà Nẵng | Y28: Aeon Mall Đà Nẵng | Z28: 180 | AB28: New | AC28: Đã ký | AE28: 1 | AH28: CD | AI28: 46204 | AJ28: 7 | AK28: Chính Gián, Thanh Khê, Đà Nẵng | AL28: 46 Điện Biên Phủ, Chính Gián, Thanh Khê, Đà Nẵng | AM28: VNM.19.7.2_1 | AN28: CloudPot Mall | AO28: CloudPot|Aeon Mall Đà Nẵng | AP28: 9351 | AQ28: 6/56 | AR28: 308/11159 | AS28: 17 | AT28: 8/17 | AW28: =Plan_2026[[#This Row],[Tên brand]]&" "&Plan_2026[[#This Row],[Trục đường chính]]&Plan_2026[[#This Row],[Tên mall (chuẩn hóa)]]&Plan_2026[[#This Row],[Địa chỉ đầy đủ]] -> CloudPot 46 Điện Biên PhủAeon Mall Đà Nẵng46 Điện Biên Phủ, Chính Gián, Thanh Khê, Đà Nẵng
A29: 30 | B29: 30GGNEW43 | C29: Gogi House | D29: Phạm Tuấn Anh Dương Chí Cường Nguyễn Xuân Hóa Đặng Thanh Quang | E29: 2025 | F29: 4 | G29: 10 | H29: 2 | J29: SBU.MN | K29: Trung | L29: Đà Nẵng | M29: VNM.19_1 | N29: Liên Chiểu | O29: Hòa Khánh Nam | P29: Nguyễn Sinh Sắc | Q29: Mall | R29: 6 | S29: <= 6 | T29: 180 - 250 | U29: 200 - 300 | V29: 1 | W29: UT1 | X29: Mm Mega Market Hòa Khánh Nam | Y29: Mm Mega Market Hòa Khánh Nam | Z29: - | AB29: New | AC29: Chưa có | AE29: 0 | AF29: nếu kh có thì hỏi thêm tầng trệt, đối diện Local phúc long tháng 2 nhận | AH29: GG | AI29: 45931 | AJ29: 10 | AK29: Hòa Khánh Nam, Liên Chiểu, Đà Nẵng | AL29: Nguyễn Sinh Sắc, Hòa Khánh Nam, Liên Chiểu, Đà Nẵng | AM29: VNM.19.4.4_1 | AN29: Gogi House Mall | AO29: Gogi House|Mm Mega Market Hòa Khánh Nam | AP29: 1137 | AQ29: 38/56 | AR29: 1045/11159 | AS29: 144 | AT29: 132/144 | AW29: =Plan_2026[[#This Row],[Tên brand]]&" "&Plan_2026[[#This Row],[Trục đường chính]]&Plan_2026[[#This Row],[Tên mall (chuẩn hóa)]]&Plan_2026[[#This Row],[Địa chỉ đầy đủ]] -> Gogi House Nguyễn Sinh SắcMm Mega Market Hòa Khánh NamNguyễn Sinh Sắc, Hòa Khánh Nam, Liên Chiểu, Đà Nẵng
A30: 27 | B30: 30MWNEW9 | C30: Manwah | D30: Nguyễn Văn Bạch Long | E30: 2026 | F30: 1 | G30: 1 | H30: 5 | J30: SBU.MN | K30: Trung | L30: Đà Nẵng | M30: VNM.19_1 | N30: Thanh Khê | O30: Chính Gián | P30: 46 Đường Điện Biên Phủ | Q30: Mall | R30: 8 - 12 | S30: 8 - 12 | T30: 200 - 300 | U30: 200 - 300 | V30: 1 | W30: UT1 | X30: Aeon Mall Đà Nẵng | Y30: Aeon Mall Đà Nẵng | Z30: 200 | AB30: New | AC30: Đã ký | AE30: 1 | AH30: MW | AI30: 46023 | AJ30: 1 | AK30: Chính Gián, Thanh Khê, Đà Nẵng | AL30: 46 Đường Điện Biên Phủ, Chính Gián, Thanh Khê, Đà Nẵng | AM30: VNM.19.7.2_1 | AN30: Manwah Mall | AO30: Manwah|Aeon Mall Đà Nẵng | AP30: 9351 | AQ30: 6/56 | AR30: 308/11159 | AS30: 55 | AT30: 21/55 | AW30: =Plan_2026[[#This Row],[Tên brand]]&" "&Plan_2026[[#This Row],[Trục đường chính]]&Plan_2026[[#This Row],[Tên mall (chuẩn hóa)]]&Plan_2026[[#This Row],[Địa chỉ đầy đủ]] -> Manwah 46 Đường Điện Biên PhủAeon Mall Đà Nẵng46 Đường Điện Biên Phủ, Chính Gián, Thanh Khê, Đà Nẵng
A31: 28 | B31: 30KKNEW09 | C31: Kichi Kichi | D31: Phan Văn Thủy Hà Mỹ Phượng | E31: 2025 | F31: 4 | G31: 12 | H31: 4 | I31: 5 | J31: SBU.MN | K31: Trung | L31: Đà Nẵng | M31: VNM.19_1 | N31: Thanh Khê | O31: Chính Gián | P31: 46 Đường Điện Biên Phủ | Q31: Mall | R31: 8 - 12 | S31: 8 - 12 | T31: 200 | U31: 200 - 300 | V31: 1 | W31: UT1 | X31: Aeon Mall Đà Nẵng | Y31: Aeon Mall Đà Nẵng | Z31: - | AB31: New | AC31: Đã ký | AE31: 1 | AH31: KK | AI31: 45992 | AJ31: 12 | AK31: Chính Gián, Thanh Khê, Đà Nẵng | AL31: 46 Đường Điện Biên Phủ, Chính Gián, Thanh Khê, Đà Nẵng | AM31: VNM.19.7.2_1 | AN31: Kichi Kichi Mall | AO31: Kichi Kichi|Aeon Mall Đà Nẵng | AP31: 9351 | AQ31: 6/56 | AR31: 308/11159 | AS31: 107 | AT31: 36/107 | AW31: =Plan_2026[[#This Row],[Tên brand]]&" "&Plan_2026[[#This Row],[Trục đường chính]]&Plan_2026[[#This Row],[Tên mall (chuẩn hóa)]]&Plan_2026[[#This Row],[Địa chỉ đầy đủ]] -> Kichi Kichi 46 Đường Điện Biên PhủAeon Mall Đà Nẵng46 Đường Điện Biên Phủ, Chính Gián, Thanh Khê, Đà Nẵng
A32: 29 | B32: 30SSNEW08 | C32: Isushi | D32: Trần Tuấn Sĩ Lương Anh Lộc Võ Hoàng Dũng | E32: 2026 | F32: 3 | G32: 7 | H32: 11 | J32: SBU.MN | K32: Trung | L32: Đà Nẵng | M32: VNM.19_1 | N32: Hải Châu | O32: Bình Thuận | P32: 2 tháng 9 | Q32: Shophouse | R32: 8 - 12 | S32: 8 - 12 | T32: 200 - 300 | U32: 200 - 300 | V32: 1 | W32: UT1 | X32: 2.9 Hải Châu, Đà Nẵng | Z32: 300 | AA32: 150 - 180tr | AB32: New | AC32: Đã ký | AE32: 1 | AH32: SS | AI32: 46204 | AJ32: 7 | AK32: Bình Thuận, Hải Châu, Đà Nẵng | AL32: 2 tháng 9, Bình Thuận, Hải Châu, Đà Nẵng | AM32: VNM.19.2.2_1 | AN32: Isushi Shophouse | AO32: Isushi|Bình Thuận, Hải Châu, Đà Nẵng | AP32: 9947 | AQ32: 5/56 | AR32: 293/11159 | AS32: 25 | AT32: 11/25 | AW32: =Plan_2026[[#This Row],[Tên brand]]&" "&Plan_2026[[#This Row],[Trục đường chính]]&Plan_2026[[#This Row],[Tên mall (chuẩn hóa)]]&Plan_2026[[#This Row],[Địa chỉ đầy đủ]] -> Isushi 2 tháng 92 tháng 9, Bình Thuận, Hải Châu, Đà Nẵng
A33: 198 | B33: 30GGNEW06 | C33: Gogi House | D33: Lê Kim Hồng Võ Trường Giang | E33: 2026 | F33: 1 | G33: 2 | H33: 6 | J33: HCM | K33: Nam | L33: Hồ Chí Minh | M33: VNM.25_1 | N33: Quận 1 | O33: Nguyễn Cư Trinh | P33: 235 Nguyễn Văn Cừ | Q33: Mall | R33: 6 | S33: <= 6 | T33: 180 - 250 | U33: 200 - 300 | V33: 1 | W33: UT1 | X33: Nowzone | Y33: Nowzone | Z33: - | AB33: New | AC33: Chưa có | AE33: 0 | AH33: GG | AI33: 46054 | AJ33: 2 | AK33: Nguyễn Cư Trinh, Quận 1, Hồ Chí Minh | AL33: 235 Nguyễn Văn Cừ, Nguyễn Cư Trinh, Quận 1, Hồ Chí Minh | AM33: VNM.25.13.7_1 | AN33: Gogi House Mall | AO33: Gogi House|Nowzone | AP33: 15403 | AQ33: 104/322 | AR33: 172/11159 | AS33: 144 | AT33: 30/144 | AW33: =Plan_2026[[#This Row],[Tên brand]]&" "&Plan_2026[[#This Row],[Trục đường chính]]&Plan_2026[[#This Row],[Tên mall (chuẩn hóa)]]&Plan_2026[[#This Row],[Địa chỉ đầy đủ]] -> Gogi House 235 Nguyễn Văn CừNowzone235 Nguyễn Văn Cừ, Nguyễn Cư Trinh, Quận 1, Hồ Chí Minh
A34: 31 | B34: 30KKNEW08 | C34: Kichi Kichi | D34: Phan Văn Thủy Hà Mỹ Phượng | E34: 2025 | F34: 4 | G34: 12 | H34: 4 | J34: SBU.MN | K34: Trung | L34: Đà Nẵng | M34: VNM.19_1 | N34: Liên Chiểu | O34: Hòa Khánh Nam | P34: Nguyễn Sinh Sắc | Q34: Mall | R34: 8 - 12 | S34: 8 - 12 | T34: 200 | U34: 200 - 300 | V34: 1 | W34: UT1 | X34: MM Supercenter | Y34: MM Supercenter | Z34: - | AB34: New | AC34: Chưa có | AE34: 0 | AF34: Slot bị khuất, đang xem xét Cần theo dõi thêm | AH34: KK | AI34: 45992 | AJ34: 12 | AK34: Hòa Khánh Nam, Liên Chiểu, Đà Nẵng | AL34: Nguyễn Sinh Sắc, Hòa Khánh Nam, Liên Chiểu, Đà Nẵng | AM34: VNM.19.4.4_1 | AN34: Kichi Kichi Mall | AO34: Kichi Kichi|MM Supercenter | AP34: 1137 | AQ34: 38/56 | AR34: 1045/11159 | AS34: 107 | AT34: 97/107 | AW34: =Plan_2026[[#This Row],[Tên brand]]&" "&Plan_2026[[#This Row],[Trục đường chính]]&Plan_2026[[#This Row],[Tên mall (chuẩn hóa)]]&Plan_2026[[#This Row],[Địa chỉ đầy đủ]] -> Kichi Kichi Nguyễn Sinh SắcMM SupercenterNguyễn Sinh Sắc, Hòa Khánh Nam, Liên Chiểu, Đà Nẵng
A35: 32 | B35: TCHNEW043 | C35: The Coffee House | D35: Phạm Thanh Trúc | E35: 2026 | F35: 1 | G35: 3 | H35: 7 | J35: SBU.MN | K35: Trung | L35: Đà Nẵng | M35: VNM.19_1 | N35: Hải Châu | O35: Bình Thuận | P35: Nguyễn Văn Linh, giao với 2 tháng 9 | Q35: Shophouse | R35: 6 - 8 | S35: 6 - 8 | T35: 100 - 150 | U35: 100 - 150 | V35: 1 | W35: UT2 | Z35: 132 | AB35: New | AC35: Chưa có | AE35: 0 | AF35: khúc có AEON | AH35: TCH | AI35: 46082 | AJ35: 3 | AK35: Bình Thuận, Hải Châu, Đà Nẵng | AL35: Nguyễn Văn Linh, giao với 2 tháng 9, Bình Thuận, Hải Châu, Đà Nẵng | AM35: VNM.19.2.2_1 | AN35: The Coffee House Shophouse | AO35: The Coffee House|Bình Thuận, Hải Châu, Đà Nẵng | AP35: 9947 | AQ35: 5/56 | AR35: 293/11159 | AS35: 81 | AT35: 45/81 | AW35: =Plan_2026[[#This Row],[Tên brand]]&" "&Plan_2026[[#This Row],[Trục đường chính]]&Plan_2026[[#This Row],[Tên mall (chuẩn hóa)]]&Plan_2026[[#This Row],[Địa chỉ đầy đủ]] -> The Coffee House Nguyễn Văn Linh, giao với 2 tháng 9Nguyễn Văn Linh, giao với 2 tháng 9, Bình Thuận, Hải Châu, Đà Nẵng
A36: 33 | B36: TCHNEW059 | C36: The Coffee House | D36: Phạm Thanh Trúc | E36: 2026 | F36: 2 | G36: 5 | H36: 9 | J36: SBU.MN | K36: Trung | L36: Đà Nẵng | M36: VNM.19_1 | N36: Thanh Khê | O36: Tân Chính | Q36: Mall | R36: 6 - 8 | S36: 6 - 8 | T36: 100 - 150 | U36: 100 - 150 | V36: 1 | W36: UT2 | X36: Lotte, Go hoặc Aeon | Z36: 132 | AB36: New | AC36: Chưa có | AE36: 0 | AG36: Tự thêm quận, phường | AH36: TCH | AI36: 46143 | AJ36: 5 | AK36: Tân Chính, Thanh Khê, Đà Nẵng | AL36: Tân Chính, Thanh Khê, Đà Nẵng | AM36: VNM.19.7.5_1 | AN36: The Coffee House Mall | AO36: The Coffee House | AP36: 13534 | AQ36: 1/56 | AR36: 215/11159 | AS36: 81 | AT36: 36/81 | AW36: =Plan_2026[[#This Row],[Tên brand]]&" "&Plan_2026[[#This Row],[Trục đường chính]]&Plan_2026[[#This Row],[Tên mall (chuẩn hóa)]]&Plan_2026[[#This Row],[Địa chỉ đầy đủ]] -> The Coffee House Tân Chính, Thanh Khê, Đà Nẵng
A37: 34 | B37: 30DNNOBUD01 | C37: Dao Niu Guo | D37: Lê Thị Như Bích | E37: 2026 | F37: 1 | G37: 1 | H37: 5 | J37: SBU.MN | K37: Trung | L37: Đà Nẵng | M37: VNM.19_1 | N37: Hải Châu | O37: Bình Thuận | P37: 2 tháng 9 | Q37: Shophouse | R37: 8 - 12 | S37: 8 - 12 | T37: 300 | U37: 300 - 500 | V37: 1 | W37: UT2 | X37: 2.9 Hải Châu, Đà Nẵng | Z37: 160 | AB37: New | AC37: Đã ký | AE37: 1 | AH37: DN | AI37: 46023 | AJ37: 1 | AK37: Bình Thuận, Hải Châu, Đà Nẵng | AL37: 2 tháng 9, Bình Thuận, Hải Châu, Đà Nẵng | AM37: VNM.19.2.2_1 | AN37: Dao Niu Guo Shophouse | AO37: Dao Niu Guo|Bình Thuận, Hải Châu, Đà Nẵng | AP37: 9947 | AQ37: 5/56 | AR37: 293/11159 | AS37: 6 | AT37: 3/6 | AW37: =Plan_2026[[#This Row],[Tên brand]]&" "&Plan_2026[[#This Row],[Trục đường chính]]&Plan_2026[[#This Row],[Tên mall (chuẩn hóa)]]&Plan_2026[[#This Row],[Địa chỉ đầy đủ]] -> Dao Niu Guo 2 tháng 92 tháng 9, Bình Thuận, Hải Châu, Đà Nẵng
A38: 35 | B38: 30KKNOBUD07 | C38: Kichi Kichi | D38: Phan Văn Thủy Hà Mỹ Phượng | E38: 2026 | F38: 3 | G38: 7 | H38: 11 | J38: SBU.MN | K38: Nam | L38: Đồng Nai | M38: VNM.17_1 | N38: Long Khánh | O38: Xuân An | P38: Long Thành/Long Khánh | Q38: Shophouse | R38: 8 - 12 | S38: 8 - 12 | T38: 200 | U38: 150 - 200 | V38: 1 | W38: UT2 | Z38: - | AB38: New | AC38: Chưa có | AE38: 0 | AF38: standard | AG38: Tự thêm phường | AH38: KK | AI38: 46204 | AJ38: 7 | AK38: Xuân An, Long Khánh, Đồng Nai | AL38: Long Thành/Long Khánh, Xuân An, Long Khánh, Đồng Nai | AM38: VNM.17.4.9_1 | AN38: Kichi Kichi Shophouse | AO38: Kichi Kichi|Xuân An, Long Khánh, Đồng Nai | AP38: 4368 | AQ38: 12/171 | AR38: 567/11159 | AS38: 107 | AT38: 71/107 | AW38: =Plan_2026[[#This Row],[Tên brand]]&" "&Plan_2026[[#This Row],[Trục đường chính]]&Plan_2026[[#This Row],[Tên mall (chuẩn hóa)]]&Plan_2026[[#This Row],[Địa chỉ đầy đủ]] -> Kichi Kichi Long Thành/Long KhánhLong Thành/Long Khánh, Xuân An, Long Khánh, Đồng Nai
A39: 36 | B39: 30WYNOBUD03 | C39: Wow!Yakiniku | D39: Bùi Hồng Gấm | E39: 2025 | F39: 4 | G39: 10 | H39: 2 | J39: SBU.MN | K39: Nam | L39: Đồng Nai | M39: VNM.17_1 | N39: Biên Hòa | O39: Thống Nhất | Q39: Shophouse | R39: 8 - 12 | S39: 8 - 12 | T39: 150 - 200 | U39: 150 - 200 | V39: 1 | W39: UT2 | Z39: - | AB39: New | AC39: Đang offer | AE39: 1 | AF39: Ezy Center | AH39: WY | AI39: 45931 | AJ39: 10 | AK39: Thống Nhất, Biên Hòa, Đồng Nai | AL39: Thống Nhất, Biên Hòa, Đồng Nai | AM39: VNM.17.1.27_1 | AN39: Wow!Yakiniku Shophouse | AO39: Wow!Yakiniku|Thống Nhất, Biên Hòa, Đồng Nai | AP39: 3387 | AQ39: 13/171 | AR39: 656/11159 | AS39: 2 | AT39: 3/2 | AW39: =Plan_2026[[#This Row],[Tên brand]]&" "&Plan_2026[[#This Row],[Trục đường chính]]&Plan_2026[[#This Row],[Tên mall (chuẩn hóa)]]&Plan_2026[[#This Row],[Địa chỉ đầy đủ]] -> Wow!Yakiniku Thống Nhất, Biên Hòa, Đồng Nai
A40: 37 | B40: 30CDNOBUD5 | C40: CloudPot | D40: Lê Thị Như Bích | E40: 2026 | F40: 3 | G40: 7 | H40: 11 | J40: SBU.MN | K40: Nam | L40: Đồng Nai | M40: VNM.17_1 | N40: Biên Hòa | O40: Thống Nhất | P40: Võ Thị Sáu | Q40: Shophouse | R40: 6 | S40: <= 6 | T40: 200 - 240 | U40: 200 - 300 | V40: 1 | W40: UT2 | X40: 146 Võ Thị Sáu-Biên Hoà | Z40: 180 | AB40: New | AC40: Reject | AE40: 0 | AF40: Có thể không theo nữa do không có chỗ đỗ xe ô tô va vị trí đặt chạm điện 3P có thể thay bằng cụm Ezy Center | AH40: CD | AI40: 46204 | AJ40: 7 | AK40: Thống Nhất, Biên Hòa, Đồng Nai | AL40: Võ Thị Sáu, Thống Nhất, Biên Hòa, Đồng Nai | AM40: VNM.17.1.27_1 | AN40: CloudPot Shophouse | AO40: CloudPot|Thống Nhất, Biên Hòa, Đồng Nai | AP40: 3387 | AQ40: 13/171 | AR40: 656/11159 | AS40: 17 | AT40: 14/17 | AW40: =Plan_2026[[#This Row],[Tên brand]]&" "&Plan_2026[[#This Row],[Trục đường chính]]&Plan_2026[[#This Row],[Tên mall (chuẩn hóa)]]&Plan_2026[[#This Row],[Địa chỉ đầy đủ]] -> CloudPot Võ Thị SáuVõ Thị Sáu, Thống Nhất, Biên Hòa, Đồng Nai
A41: 395 | B41: TCHNOBUD12 | C41: The Coffee House | D41: Lê Hoàng Bảo Trân | E41: 2026 | F41: 3 | G41: 7 | H41: 11 | J41: SBU.MN | K41: Nam | L41: Đồng Nai | M41: VNM.17_1 | N41: Biên Hòa | O41: Quang Vinh | P41: Nguyễn Ái Quốc | Q41: Chân đế | R41: 6 - 8 | S41: 6 - 8 | T41: 100 - 150 | U41: 100 - 150 | V41: 1 | W41: KOUT | X41: Ezy Center | Z41: 132 | AB41: New | AC41: Đang đàm phán | AE41: 1 | AH41: TCH | AI41: 46204 | AJ41: 7 | AK41: Quang Vinh, Biên Hòa, Đồng Nai | AM41: VNM.17.1.14_1 | AN41: The Coffee House Chân đế | AO41: The Coffee House|Quang Vinh, Biên Hòa, Đồng Nai | AP41: 8477 | AQ41: 2/171 | AR41: 340/11159 | AS41: 81 | AT41: 52/81 | AW41: =Plan_2026[[#This Row],[Tên brand]]&" "&Plan_2026[[#This Row],[Trục đường chính]]&Plan_2026[[#This Row],[Tên mall (chuẩn hóa)]]&Plan_2026[[#This Row],[Địa chỉ đầy đủ]] -> The Coffee House Nguyễn Ái Quốc
A42: 395 | B42: 30YTNOBUD03 | C42: Yutang | D42: Võ Hoàng Dũng | E42: 2026 | F42: 3 | G42: 7 | H42: 11 | J42: SBU.MN | K42: Nam | L42: Đồng Nai | M42: VNM.17_1 | N42: Biên Hòa | O42: Long Bình Tân | P42: Go Đồng Nai | Q42: Mall | R42: 8 | S42: 6 - 8 | T42: 120 - 150 | U42: 100 - 150 | V42: 1 | W42: KOUT | X42: Go Đồng Nai | Z42: - | AB42: New | AC42: Đang offer | AE42: 1 | AF42: Đợi tổ 33 phê duyệt | AH42: YT | AI42: 46204 | AJ42: 7 | AK42: Long Bình Tân, Biên Hòa, Đồng Nai | AM42: VNM.17.1.11_1 | AN42: Yutang Mall | AO42: Yutang | AP42: 1549 | AQ42: 24/171 | AR42: 929/11159 | AS42: 10 | AT42: 8/10 | AW42: =Plan_2026[[#This Row],[Tên brand]]&" "&Plan_2026[[#This Row],[Trục đường chính]]&Plan_2026[[#This Row],[Tên mall (chuẩn hóa)]]&Plan_2026[[#This Row],[Địa chỉ đầy đủ]] -> Yutang Go Đồng Nai
A43: 38 | B43: 10KKNOBUD04 | C43: Kichi Kichi | D43: Phạm Thị Thanh Hoa | E43: 2026 | F43: 3 | G43: 7 | H43: 11 | J43: HN | K43: Bắc | L43: Hà Nội | M43: VNM.27_1 | N43: Thanh Xuân | O43: Thanh Xuân Bắc | P43: PCC1 - 44 Triều Khúc, Thanh Xuân | Q43: Chân đế | R43: 8 - 12 | S43: 8 - 12 | T43: 200 | U43: 200 - 300 | V43: 1 | W43: UT2 | Z43: - | AA43: 80 - 100 tr | AB43: New | AC43: Hủy bỏ | AE43: 0 | AF43: tập trung khu dân cư đông đúc, mặt đường chính chính là khách văn phòng | AH43: KK | AI43: 46204 | AJ43: 7 | AK43: Thanh Xuân Bắc, Thanh Xuân, Hà Nội | AL43: PCC1 - 44 Triều Khúc, Thanh Xuân, Thanh Xuân Bắc, Thanh Xuân, Hà Nội | AM43: VNM.27.29.8_1 | AN43: Kichi Kichi Chân đế | AO43: Kichi Kichi|Thanh Xuân Bắc, Thanh Xuân, Hà Nội | AP43: 22853 | AQ43: 17/584 | AR43: 65/11159 | AS43: 107 | AT43: 6/107 | AW43: =Plan_2026[[#This Row],[Tên brand]]&" "&Plan_2026[[#This Row],[Trục đường chính]]&Plan_2026[[#This Row],[Tên mall (chuẩn hóa)]]&Plan_2026[[#This Row],[Địa chỉ đầy đủ]] -> Kichi Kichi PCC1 - 44 Triều Khúc, Thanh XuânPCC1 - 44 Triều Khúc, Thanh Xuân, Thanh Xuân Bắc, Thanh Xuân, Hà Nội
A44: 39 | B44: 10DNNOBUD01 | C44: Dao Niu Guo | D44: Nguyễn Ngọc Hà | E44: 2026 | F44: 3 | G44: 7 | H44: 11 | J44: HN | K44: Bắc | L44: Hà Nội | M44: VNM.27_1 | N44: Đống Đa | O44: Láng Hạ | P44: Huỳnh Thúc Kháng | Q44: Shophouse | R44: 8 - 12 | S44: 8 - 12 | T44: 300 | U44: 300 - 500 | V44: 1 | W44: UT2 | X44: Huỳnh Thúc Kháng | Z44: 160 | AB44: New | AC44: Hủy bỏ | AE44: 0 | AF44: Sentosa | AH44: DN | AI44: 46204 | AJ44: 7 | AK44: Láng Hạ, Đống Đa, Hà Nội | AL44: Huỳnh Thúc Kháng, Láng Hạ, Đống Đa, Hà Nội | AM44: VNM.27.7.6_1 | AN44: Dao Niu Guo Shophouse | AO44: Dao Niu Guo|Láng Hạ, Đống Đa, Hà Nội | AP44: 21722 | AQ44: 20/584 | AR44: 73/11159 | AS44: 6 | AT44: 1/6 | AW44: =Plan_2026[[#This Row],[Tên brand]]&" "&Plan_2026[[#This Row],[Trục đường chính]]&Plan_2026[[#This Row],[Tên mall (chuẩn hóa)]]&Plan_2026[[#This Row],[Địa chỉ đầy đủ]] -> Dao Niu Guo Huỳnh Thúc KhángHuỳnh Thúc Kháng, Láng Hạ, Đống Đa, Hà Nội
A45: 40 | B45: TCHNEW046 | C45: The Coffee House | D45: Nguyễn Thị Thanh | E45: 2026 | F45: 1 | G45: 3 | H45: 7 | J45: HN | K45: Bắc | L45: Hà Nội | M45: VNM.27_1 | N45: Đống Đa | O45: Láng Hạ | P45: Láng Hạ | Q45: Shophouse | R45: 8 - 12 | S45: 8 - 12 | T45: 150 - 200 | U45: 150 - 200 | V45: 1 | W45: UT1 | X45: 12H Láng Hạ | Z45: 132 | AB45: New | AC45: Reject | AE45: 0 | AF45: BU muốn mặt tiền rộng hơn (hiện tại đang 6m) | AH45: TCH | AI45: 46082 | AJ45: 3 | AK45: Láng Hạ, Đống Đa, Hà Nội | AL45: Láng Hạ, Láng Hạ, Đống Đa, Hà Nội | AM45: VNM.27.7.6_1 | AN45: The Coffee House Shophouse | AO45: The Coffee House|Láng Hạ, Đống Đa, Hà Nội | AP45: 21722 | AQ45: 20/584 | AR45: 73/11159 | AS45: 81 | AT45: 11/81 | AW45: =Plan_2026[[#This Row],[Tên brand]]&" "&Plan_2026[[#This Row],[Trục đường chính]]&Plan_2026[[#This Row],[Tên mall (chuẩn hóa)]]&Plan_2026[[#This Row],[Địa chỉ đầy đủ]] -> The Coffee House Láng HạLáng Hạ, Láng Hạ, Đống Đa, Hà Nội
A46: 41 | B46: 10GGNOBUD02 | C46: Gogi House | D46: Hà Thị Hải Yến Nguyễn Thanh Bình | E46: 2026 | F46: 1 | G46: 1 | H46: 5 | J46: HN | K46: Bắc | L46: Hà Nội | M46: VNM.27_1 | N46: Ba Đình | O46: Nguyễn Trung Trực | P46: Hàng Bún | Q46: Shophouse | R46: 8 | S46: 6 - 8 | T46: 220 | U46: 200 - 300 | V46: 1 | W46: UT2 | X46: 24 Hàng Bún | Z46: - | AB46: New | AC46: Đã ký | AE46: 1 | AF46: không nhận sau tết, không nhận tháng 3, muốn nhận luôn, đang xử lý | AH46: GG | AI46: 46023 | AJ46: 1 | AK46: Nguyễn Trung Trực, Ba Đình, Hà Nội | AL46: Hàng Bún, Nguyễn Trung Trực, Ba Đình, Hà Nội | AM46: VNM.27.3.9_1 | AN46: Gogi House Shophouse | AO46: Gogi House|Nguyễn Trung Trực, Ba Đình, Hà Nội | AP46: 20240 | AQ46: 26/584 | AR46: 93/11159 | AS46: 144 | AT46: 13/144 | AW46: =Plan_2026[[#This Row],[Tên brand]]&" "&Plan_2026[[#This Row],[Trục đường chính]]&Plan_2026[[#This Row],[Tên mall (chuẩn hóa)]]&Plan_2026[[#This Row],[Địa chỉ đầy đủ]] -> Gogi House Hàng BúnHàng Bún, Nguyễn Trung Trực, Ba Đình, Hà Nội
A47: 42 | B47: 10DNNEW2 | C47: Dao Niu Guo | D47: Nguyễn Ngọc Hà | E47: 2026 | F47: 1 | G47: 1 | H47: 5 | I47: 5 | J47: HN | K47: Bắc | L47: Hà Nội | M47: VNM.27_1 | N47: Đống Đa | O47: Trung Liệt | P47: Số 1 Thái Hà | Q47: Shophouse | R47: 8 - 12 | S47: 8 - 12 | T47: > 500 | U47: > 500 | V47: 1 | W47: UT1 | Z47: 160 | AB47: Convert | AC47: Đã ký | AE47: 1 | AF47: 700m2 MW Thái Hà, convert DNG email NWS trước khi gia hạn convert | AH47: DN | AI47: 46023 | AJ47: 1 | AK47: Trung Liệt, Đống Đa, Hà Nội | AL47: Số 1 Thái Hà, Trung Liệt, Đống Đa, Hà Nội | AM47: VNM.27.7.17_1 | AN47: Dao Niu Guo Shophouse | AO47: Dao Niu Guo|Trung Liệt, Đống Đa, Hà Nội | AP47: 20220 | AQ47: 27/584 | AR47: 94/11159 | AS47: 6 | AT47: 1/6 | AW47: =Plan_2026[[#This Row],[Tên brand]]&" "&Plan_2026[[#This Row],[Trục đường chính]]&Plan_2026[[#This Row],[Tên mall (chuẩn hóa)]]&Plan_2026[[#This Row],[Địa chỉ đầy đủ]] -> Dao Niu Guo Số 1 Thái HàSố 1 Thái Hà, Trung Liệt, Đống Đa, Hà Nội
A48: 43 | B48: TCHNEW007 | C48: The Coffee House | D48: Nguyễn Thị Thanh | E48: 2025 | F48: 4 | G48: 12 | H48: 4 | J48: HN | K48: Bắc | L48: Hà Nội | M48: VNM.27_1 | N48: Đống Đa | O48: Trung Liệt | P48: Thái Hà, Tây Sơn, Nguyễn Lương Bằng (thay thế cho TCH Thái Hà) | Q48: Shophouse | R48: 6 - 8 | S48: 6 - 8 | T48: 100 - 150 | U48: 100 - 150 | V48: 1 | W48: UT1 | Z48: 132 | AB48: New | AC48: Đang offer | AE48: 1 | AF48: Có site nhưng Thái Hà sắp tới trong diện quy hoạch sẽ có giải tỏa nên cân nhắc đề xuất tuyến khác | AH48: TCH | AI48: 45992 | AJ48: 12 | AK48: Trung Liệt, Đống Đa, Hà Nội | AL48: Thái Hà, Tây Sơn, Nguyễn Lương Bằng (thay thế cho TCH Thái Hà), Trung Liệt, Đống Đa, Hà Nội | AM48: VNM.27.7.17_1 | AN48: The Coffee House Shophouse | AO48: The Coffee House|Trung Liệt, Đống Đa, Hà Nội | AP48: 20220 | AQ48: 27/584 | AR48: 94/11159 | AS48: 81 | AT48: 13/81 | AW48: =Plan_2026[[#This Row],[Tên brand]]&" "&Plan_2026[[#This Row],[Trục đường chính]]&Plan_2026[[#This Row],[Tên mall (chuẩn hóa)]]&Plan_2026[[#This Row],[Địa chỉ đầy đủ]] -> The Coffee House Thái Hà, Tây Sơn, Nguyễn Lương Bằng (thay thế cho TCH Thái Hà)Thái Hà, Tây Sơn, Nguyễn Lương Bằng (thay thế cho TCH Thái Hà), Trung Liệt, Đống Đa, Hà Nội
A49: 44 | B49: 10UP4880 | C49: Union Pizza | D49: Trần Thị Huệ | E49: 2025 | F49: 3 | G49: 9 | H49: 1 | I49: 2 | J49: HN | K49: Bắc | L49: Hà Nội | M49: VNM.27_1 | N49: Đống Đa | O49: Trung Liệt | P49: Số 1-2 Thái Hà | Q49: Shophouse | R49: 8 - 12 | S49: 8 - 12 | T49: 200 - 300 | U49: 200 - 300 | V49: 1 | W49: UT1 | Z49: 200 | AB49: Convert | AC49: Đã ký | AE49: 1 | AF49: Chuyển từ TCH | AH49: UP | AI49: 45901 | AJ49: 9 | AK49: Trung Liệt, Đống Đa, Hà Nội | AL49: Số 1-2 Thái Hà, Trung Liệt, Đống Đa, Hà Nội | AM49: VNM.27.7.17_1 | AN49: Union Pizza Shophouse | AO49: Union Pizza|Trung Liệt, Đống Đa, Hà Nội | AP49: 20220 | AQ49: 27/584 | AR49: 94/11159 | AS49: 5 | AT49: 3/5 | AW49: =Plan_2026[[#This Row],[Tên brand]]&" "&Plan_2026[[#This Row],[Trục đường chính]]&Plan_2026[[#This Row],[Tên mall (chuẩn hóa)]]&Plan_2026[[#This Row],[Địa chỉ đầy đủ]] -> Union Pizza Số 1-2 Thái HàSố 1-2 Thái Hà, Trung Liệt, Đống Đa, Hà Nội
A50: 45 | B50: 10GGNEW53 | C50: Gogi House | D50: Hà Thị Hải Yến Nguyễn Thanh Bình | E50: 2026 | F50: 3 | G50: 8 | H50: 12 | J50: HN | K50: Bắc | L50: Hà Nội | M50: VNM.27_1 | N50: Thanh Xuân | O50: Thanh Xuân Trung | P50: Thanh Xuân, Triều Khúc, Tân Triều | Q50: Shophouse | R50: 8 | S50: 6 - 8 | T50: 220 | U50: 200 - 300 | V50: 1 | W50: UT1 | Z50: - | AB50: New | AC50: Chưa có | AE50: 0 | AH50: GG | AI50: 46235 | AJ50: 8 | AK50: Thanh Xuân Trung, Thanh Xuân, Hà Nội | AL50: Thanh Xuân, Triều Khúc, Tân Triều, Thanh Xuân Trung, Thanh Xuân, Hà Nội | AM50: VNM.27.29.10_1 | AN50: Gogi House Shophouse | AO50: Gogi House|Thanh Xuân Trung, Thanh Xuân, Hà Nội | AP50: 20201 | AQ50: 28/584 | AR50: 95/11159 | AS50: 144 | AT50: 13/144 | AW50: =Plan_2026[[#This Row],[Tên brand]]&" "&Plan_2026[[#This Row],[Trục đường chính]]&Plan_2026[[#This Row],[Tên mall (chuẩn hóa)]]&Plan_2026[[#This Row],[Địa chỉ đầy đủ]] -> Gogi House Thanh Xuân, Triều Khúc, Tân TriềuThanh Xuân, Triều Khúc, Tân Triều, Thanh Xuân Trung, Thanh Xuân, Hà Nội
A51: 46 | B51: 10SMNOBUD01 | C51: Sumogoya | D51: Hà Anh Tuấn | E51: 2026 | F51: 3 | G51: 7 | H51: 11 | J51: HN | K51: Bắc | L51: Hà Nội | M51: VNM.27_1 | N51: Thanh Xuân | O51: Thanh Xuân Trung | P51: Lê Trọng Tấn/Vũ Trọng Phụng | Q51: Shophouse | R51: 6 - 8 | S51: 6 - 8 | T51: 220 - 250 | U51: 200 - 300 | V51: 1 | W51: UT2 | Z51: - | AB51: New | AC51: Chưa có | AE51: 0 | AH51: SM | AI51: 46204 | AJ51: 7 | AK51: Thanh Xuân Trung, Thanh Xuân, Hà Nội | AL51: Lê Trọng Tấn/Vũ Trọng Phụng, Thanh Xuân Trung, Thanh Xuân, Hà Nội | AM51: VNM.27.29.10_1 | AN51: Sumogoya Shophouse | AO51: Sumogoya|Thanh Xuân Trung, Thanh Xuân, Hà Nội | AP51: 20201 | AQ51: 28/584 | AR51: 95/11159 | AS51: 11 | AT51: 2/11 | AW51: =Plan_2026[[#This Row],[Tên brand]]&" "&Plan_2026[[#This Row],[Trục đường chính]]&Plan_2026[[#This Row],[Tên mall (chuẩn hóa)]]&Plan_2026[[#This Row],[Địa chỉ đầy đủ]] -> Sumogoya Lê Trọng Tấn/Vũ Trọng PhụngLê Trọng Tấn/Vũ Trọng Phụng, Thanh Xuân Trung, Thanh Xuân, Hà Nội
A52: 47 | B52: TCHNEW044 | C52: The Coffee House | D52: Nguyễn Thị Thanh | E52: 2026 | F52: 1 | G52: 3 | H52: 7 | J52: HN | K52: Bắc | L52: Hà Nội | M52: VNM.27_1 | N52: Hoàn Kiếm | O52: Hàng Mã | P52: Phan Đình Phùng, Hàng Cót, Hàng Điếu, Đường Thành | Q52: Shophouse | R52: 6 - 8 | S52: 6 - 8 | T52: 100 - 150 | U52: 100 - 150 | V52: 1 | W52: UT1 | Z52: 132 | AB52: New | AC52: Chưa có | AE52: 0 | AH52: TCH | AI52: 46082 | AJ52: 3 | AK52: Hàng Mã, Hoàn Kiếm, Hà Nội | AL52: Phan Đình Phùng, Hàng Cót, Hàng Điếu, Đường Thành, Hàng Mã, Hoàn Kiếm, Hà Nội | AM52: VNM.27.14.12_1 | AN52: The Coffee House Shophouse | AO52: The Coffee House|Hàng Mã, Hoàn Kiếm, Hà Nội | AP52: 20017 | AQ52: 31/584 | AR52: 100/11159 | AS52: 81 | AT52: 14/81 | AW52: =Plan_2026[[#This Row],[Tên brand]]&" "&Plan_2026[[#This Row],[Trục đường chính]]&Plan_2026[[#This Row],[Tên mall (chuẩn hóa)]]&Plan_2026[[#This Row],[Địa chỉ đầy đủ]] -> The Coffee House Phan Đình Phùng, Hàng Cót, Hàng Điếu, Đường ThànhPhan Đình Phùng, Hàng Cót, Hàng Điếu, Đường Thành, Hàng Mã, Hoàn Kiếm, Hà Nội
A53: 48 | B53: 10CKNOBUD01 | C53: Chix Max | D53: Nguyễn Thế Oanh | E53: 2026 | F53: 3 | G53: 7 | H53: 11 | J53: HN | K53: Bắc | L53: Hà Nội | M53: VNM.27_1 | N53: Ba Đình | O53: Giảng Võ | P53: 175 Nguyễn Thái Học | Q53: Mall | R53: 6 - 8 | S53: 6 - 8 | T53: 50 - 100 | U53: 50 - 100 | V53: 1 | W53: UT2 | X53: Hanoi Centre (Tiến Bộ Plaza) | Y53: Hanoi Centre | Z53: - | AB53: New | AC53: Không có | AE53: 0 | AF53: Xem thêm | AG53: Tự thêm phường | AH53: CK | AI53: 46204 | AJ53: 7 | AK53: Giảng Võ, Ba Đình, Hà Nội | AL53: 175 Nguyễn Thái Học, Giảng Võ, Ba Đình, Hà Nội | AM53: VNM.27.3.4_1 | AN53: Chix Max Mall | AO53: Chix Max|Hanoi Centre | AP53: 16398 | AQ53: 56/584 | AR53: 150/11159 | AS53: 3 | AT53: 2/3 | AW53: =Plan_2026[[#This Row],[Tên brand]]&" "&Plan_2026[[#This Row],[Trục đường chính]]&Plan_2026[[#This Row],[Tên mall (chuẩn hóa)]]&Plan_2026[[#This Row],[Địa chỉ đầy đủ]] -> Chix Max 175 Nguyễn Thái HọcHanoi Centre175 Nguyễn Thái Học, Giảng Võ, Ba Đình, Hà Nội
A54: 49 | B54: 10CDNOBUD3 | C54: CloudPot | D54: Lê Văn Tư | E54: 2026 | F54: 3 | G54: 7 | H54: 11 | J54: HN | K54: Bắc | L54: Hà Nội | M54: VNM.27_1 | N54: Đống Đa | O54: Ô Chợ Dừa | P54: Nguyễn Thái Học | Q54: Mall | R54: 6 | S54: <= 6 | T54: 200 - 240 | U54: 200 - 300 | V54: 1 | W54: UT2 | X54: Hanoi Centre (Tiến Bộ Plaza) | Y54: Hanoi Centre | Z54: 180 | AB54: New | AC54: Không có | AE54: 0 | AF54: Hanoi Center/Metropolis/Times City 1 trong 3 mall được nêu diện tích: 200m2 | AH54: CD | AI54: 46204 | AJ54: 7 | AK54: Ô Chợ Dừa, Đống Đa, Hà Nội | AL54: Nguyễn Thái Học, Ô Chợ Dừa, Đống Đa, Hà Nội | AM54: VNM.27.7.10_1 | AN54: CloudPot Mall | AO54: CloudPot|Hanoi Centre | AP54: 19500 | AQ54: 35/584 | AR54: 112/11159 | AS54: 17 | AT54: 5/17 | AW54: =Plan_2026[[#This Row],[Tên brand]]&" "&Plan_2026[[#This Row],[Trục đường chính]]&Plan_2026[[#This Row],[Tên mall (chuẩn hóa)]]&Plan_2026[[#This Row],[Địa chỉ đầy đủ]] -> CloudPot Nguyễn Thái HọcHanoi CentreNguyễn Thái Học, Ô Chợ Dừa, Đống Đa, Hà Nội
A55: 50 | B55: 10CJNOBUD01 | C55: Crystal Jade | D55: Trần Thị Huệ | E55: 2026 | F55: 3 | G55: 7 | H55: 11 | J55: HN | K55: Bắc | L55: Hà Nội | M55: VNM.27_1 | N55: Đống Đa | O55: Ô Chợ Dừa | P55: 175 Nguyễn Thái Học | Q55: Mall | R55: 8 - 12 | S55: 8 - 12 | T55: 200 - 300 | U55: 200 - 300 | V55: 1 | W55: UT2 | X55: Hanoi Centre (Tiến Bộ Plaza) | Y55: Hanoi Centre | Z55: 220 | AB55: New | AC55: Đang offer | AE55: 1 | AH55: CJ | AI55: 46204 | AJ55: 7 | AK55: Ô Chợ Dừa, Đống Đa, Hà Nội | AL55: 175 Nguyễn Thái Học, Ô Chợ Dừa, Đống Đa, Hà Nội | AM55: VNM.27.7.10_1 | AN55: Crystal Jade Mall | AO55: Crystal Jade|Hanoi Centre | AP55: 19500 | AQ55: 35/584 | AR55: 112/11159 | AS55: 8 | AT55: 1/8 | AW55: =Plan_2026[[#This Row],[Tên brand]]&" "&Plan_2026[[#This Row],[Trục đường chính]]&Plan_2026[[#This Row],[Tên mall (chuẩn hóa)]]&Plan_2026[[#This Row],[Địa chỉ đầy đủ]] -> Crystal Jade 175 Nguyễn Thái HọcHanoi Centre175 Nguyễn Thái Học, Ô Chợ Dừa, Đống Đa, Hà Nội
A56: 51 | B56: 10SMNOBUD07 | C56: Sumogoya | D56: Hà Anh Tuấn | E56: 2026 | F56: 3 | G56: 7 | H56: 11 | J56: HN | K56: Bắc | L56: Hà Nội | M56: VNM.27_1 | N56: Ba Đình | O56: Giảng Võ | P56: 175 Phố Nguyễn Thái Học | Q56: Mall | R56: 6 - 8 | S56: 6 - 8 | T56: 200 - 300 | U56: 200 - 300 | V56: 1 | W56: UT2 | X56: Hanoi Centre (Tiến Bộ Plaza) | Y56: Hanoi Centre | Z56: - | AB56: New | AC56: Không có | AE56: 0 | AF56: Tỷ lệ lấp đầy FnB chỉ còn 2 slots, cả mall được 98% Quét Canni Làm việc tiếp về giá Có thể làm Sumo mini | AG56: Tự thêm phường | AH56: SM | AI56: 46204 | AJ56: 7 | AK56: Giảng Võ, Ba Đình, Hà Nội | AL56: 175 Phố Nguyễn Thái Học, Giảng Võ, Ba Đình, Hà Nội | AM56: VNM.27.3.4_1 | AN56: Sumogoya Mall | AO56: Sumogoya|Hanoi Centre | AP56: 16398 | AQ56: 56/584 | AR56: 150/11159 | AS56: 11 | AT56: 4/11 | AW56: =Plan_2026[[#This Row],[Tên brand]]&" "&Plan_2026[[#This Row],[Trục đường chính]]&Plan_2026[[#This Row],[Tên mall (chuẩn hóa)]]&Plan_2026[[#This Row],[Địa chỉ đầy đủ]] -> Sumogoya 175 Phố Nguyễn Thái HọcHanoi Centre175 Phố Nguyễn Thái Học, Giảng Võ, Ba Đình, Hà Nội
A57: 342 | B57: 30GGNOBUD06 | C57: Gogi House | D57: Phạm Tuấn Anh Dương Chí Cường Nguyễn Xuân Hóa Đặng Thanh Quang | E57: 2026 | F57: 3 | G57: 8 | H57: 12 | J57: SBU.MN | K57: Trung | L57: Lâm Đồng | M57: VNM.37_1 | N57: Bảo Lộc | O57: Lộc Sơn | P57: 280 Trần Phú | Q57: Mall | R57: 6 | S57: <= 6 | T57: 180 - 250 | U57: 200 - 300 | V57: 1 | W57: UT2 | X57: Bao Loc Center | Y57: Bao Loc Center | Z57: - | AB57: New | AC57: Chưa có | AE57: 0 | AF57: 175 m2 quý 3,4 mall vừa mới xây xong | AH57: GG | AI57: 46235 | AJ57: 8 | AK57: Lộc Sơn, Bảo Lộc, Lâm Đồng | AM57: VNM.37.1.7_1 | AN57: Gogi House Mall | AO57: Gogi House|Bao Loc Center | AP57: 436 | AQ57: 10/147 | AR57: 1544/11159 | AS57: 144 | AT57: 140/144 | AW57: =Plan_2026[[#This Row],[Tên brand]]&" "&Plan_2026[[#This Row],[Trục đường chính]]&Plan_2026[[#This Row],[Tên mall (chuẩn hóa)]]&Plan_2026[[#This Row],[Địa chỉ đầy đủ]] -> Gogi House 280 Trần PhúBao Loc Center
A58: 53 | B58: 10NRNOBUD01 | C58: Ngonya | D58: Hà Anh Tuấn | E58: 2026 | F58: 3 | G58: 7 | H58: 11 | J58: HN | K58: Bắc | L58: Hà Nội | M58: VNM.27_1 | N58: Ba Đình | O58: Cống Vị | P58: Linh Lang/Phan Kế Bính/Kim Mã Thượng | Q58: Shophouse | R58: 5 - 6 | S58: <= 6 | T58: 50 | U58: 30 - 50 | V58: 1 | W58: UT2 | X58: 57 Linh Lang | Z58: - | AA58: < 50 tr | AB58: New | AC58: Đang offer | AE58: 1 | AH58: YA | AI58: 46204 | AJ58: 7 | AK58: Cống Vị, Ba Đình, Hà Nội | AL58: Linh Lang/Phan Kế Bính/Kim Mã Thượng, Cống Vị, Ba Đình, Hà Nội | AM58: VNM.27.3.1_1 | AN58: Ngonya Shophouse | AO58: Ngonya|Cống Vị, Ba Đình, Hà Nội | AP58: 19336 | AQ58: 38/584 | AR58: 116/11159 | AS58: 0 | AT58: 1/0 | AW58: =Plan_2026[[#This Row],[Tên brand]]&" "&Plan_2026[[#This Row],[Trục đường chính]]&Plan_2026[[#This Row],[Tên mall (chuẩn hóa)]]&Plan_2026[[#This Row],[Địa chỉ đầy đủ]] -> Ngonya Linh Lang/Phan Kế Bính/Kim Mã ThượngLinh Lang/Phan Kế Bính/Kim Mã Thượng, Cống Vị, Ba Đình, Hà Nội
A59: 54 | B59: 10SGNEW02 | C59: Shogun | D59: Nguyễn Thị Thùy | E59: 2026 | F59: 2 | G59: 6 | H59: 10 | J59: HN | K59: Bắc | L59: Hà Nội | M59: VNM.27_1 | N59: Ba Đình | O59: Cống Vị | P59: Linh Lang/Phan Kế Bính | Q59: Shophouse | R59: 6 - 8 | S59: 6 - 8 | T59: 150 - 200 | U59: 150 - 200 | V59: 1 | W59: UT1 | X59: 57 Linh Lang | Z59: 220 | AB59: New | AC59: Reject | AE59: 0 | AF59: tầng 2,3 nhỏ không phù hợp | AH59: SG | AI59: 46174 | AJ59: 6 | AK59: Cống Vị, Ba Đình, Hà Nội | AL59: Linh Lang/Phan Kế Bính, Cống Vị, Ba Đình, Hà Nội | AM59: VNM.27.3.1_1 | AN59: Shogun Shophouse | AO59: Shogun|Cống Vị, Ba Đình, Hà Nội | AP59: 19336 | AQ59: 38/584 | AR59: 116/11159 | AS59: 10 | AT59: 4/10 | AW59: =Plan_2026[[#This Row],[Tên brand]]&" "&Plan_2026[[#This Row],[Trục đường chính]]&Plan_2026[[#This Row],[Tên mall (chuẩn hóa)]]&Plan_2026[[#This Row],[Địa chỉ đầy đủ]] -> Shogun Linh Lang/Phan Kế BínhLinh Lang/Phan Kế Bính, Cống Vị, Ba Đình, Hà Nội
A60: 55 | B60: TCHNEW045 | C60: The Coffee House | D60: Nguyễn Thị Thanh | E60: 2026 | F60: 1 | G60: 3 | H60: 7 | J60: HN | K60: Bắc | L60: Hà Nội | M60: VNM.27_1 | N60: Đống Đa | O60: Láng Thượng | P60: Vincom Nguyễn Chí Thanh (trệt) | Q60: Mall | R60: 6 - 8 | S60: 6 - 8 | T60: 100 - 150 | U60: 100 - 150 | V60: 1 | W60: UT1 | X60: Vincom | Y60: Vincom Center Nguyễn Chí Thanh | Z60: 132 | AB60: New | AC60: Chưa có | AE60: 0 | AF60: Vincom Nguyễn Chí Thanh (trệt) | AH60: TCH | AI60: 46082 | AJ60: 3 | AK60: Láng Thượng, Đống Đa, Hà Nội | AL60: Vincom Nguyễn Chí Thanh (trệt), Láng Thượng, Đống Đa, Hà Nội | AM60: VNM.27.7.7_1 | AN60: The Coffee House Mall | AO60: The Coffee House|Vincom Center Nguyễn Chí Thanh | AP60: 17710 | AQ60: 49/584 | AR60: 135/11159 | AS60: 81 | AT60: 19/81 | AW60: =Plan_2026[[#This Row],[Tên brand]]&" "&Plan_2026[[#This Row],[Trục đường chính]]&Plan_2026[[#This Row],[Tên mall (chuẩn hóa)]]&Plan_2026[[#This Row],[Địa chỉ đầy đủ]] -> The Coffee House Vincom Nguyễn Chí Thanh (trệt)Vincom Center Nguyễn Chí ThanhVincom Nguyễn Chí Thanh (trệt), Láng Thượng, Đống Đa, Hà Nội
A61: 56 | B61: 10KKNEW84 | C61: Kichi Kichi | D61: Phạm Thị Thanh Hoa | E61: 2026 | F61: 1 | G61: 3 | H61: 7 | J61: HN | K61: Bắc | L61: Hà Nội | M61: VNM.27_1 | N61: Đống Đa | O61: Ngã Tư Sở | P61: 102 Thái Thịnh | Q61: Shophouse | R61: 6 - 8 | S61: 6 - 8 | T61: 120 - 150 | U61: 200 - 300 | V61: 1 | W61: UT1 | X61: Hà Thành Plaza | Z61: - | AA61: 40 - 50 tr | AB61: New | AC61: Reject | AE61: 0 | AF61: trống, nhưng không cắt lẻ, cho thuê nguyên sàn | AH61: KK | AI61: 46082 | AJ61: 3 | AK61: Ngã Tư Sở, Đống Đa, Hà Nội | AL61: 102 Thái Thịnh, Ngã Tư Sở, Đống Đa, Hà Nội | AM61: VNM.27.7.9_1 | AN61: Kichi Kichi Shophouse | AO61: Kichi Kichi|Ngã Tư Sở, Đống Đa, Hà Nội | AP61: 17190 | AQ61: 52/584 | AR61: 143/11159 | AS61: 107 | AT61: 15/107 | AW61: =Plan_2026[[#This Row],[Tên brand]]&" "&Plan_2026[[#This Row],[Trục đường chính]]&Plan_2026[[#This Row],[Tên mall (chuẩn hóa)]]&Plan_2026[[#This Row],[Địa chỉ đầy đủ]] -> Kichi Kichi 102 Thái Thịnh102 Thái Thịnh, Ngã Tư Sở, Đống Đa, Hà Nội
A62: 57 | B62: 10UTNOBUD09 | C62: Universal Tea | D62: Phạm Minh Đức | E62: 2026 | F62: 2 | G62: 6 | H62: 10 | J62: HN | K62: Bắc | L62: Hà Nội | M62: VNM.27_1 | N62: Đống Đa | O62: Trung Tự | P62: 2 Đường Phạm Ngọc Thạch | Q62: Mall | R62: 8 - 12 | S62: 8 - 12 | T62: 100 - 150 | U62: 100 - 150 | V62: 1 | W62: UT2 | X62: Vincom Center Phạm Ngọc Thạch | Y62: Vincom Center Phạm Ngọc Thạch | Z62: 130tr | AB62: New | AC62: Reject | AE62: 0 | AF62: có site nhưng không đồng ý | AH62: UT | AI62: 46174 | AJ62: 6 | AK62: Trung Tự, Đống Đa, Hà Nội | AL62: 2 Đường Phạm Ngọc Thạch, Trung Tự, Đống Đa, Hà Nội | AM62: VNM.27.7.19_1 | AN62: Universal Tea Mall | AO62: Universal Tea|Vincom Center Phạm Ngọc Thạch | AP62: 16783 | AQ62: 54/584 | AR62: 147/11159 | AS62: 16 | AT62: 8/16 | AW62: =Plan_2026[[#This Row],[Tên brand]]&" "&Plan_2026[[#This Row],[Trục đường chính]]&Plan_2026[[#This Row],[Tên mall (chuẩn hóa)]]&Plan_2026[[#This Row],[Địa chỉ đầy đủ]] -> Universal Tea 2 Đường Phạm Ngọc ThạchVincom Center Phạm Ngọc Thạch2 Đường Phạm Ngọc Thạch, Trung Tự, Đống Đa, Hà Nội
A63: 58 | B63: 10DNNOBUD03 | C63: Dao Niu Guo | D63: Nguyễn Ngọc Hà | E63: 2026 | F63: 1 | G63: 1 | H63: 5 | J63: HN | K63: Bắc | L63: Hà Nội | M63: VNM.27_1 | N63: Ba Đình | O63: Giảng Võ | P63: DNG Trần Huy Liệu | Q63: Shophouse | R63: 8 - 12 | S63: 8 - 12 | T63: 200 - 300 | U63: 200 - 300 | V63: 1 | W63: UT1 | Z63: 160 | AB63: Convert | AC63: Đã ký | AE63: 1 | AF63: Convert CloudPot | AH63: DN | AI63: 46023 | AJ63: 1 | AK63: Giảng Võ, Ba Đình, Hà Nội | AL63: DNG Trần Huy Liệu, Giảng Võ, Ba Đình, Hà Nội | AM63: VNM.27.3.4_1 | AN63: Dao Niu Guo Shophouse | AO63: Dao Niu Guo|Giảng Võ, Ba Đình, Hà Nội | AP63: 16398 | AQ63: 56/584 | AR63: 150/11159 | AS63: 6 | AT63: 2/6 | AW63: =Plan_2026[[#This Row],[Tên brand]]&" "&Plan_2026[[#This Row],[Trục đường chính]]&Plan_2026[[#This Row],[Tên mall (chuẩn hóa)]]&Plan_2026[[#This Row],[Địa chỉ đầy đủ]] -> Dao Niu Guo DNG Trần Huy LiệuDNG Trần Huy Liệu, Giảng Võ, Ba Đình, Hà Nội
A64: 59 | B64: 10GGNOBUD03 | C64: Gogi House | D64: Hà Thị Hải Yến Nguyễn Thanh Bình | E64: 2026 | F64: 2 | G64: 5 | H64: 9 | J64: HN | K64: Bắc | L64: Hà Nội | M64: VNM.27_1 | N64: Ba Đình | O64: Giảng Võ | P64: Ngọc Khánh | Q64: Shophouse | R64: 8 | S64: 6 - 8 | T64: 220 - 240 | U64: 200 - 300 | V64: 1 | W64: UT2 | Z64: - | AB64: New | AC64: Chưa có | AE64: 0 | AF64: 1 mặt sàn là tốt nhất Hồ Ngọc Khánh, vòng hồ, trục đường đang có Bò Tơ Quán Mộc, Long Wang…Phố Ngọc Khánh | AH64: GG | AI64: 46143 | AJ64: 5 | AK64: Giảng Võ, Ba Đình, Hà Nội | AL64: Ngọc Khánh, Giảng Võ, Ba Đình, Hà Nội | AM64: VNM.27.3.4_1 | AN64: Gogi House Shophouse | AO64: Gogi House|Giảng Võ, Ba Đình, Hà Nội | AP64: 16398 | AQ64: 56/584 | AR64: 150/11159 | AS64: 144 | AT64: 24/144 | AW64: =Plan_2026[[#This Row],[Tên brand]]&" "&Plan_2026[[#This Row],[Trục đường chính]]&Plan_2026[[#This Row],[Tên mall (chuẩn hóa)]]&Plan_2026[[#This Row],[Địa chỉ đầy đủ]] -> Gogi House Ngọc KhánhNgọc Khánh, Giảng Võ, Ba Đình, Hà Nội
A65: 60 | B65: 10UTNOBUD02 | C65: Universal Tea | D65: Phạm Minh Đức | E65: 2026 | F65: 1 | G65: 2 | H65: 6 | J65: HN | K65: Bắc | L65: Hà Nội | M65: VNM.27_1 | N65: Hà Đông | O65: Mộ Lao | P65: Nguyễn Văn Lộc | Q65: Shophouse | R65: > 12 | S65: >= 12 | T65: 150 - 200 | U65: 150 - 200 | V65: 1 | W65: UT2 | Z65: 130tr | AB65: New | AC65: Hủy bỏ | AE65: 0 | AH65: UT | AI65: 46054 | AJ65: 2 | AK65: Mộ Lao, Hà Đông, Hà Nội | AL65: Nguyễn Văn Lộc, Mộ Lao, Hà Đông, Hà Nội | AM65: VNM.27.11.7_1 | AN65: Universal Tea Shophouse | AO65: Universal Tea|Mộ Lao, Hà Đông, Hà Nội | AP65: 16052 | AQ65: 59/584 | AR65: 160/11159 | AS65: 16 | AT65: 9/16 | AW65: =Plan_2026[[#This Row],[Tên brand]]&" "&Plan_2026[[#This Row],[Trục đường chính]]&Plan_2026[[#This Row],[Tên mall (chuẩn hóa)]]&Plan_2026[[#This Row],[Địa chỉ đầy đủ]] -> Universal Tea Nguyễn Văn LộcNguyễn Văn Lộc, Mộ Lao, Hà Đông, Hà Nội
A66: 61 | B66: 10SMNOBUD02 | C66: Sumogoya | D66: Hà Anh Tuấn | E66: 2026 | F66: 3 | G66: 7 | H66: 11 | J66: HN | K66: Bắc | L66: Hà Nội | M66: VNM.27_1 | N66: Hai Bà Trưng | O66: Phạm Đình Hổ | P66: Tô Hiến Thành/Ngô Thì Nhậm | Q66: Shophouse | R66: 6 - 8 | S66: 6 - 8 | T66: 220 - 250 | U66: 200 - 300 | V66: 1 | W66: UT2 | Z66: - | AB66: New | AC66: Chưa có | AE66: 0 | AH66: SM | AI66: 46204 | AJ66: 7 | AK66: Phạm Đình Hổ, Hai Bà Trưng, Hà Nội | AL66: Tô Hiến Thành/Ngô Thì Nhậm, Phạm Đình Hổ, Hai Bà Trưng, Hà Nội | AM66: VNM.27.12.13_1 | AN66: Sumogoya Shophouse | AO66: Sumogoya|Phạm Đình Hổ, Hai Bà Trưng, Hà Nội | AP66: 15551 | AQ66: 60/584 | AR66: 169/11159 | AS66: 11 | AT66: 4/11 | AW66: =Plan_2026[[#This Row],[Tên brand]]&" "&Plan_2026[[#This Row],[Trục đường chính]]&Plan_2026[[#This Row],[Tên mall (chuẩn hóa)]]&Plan_2026[[#This Row],[Địa chỉ đầy đủ]] -> Sumogoya Tô Hiến Thành/Ngô Thì NhậmTô Hiến Thành/Ngô Thì Nhậm, Phạm Đình Hổ, Hai Bà Trưng, Hà Nội
A67: 62 | B67: 10KKNEW82 | C67: Kichi Kichi | D67: Phạm Thị Thanh Hoa | E67: 2026 | F67: 1 | G67: 3 | H67: 7 | J67: HN | K67: Bắc | L67: Hà Nội | M67: VNM.27_1 | N67: Cầu Giấy | O67: Yên Hoà | P67: 56 Vũ Phạm Hàm | Q67: Shophouse | R67: 6 - 8 | S67: 6 - 8 | T67: 120 - 150 | U67: 200 - 300 | V67: 1 | W67: UT1 | X67: Yên Hòa Sunshine | Z67: - | AA67: 40 - 50 tr | AB67: New | AC67: Chưa có | AE67: 0 | AH67: KK | AI67: 46082 | AJ67: 3 | AK67: Yên Hoà, Cầu Giấy, Hà Nội | AL67: 56 Vũ Phạm Hàm , Yên Hoà, Cầu Giấy, Hà Nội | AM67: VNM.27.5.8_1 | AN67: Kichi Kichi Shophouse | AO67: Kichi Kichi|Yên Hoà, Cầu Giấy, Hà Nội | AP67: 14831 | AQ67: 65/584 | AR67: 184/11159 | AS67: 107 | AT67: 21/107 | AW67: =Plan_2026[[#This Row],[Tên brand]]&" "&Plan_2026[[#This Row],[Trục đường chính]]&Plan_2026[[#This Row],[Tên mall (chuẩn hóa)]]&Plan_2026[[#This Row],[Địa chỉ đầy đủ]] -> Kichi Kichi 56 Vũ Phạm Hàm 56 Vũ Phạm Hàm , Yên Hoà, Cầu Giấy, Hà Nội
A68: 63 | B68: TCHNEW006 | C68: The Coffee House | D68: Nguyễn Thị Thanh | E68: 2025 | F68: 4 | G68: 12 | H68: 4 | J68: HN | K68: Bắc | L68: Hà Nội | M68: VNM.27_1 | N68: Thanh Xuân | O68: Khương Đình | P68: Vương Thừa Vũ | Q68: Shophouse | R68: 8 - 12 | S68: 8 - 12 | T68: 150 - 200 | U68: 150 - 200 | V68: 1 | W68: UT1 | X68: Tòa ICC Vương Thừa Vũ | Z68: 132 | AB68: New | AC68: Đang offer | AE68: 1 | AF68: Vương Thừa Vũ (shophouse hoặc chân đế gần VP GGG), đã làm việc với CĐT, hiện đang hoàn thiện phòng cháy | AH68: TCH | AI68: 45992 | AJ68: 12 | AK68: Khương Đình, Thanh Xuân, Hà Nội | AL68: Vương Thừa Vũ, Khương Đình, Thanh Xuân, Hà Nội | AM68: VNM.27.29.2_1 | AN68: The Coffee House Shophouse | AO68: The Coffee House|Khương Đình, Thanh Xuân, Hà Nội | AP68: 14584 | AQ68: 71/584 | AR68: 197/11159 | AS68: 81 | AT68: 36/81 | AW68: =Plan_2026[[#This Row],[Tên brand]]&" "&Plan_2026[[#This Row],[Trục đường chính]]&Plan_2026[[#This Row],[Tên mall (chuẩn hóa)]]&Plan_2026[[#This Row],[Địa chỉ đầy đủ]] -> The Coffee House Vương Thừa VũVương Thừa Vũ, Khương Đình, Thanh Xuân, Hà Nội
A69: 64 | B69: 10MTNOBUD01 | C69: Man Tang Guo | D69: Nguyễn Ngọc Hà | E69: 2026 | F69: 3 | G69: 7 | H69: 11 | J69: HN | K69: Bắc | L69: Hà Nội | M69: VNM.27_1 | N69: Đống Đa | O69: Cát Linh | P69: 175 Nguyễn Thái Học | Q69: Mall | R69: 8 - 12 | S69: 8 - 12 | T69: 200 - 300 | U69: 200 - 300 | V69: 1 | W69: UT2 | X69: Hanoi Centre (Tiến Bộ Plaza) | Y69: Hanoi Centre | Z69: - | AB69: New | AC69: Chưa có | AE69: 0 | AF69: gửi lại thong tin | AG69: Tự thêm phường | AH69: MT | AI69: 46204 | AJ69: 7 | AK69: Cát Linh, Đống Đa, Hà Nội | AL69: 175 Nguyễn Thái Học, Cát Linh, Đống Đa, Hà Nội | AM69: VNM.27.7.1_1 | AN69: Man Tang Guo Mall | AO69: Man Tang Guo|Hanoi Centre | AP69: 14390 | AQ69: 73/584 | AR69: 201/11159 | AS69: 4 | AT69: 3/4 | AW69: =Plan_2026[[#This Row],[Tên brand]]&" "&Plan_2026[[#This Row],[Trục đường chính]]&Plan_2026[[#This Row],[Tên mall (chuẩn hóa)]]&Plan_2026[[#This Row],[Địa chỉ đầy đủ]] -> Man Tang Guo 175 Nguyễn Thái HọcHanoi Centre175 Nguyễn Thái Học, Cát Linh, Đống Đa, Hà Nội
A70: 65 | B70: 10SGNOBUD03 | C70: Shogun | D70: Nguyễn Thị Thùy | E70: 2026 | F70: 3 | G70: 7 | H70: 11 | J70: HN | K70: Bắc | L70: Hà Nội | M70: VNM.27_1 | N70: Đống Đa | O70: Cát Linh | P70: 175 Phố Nguyễn Thái Học | Q70: Mall | R70: 6 - 8 | S70: 6 - 8 | T70: 150 - 200 | U70: 150 - 200 | V70: 1 | W70: UT2 | X70: Hanoi Centre (Tiến Bộ Plaza) | Y70: Hanoi Centre | Z70: 220 | AB70: New | AC70: Không có | AE70: 0 | AF70: scan lại sau các MB mall và báo lại sau | AG70: Tự thêm phường | AH70: SG | AI70: 46204 | AJ70: 7 | AK70: Cát Linh, Đống Đa, Hà Nội | AL70: 175 Phố Nguyễn Thái Học, Cát Linh, Đống Đa, Hà Nội | AM70: VNM.27.7.1_1 | AN70: Shogun Mall | AO70: Shogun|Hanoi Centre | AP70: 14390 | AQ70: 73/584 | AR70: 201/11159 | AS70: 10 | AT70: 7/10 | AW70: =Plan_2026[[#This Row],[Tên brand]]&" "&Plan_2026[[#This Row],[Trục đường chính]]&Plan_2026[[#This Row],[Tên mall (chuẩn hóa)]]&Plan_2026[[#This Row],[Địa chỉ đầy đủ]] -> Shogun 175 Phố Nguyễn Thái HọcHanoi Centre175 Phố Nguyễn Thái Học, Cát Linh, Đống Đa, Hà Nội
A71: 66 | B71: 10MMNOBUD01 | C71: Mama's Bakery | D71: Đặng Phương Trang | E71: 2026 | F71: 2 | G71: 5 | H71: 9 | J71: HN | K71: Bắc | L71: Hà Nội | M71: VNM.27_1 | N71: Hai Bà Trưng | O71: Bách Khoa | P71: Bách - Kinh - Xây | Q71: Shophouse | R71: 8 - 12 | S71: 8 - 12 | T71: 150 - 200 | U71: 150 - 200 | V71: 1 | W71: UT2 | Z71: 130tr | AA71: max 150tr | AB71: New | AC71: Chưa có | AE71: 0 | AF71: diện tích: 80 - 150, ưu tiên 3 | AH71: MM | AI71: 46143 | AJ71: 5 | AK71: Bách Khoa, Hai Bà Trưng, Hà Nội | AL71: Bách - Kinh - Xây, Bách Khoa, Hai Bà Trưng, Hà Nội | AM71: VNM.27.12.3_1 | AN71: Mama's Bakery Shophouse | AO71: Mama's Bakery|Bách Khoa, Hai Bà Trưng, Hà Nội | AP71: 12645 | AQ71: 81/584 | AR71: 231/11159 | AS71: 0 | AT71: 1/0 | AW71: =Plan_2026[[#This Row],[Tên brand]]&" "&Plan_2026[[#This Row],[Trục đường chính]]&Plan_2026[[#This Row],[Tên mall (chuẩn hóa)]]&Plan_2026[[#This Row],[Địa chỉ đầy đủ]] -> Mama's Bakery Bách - Kinh - XâyBách - Kinh - Xây, Bách Khoa, Hai Bà Trưng, Hà Nội
A72: 67 | B72: 10UTNOBUD04 | C72: Universal Tea | D72: Phạm Minh Đức | E72: 2026 | F72: 2 | G72: 4 | H72: 8 | J72: HN | K72: Bắc | L72: Hà Nội | M72: VNM.27_1 | N72: Hai Bà Trưng | O72: Bách Khoa | Q72: Shophouse | R72: 6 - 8 | S72: 6 - 8 | T72: 100 - 150 | U72: 100 - 150 | V72: 1 | W72: UT2 | Z72: 130tr | AB72: New | AC72: Hủy bỏ | AE72: 0 | AH72: UT | AI72: 46113 | AJ72: 4 | AK72: Bách Khoa, Hai Bà Trưng, Hà Nội | AL72: Bách Khoa, Hai Bà Trưng, Hà Nội | AM72: VNM.27.12.3_1 | AN72: Universal Tea Shophouse | AO72: Universal Tea|Bách Khoa, Hai Bà Trưng, Hà Nội | AP72: 12645 | AQ72: 81/584 | AR72: 231/11159 | AS72: 16 | AT72: 11/16 | AW72: =Plan_2026[[#This Row],[Tên brand]]&" "&Plan_2026[[#This Row],[Trục đường chính]]&Plan_2026[[#This Row],[Tên mall (chuẩn hóa)]]&Plan_2026[[#This Row],[Địa chỉ đầy đủ]] -> Universal Tea Bách Khoa, Hai Bà Trưng, Hà Nội
A73: 68 | B73: 10ASNEW05 | C73: Ashima | D73: Đinh Thị Tâm | E73: 2026 | F73: 1 | G73: 1 | H73: 5 | I73: 5 | J73: HN | K73: Bắc | L73: Hà Nội | M73: VNM.27_1 | N73: Ba Đình | O73: Ngọc Khánh | P73: 29 Liễu Giai | Q73: Mall | R73: 8 - 12 | S73: 8 - 12 | T73: 200 - 300 | U73: 200 - 300 | V73: 1 | W73: UT1 | X73: Vincom Center Metropolis | Y73: Vincom Center Metropolis | Z73: - | AB73: New | AC73: Reject | AE73: 0 | AF73: Bom hủy dự án | AH73: AS | AI73: 46023 | AJ73: 1 | AK73: Ngọc Khánh, Ba Đình, Hà Nội | AL73: 29 Liễu Giai, Ngọc Khánh, Ba Đình, Hà Nội | AM73: VNM.27.3.8_1 | AN73: Ashima Mall | AO73: Ashima|Vincom Center Metropolis | AP73: 11584 | AQ73: 87/584 | AR73: 252/11159 | AS73: 9 | AT73: 7/9 | AW73: =Plan_2026[[#This Row],[Tên brand]]&" "&Plan_2026[[#This Row],[Trục đường chính]]&Plan_2026[[#This Row],[Tên mall (chuẩn hóa)]]&Plan_2026[[#This Row],[Địa chỉ đầy đủ]] -> Ashima 29 Liễu GiaiVincom Center Metropolis29 Liễu Giai, Ngọc Khánh, Ba Đình, Hà Nội
A74: 69 | B74: 10KK5017 | C74: Kichi Kichi | D74: Phạm Thị Thanh Hoa | E74: 2025 | F74: 3 | G74: 9 | H74: 1 | I74: 3 | J74: HN | K74: Bắc | L74: Hà Nội | M74: VNM.27_1 | N74: Ba Đình | O74: Ngọc Khánh | P74: 29 Liễu Giai | Q74: Mall | R74: 6 - 8 | S74: 6 - 8 | T74: 200 | U74: 200 - 300 | V74: 1 | W74: UT1 | X74: Vincom Center Metropolis | Y74: Vincom Center Metropolis | Z74: - | AB74: New | AC74: Reject | AE74: 0 | AF74: BOM reject | AH74: KK | AI74: 45901 | AJ74: 9 | AK74: Ngọc Khánh, Ba Đình, Hà Nội | AL74: 29 Liễu Giai, Ngọc Khánh, Ba Đình, Hà Nội | AM74: VNM.27.3.8_1 | AN74: Kichi Kichi Mall | AO74: Kichi Kichi|Vincom Center Metropolis | AP74: 11584 | AQ74: 87/584 | AR74: 252/11159 | AS74: 107 | AT74: 31/107 | AW74: =Plan_2026[[#This Row],[Tên brand]]&" "&Plan_2026[[#This Row],[Trục đường chính]]&Plan_2026[[#This Row],[Tên mall (chuẩn hóa)]]&Plan_2026[[#This Row],[Địa chỉ đầy đủ]] -> Kichi Kichi 29 Liễu GiaiVincom Center Metropolis29 Liễu Giai, Ngọc Khánh, Ba Đình, Hà Nội
A75: 70 | B75: 10MWNEW1 | C75: Manwah | D75: Nguyễn Tuấn Dũng | E75: 2026 | F75: 1 | G75: 1 | H75: 5 | J75: HN | K75: Bắc | L75: Hà Nội | M75: VNM.27_1 | N75: Ba Đình | O75: Ngọc Khánh | P75: Nguyễn Chí Thanh | Q75: Shophouse | R75: 8 - 12 | S75: 8 - 12 | T75: 300 - 500 | U75: 300 - 500 | V75: 1 | W75: UT1 | Z75: 200 | AB75: New | AC75: Chưa có | AE75: 0 | AH75: MW | AI75: 46023 | AJ75: 1 | AK75: Ngọc Khánh, Ba Đình, Hà Nội | AL75: Nguyễn Chí Thanh, Ngọc Khánh, Ba Đình, Hà Nội | AM75: VNM.27.3.8_1 | AN75: Manwah Shophouse | AO75: Manwah|Ngọc Khánh, Ba Đình, Hà Nội | AP75: 11584 | AQ75: 87/584 | AR75: 252/11159 | AS75: 55 | AT75: 18/55 | AW75: =Plan_2026[[#This Row],[Tên brand]]&" "&Plan_2026[[#This Row],[Trục đường chính]]&Plan_2026[[#This Row],[Tên mall (chuẩn hóa)]]&Plan_2026[[#This Row],[Địa chỉ đầy đủ]] -> Manwah Nguyễn Chí ThanhNguyễn Chí Thanh, Ngọc Khánh, Ba Đình, Hà Nội
A76: 71 | B76: 09HNOCHNOBUD01 | C76: Chibo | D76: Hà Anh Tuấn | E76: 2026 | F76: 3 | G76: 7 | H76: 11 | J76: HN | K76: Bắc | L76: Hà Nội | M76: VNM.27_1 | N76: Hoàn Kiếm | O76: Lý Thái Tổ | P76: Nguyễn Hữu Huân | Q76: Shophouse | R76: 6 - 8 | S76: 6 - 8 | T76: 70 - 100 | U76: 50 - 100 | V76: 1 | W76: UT2 | Z76: 100 | AA76: < 120tr | AB76: New | AC76: Chưa có | AE76: 0 | AH76: CH | AI76: 46204 | AJ76: 7 | AK76: Lý Thái Tổ, Hoàn Kiếm, Hà Nội | AL76: Nguyễn Hữu Huân, Lý Thái Tổ, Hoàn Kiếm, Hà Nội | AM76: VNM.27.14.14_1 | AN76: Chibo Shophouse | AO76: Chibo|Lý Thái Tổ, Hoàn Kiếm, Hà Nội | AP76: 10805 | AQ76: 90/584 | AR76: 272/11159 | AS76: 2 | AT76: 3/2 | AW76: =Plan_2026[[#This Row],[Tên brand]]&" "&Plan_2026[[#This Row],[Trục đường chính]]&Plan_2026[[#This Row],[Tên mall (chuẩn hóa)]]&Plan_2026[[#This Row],[Địa chỉ đầy đủ]] -> Chibo Nguyễn Hữu HuânNguyễn Hữu Huân, Lý Thái Tổ, Hoàn Kiếm, Hà Nội
A77: 72 | B77: 10SSNOBUD03 | C77: Isushi | D77: Lưu Ngọc Mai | E77: 2026 | F77: 1 | G77: 1 | H77: 5 | J77: HN | K77: Bắc | L77: Hà Nội | M77: VNM.27_1 | N77: Cầu Giấy | O77: Dịch Vọng Hậu | P77: 90 Trần Thái Tông | Q77: Shophouse | R77: 8 - 12 | S77: 8 - 12 | T77: 200 - 300 | U77: 200 - 300 | V77: 1 | W77: UT2 | X77: 90 Trần Thái Tông | Z77: 300 | AA77: < 200tr | AB77: New | AC77: Đã ký | AE77: 1 | AH77: SS | AI77: 46023 | AJ77: 1 | AK77: Dịch Vọng Hậu, Cầu Giấy, Hà Nội | AL77: 90 Trần Thái Tông, Dịch Vọng Hậu, Cầu Giấy, Hà Nội | AM77: VNM.27.5.2_1 | AN77: Isushi Shophouse | AO77: Isushi|Dịch Vọng Hậu, Cầu Giấy, Hà Nội | AP77: 10745 | AQ77: 91/584 | AR77: 274/11159 | AS77: 25 | AT77: 11/25 | AW77: =Plan_2026[[#This Row],[Tên brand]]&" "&Plan_2026[[#This Row],[Trục đường chính]]&Plan_2026[[#This Row],[Tên mall (chuẩn hóa)]]&Plan_2026[[#This Row],[Địa chỉ đầy đủ]] -> Isushi 90 Trần Thái Tông90 Trần Thái Tông, Dịch Vọng Hậu, Cầu Giấy, Hà Nội
A78: 73 | B78: 10SMNOBUD06 | C78: Sumogoya | D78: Hà Anh Tuấn | E78: 2026 | F78: 3 | G78: 7 | H78: 11 | J78: HN | K78: Bắc | L78: Hà Nội | M78: VNM.27_1 | N78: Cầu Giấy | O78: Dịch Vọng Hậu | P78: 241 Đường Xuân Thủy | Q78: Mall | R78: 6 - 8 | S78: 6 - 8 | T78: 200 - 300 | U78: 200 - 300 | V78: 1 | W78: UT2 | X78: IPH The Loop | Y78: Indochina Plaza Hanoi | Z78: - | AB78: New | AC78: Hủy bỏ | AE78: 0 | AF78: có slot, nhưng họ không vào | AH78: SM | AI78: 46204 | AJ78: 7 | AK78: Dịch Vọng Hậu, Cầu Giấy, Hà Nội | AL78: 241 Đường Xuân Thủy, Dịch Vọng Hậu, Cầu Giấy, Hà Nội | AM78: VNM.27.5.2_1 | AN78: Sumogoya Mall | AO78: Sumogoya|Indochina Plaza Hanoi | AP78: 10745 | AQ78: 91/584 | AR78: 274/11159 | AS78: 11 | AT78: 6/11 | AW78: =Plan_2026[[#This Row],[Tên brand]]&" "&Plan_2026[[#This Row],[Trục đường chính]]&Plan_2026[[#This Row],[Tên mall (chuẩn hóa)]]&Plan_2026[[#This Row],[Địa chỉ đầy đủ]] -> Sumogoya 241 Đường Xuân ThủyIndochina Plaza Hanoi241 Đường Xuân Thủy, Dịch Vọng Hậu, Cầu Giấy, Hà Nội
A79: 74 | B79: 10UTNOBUD05 | C79: Universal Tea | D79: Phạm Minh Đức | E79: 2026 | F79: 1 | G79: 1 | H79: 5 | J79: HN | K79: Bắc | L79: Hà Nội | M79: VNM.27_1 | N79: Cầu Giấy | O79: Dịch Vọng Hậu | Q79: Shophouse | R79: 6 - 8 | S79: 6 - 8 | T79: 50 - 100 | U79: 50 - 100 | V79: 1 | W79: UT2 | Z79: 130tr | AB79: New | AC79: Hủy bỏ | AE79: 0 | AH79: UT | AI79: 46023 | AJ79: 1 | AK79: Dịch Vọng Hậu, Cầu Giấy, Hà Nội | AL79: Dịch Vọng Hậu, Cầu Giấy, Hà Nội | AM79: VNM.27.5.2_1 | AN79: Universal Tea Shophouse | AO79: Universal Tea|Dịch Vọng Hậu, Cầu Giấy, Hà Nội | AP79: 10745 | AQ79: 91/584 | AR79: 274/11159 | AS79: 16 | AT79: 15/16 | AW79: =Plan_2026[[#This Row],[Tên brand]]&" "&Plan_2026[[#This Row],[Trục đường chính]]&Plan_2026[[#This Row],[Tên mall (chuẩn hóa)]]&Plan_2026[[#This Row],[Địa chỉ đầy đủ]] -> Universal Tea Dịch Vọng Hậu, Cầu Giấy, Hà Nội
A80: 75 | B80: 10KKNEW80 | C80: Kichi Kichi | D80: Phạm Thị Thanh Hoa | E80: 2025 | F80: 4 | G80: 12 | H80: 4 | J80: HN | K80: Bắc | L80: Hà Nội | M80: VNM.27_1 | N80: Cầu Giấy | O80: Mai Dịch | P80: 30 Phạm Văn Đồng | Q80: Shophouse | R80: 6 - 8 | S80: 6 - 8 | T80: 120 - 150 | U80: 200 - 300 | V80: 1 | W80: UT1 | X80: Tòa nhà Bắc Hà Lucky | Z80: - | AA80: 40 - 50 tr | AB80: New | AC80: Reject | AE80: 0 | AF80: Có site nhưng đang thuyết phục CĐT cắt diện tích nguyên sàn 500m | AH80: KK | AI80: 45992 | AJ80: 12 | AK80: Mai Dịch, Cầu Giấy, Hà Nội | AL80: 30 Phạm Văn Đồng, Mai Dịch, Cầu Giấy, Hà Nội | AM80: VNM.27.5.3_1 | AN80: Kichi Kichi Shophouse | AO80: Kichi Kichi|Mai Dịch, Cầu Giấy, Hà Nội | AP80: 10351 | AQ80: 93/584 | AR80: 283/11159 | AS80: 107 | AT80: 35/107 | AW80: =Plan_2026[[#This Row],[Tên brand]]&" "&Plan_2026[[#This Row],[Trục đường chính]]&Plan_2026[[#This Row],[Tên mall (chuẩn hóa)]]&Plan_2026[[#This Row],[Địa chỉ đầy đủ]] -> Kichi Kichi 30 Phạm Văn Đồng30 Phạm Văn Đồng, Mai Dịch, Cầu Giấy, Hà Nội
A81: 76 | B81: 10UTNOBUD06 | C81: Universal Tea | D81: Phạm Minh Đức | E81: 2026 | F81: 1 | G81: 1 | H81: 5 | J81: HN | K81: Bắc | L81: Hà Nội | M81: VNM.27_1 | N81: Cầu Giấy | O81: Mai Dịch | P81: Lê Đức Thọ | Q81: Chân đế | R81: 6 - 8 | S81: 6 - 8 | T81: 100 - 150 | U81: 100 - 150 | V81: 1 | W81: UT2 | X81: The zei | Y81: The Zei Lê Đức Thọ | Z81: 130tr | AB81: New | AC81: Hủy bỏ | AE81: 0 | AH81: UT | AI81: 46023 | AJ81: 1 | AK81: Mai Dịch, Cầu Giấy, Hà Nội | AL81: Lê Đức Thọ, Mai Dịch, Cầu Giấy, Hà Nội | AM81: VNM.27.5.3_1 | AN81: Universal Tea Chân đế | AO81: Universal Tea|Mai Dịch, Cầu Giấy, Hà Nội | AP81: 10351 | AQ81: 93/584 | AR81: 283/11159 | AS81: 16 | AT81: 15/16 | AW81: =Plan_2026[[#This Row],[Tên brand]]&" "&Plan_2026[[#This Row],[Trục đường chính]]&Plan_2026[[#This Row],[Tên mall (chuẩn hóa)]]&Plan_2026[[#This Row],[Địa chỉ đầy đủ]] -> Universal Tea Lê Đức ThọThe Zei Lê Đức ThọLê Đức Thọ, Mai Dịch, Cầu Giấy, Hà Nội
A82: 77 | B82: 10GGNOBUD04 | C82: Gogi House | D82: Hà Thị Hải Yến Nguyễn Thanh Bình | E82: 2026 | F82: 2 | G82: 4 | H82: 8 | J82: HN | K82: Bắc | L82: Hà Nội | M82: VNM.27_1 | N82: Bắc Từ Liêm | O82: Phú Diễn | P82: Hồ Tùng Mậu | Q82: Shophouse | R82: 8 | S82: 6 - 8 | T82: 220 - 240 | U82: 200 - 300 | V82: 1 | W82: UT2 | Z82: - | AB82: New | AC82: Không có | AE82: 0 | AF82: sang Cầu Diễn, Minh Khai | AG82: Tự thêm phường | AH82: GG | AI82: 46113 | AJ82: 4 | AK82: Phú Diễn, Bắc Từ Liêm, Hà Nội | AL82: Hồ Tùng Mậu, Phú Diễn, Bắc Từ Liêm, Hà Nội | AM82: VNM.27.2.7_1 | AN82: Gogi House Shophouse | AO82: Gogi House|Phú Diễn, Bắc Từ Liêm, Hà Nội | AP82: 7970 | AQ82: 106/584 | AR82: 358/11159 | AS82: 144 | AT82: 61/144 | AW82: =Plan_2026[[#This Row],[Tên brand]]&" "&Plan_2026[[#This Row],[Trục đường chính]]&Plan_2026[[#This Row],[Tên mall (chuẩn hóa)]]&Plan_2026[[#This Row],[Địa chỉ đầy đủ]] -> Gogi House Hồ Tùng MậuHồ Tùng Mậu, Phú Diễn, Bắc Từ Liêm, Hà Nội
A83: 78 | B83: TCHNEW067 | C83: The Coffee House | D83: Nguyễn Thị Thanh | E83: 2026 | F83: 2 | G83: 6 | H83: 10 | J83: HN | K83: Bắc | L83: Hà Nội | M83: VNM.27_1 | N83: Nam Từ Liêm | O83: Cầu Diễn | P83: Nguyễn Cơ Thạch, Hàm Nghi, Vincom Gardenia | Q83: Shophouse | R83: 8 - 12 | S83: 8 - 12 | T83: 150 - 200 | U83: 150 - 200 | V83: 1 | W83: UT1 | X83: Tòa A3 Hàm Nghi | Z83: 132 | AB83: New | AC83: Reject | AE83: 0 | AF83: Không đạt được giá thuê mà BOM mong muốn | AH83: TCH | AI83: 46174 | AJ83: 6 | AK83: Cầu Diễn, Nam Từ Liêm, Hà Nội | AL83: Nguyễn Cơ Thạch, Hàm Nghi, Vincom Gardenia, Cầu Diễn, Nam Từ Liêm, Hà Nội | AM83: VNM.27.19.1_1 | AN83: The Coffee House Shophouse | AO83: The Coffee House|Cầu Diễn, Nam Từ Liêm, Hà Nội | AP83: 10285 | AQ83: 94/584 | AR83: 285/11159 | AS83: 81 | AT83: 44/81 | AW83: =Plan_2026[[#This Row],[Tên brand]]&" "&Plan_2026[[#This Row],[Trục đường chính]]&Plan_2026[[#This Row],[Tên mall (chuẩn hóa)]]&Plan_2026[[#This Row],[Địa chỉ đầy đủ]] -> The Coffee House Nguyễn Cơ Thạch, Hàm Nghi, Vincom GardeniaNguyễn Cơ Thạch, Hàm Nghi, Vincom Gardenia, Cầu Diễn, Nam Từ Liêm, Hà Nội
A84: 79 | B84: 10SSNEW07 | C84: Isushi | D84: Lưu Ngọc Mai | E84: 2026 | F84: 3 | G84: 7 | H84: 11 | J84: HN | K84: Bắc | L84: Hà Nội | M84: VNM.27_1 | N84: Hoàn Kiếm | O84: Tràng Tiền | P84: Hai Bà Trưng, Hàng Bài | Q84: Shophouse | R84: 6 - 8 | S84: 6 - 8 | T84: 200 - 300 | U84: 200 - 300 | V84: 1 | W84: UT1 | Z84: 300 | AA84: 10k | AB84: New | AC84: Chưa có | AE84: 0 | AH84: SS | AI84: 46204 | AJ84: 7 | AK84: Tràng Tiền, Hoàn Kiếm, Hà Nội | AL84: Hai Bà Trưng, Hàng Bài, Tràng Tiền, Hoàn Kiếm, Hà Nội | AM84: VNM.27.14.18_1 | AN84: Isushi Shophouse | AO84: Isushi|Tràng Tiền, Hoàn Kiếm, Hà Nội | AP84: 9088 | AQ84: 99/584 | AR84: 315/11159 | AS84: 25 | AT84: 12/25 | AW84: =Plan_2026[[#This Row],[Tên brand]]&" "&Plan_2026[[#This Row],[Trục đường chính]]&Plan_2026[[#This Row],[Tên mall (chuẩn hóa)]]&Plan_2026[[#This Row],[Địa chỉ đầy đủ]] -> Isushi Hai Bà Trưng, Hàng BàiHai Bà Trưng, Hàng Bài, Tràng Tiền, Hoàn Kiếm, Hà Nội
A85: 80 | B85: 10GGNOBUD05 | C85: Gogi House | D85: Hà Thị Hải Yến Nguyễn Thanh Bình | E85: 2026 | F85: 2 | G85: 4 | H85: 8 | J85: HN | K85: Bắc | L85: Hà Nội | M85: VNM.27_1 | N85: Hoàng Mai | O85: Hoàng Liệt | P85: Hồ Linh Đàm, Nguyễn Cảnh Dị | Q85: Shophouse | R85: 8 | S85: 6 - 8 | T85: 220 - 240 | U85: 200 - 300 | V85: 1 | W85: UT2 | Z85: - | AB85: New | AC85: Chưa có | AE85: 0 | AF85: Khu Nguyễn Cảnh Dị đã offer nhưng BU báo chờ 1 thời gian nữa do đường xá đang làm | AH85: GG | AI85: 46113 | AJ85: 4 | AK85: Hoàng Liệt, Hoàng Mai, Hà Nội | AL85: Hồ Linh Đàm, Nguyễn Cảnh Dị, Hoàng Liệt, Hoàng Mai, Hà Nội | AM85: VNM.27.15.4_1 | AN85: Gogi House Shophouse | AO85: Gogi House|Hoàng Liệt, Hoàng Mai, Hà Nội | AP85: 8872 | AQ85: 102/584 | AR85: 324/11159 | AS85: 144 | AT85: 55/144 | AW85: =Plan_2026[[#This Row],[Tên brand]]&" "&Plan_2026[[#This Row],[Trục đường chính]]&Plan_2026[[#This Row],[Tên mall (chuẩn hóa)]]&Plan_2026[[#This Row],[Địa chỉ đầy đủ]] -> Gogi House Hồ Linh Đàm, Nguyễn Cảnh DịHồ Linh Đàm, Nguyễn Cảnh Dị, Hoàng Liệt, Hoàng Mai, Hà Nội
A86: 81 | B86: 10SMNOBUD03 | C86: Sumogoya | D86: Hà Anh Tuấn | E86: 2026 | F86: 3 | G86: 7 | H86: 11 | J86: HN | K86: Bắc | L86: Hà Nội | M86: VNM.27_1 | N86: Hoàng Mai | O86: Hoàng Liệt | P86: Linh Đàm: Văn Tân | Q86: Shophouse | R86: 6 - 8 | S86: 6 - 8 | T86: 220 - 250 | U86: 200 - 300 | V86: 1 | W86: UT2 | Z86: - | AB86: New | AC86: Chưa có | AE86: 0 | AH86: SM | AI86: 46204 | AJ86: 7 | AK86: Hoàng Liệt, Hoàng Mai, Hà Nội | AL86: Linh Đàm: Văn Tân, Hoàng Liệt, Hoàng Mai, Hà Nội | AM86: VNM.27.15.4_1 | AN86: Sumogoya Shophouse | AO86: Sumogoya|Hoàng Liệt, Hoàng Mai, Hà Nội | AP86: 8872 | AQ86: 102/584 | AR86: 324/11159 | AS86: 11 | AT86: 7/11 | AW86: =Plan_2026[[#This Row],[Tên brand]]&" "&Plan_2026[[#This Row],[Trục đường chính]]&Plan_2026[[#This Row],[Tên mall (chuẩn hóa)]]&Plan_2026[[#This Row],[Địa chỉ đầy đủ]] -> Sumogoya Linh Đàm: Văn TânLinh Đàm: Văn Tân, Hoàng Liệt, Hoàng Mai, Hà Nội
A87: 82 | B87: 10WYNEW21 | C87: Wow!Yakiniku | D87: Ngô Quang Thắng | E87: 2026 | F87: 1 | G87: 3 | H87: 7 | J87: HN | K87: Bắc | L87: Hà Nội | M87: VNM.27_1 | N87: Hoàng Mai | O87: Hoàng Liệt | P87: Linh Đàm Hoàng Mai HN | Q87: Chân đế | R87: 8 - 12 | S87: 8 - 12 | T87: 100 - 150 | U87: 100 - 150 | V87: 1 | W87: UT1 | Z87: - | AB87: New | AC87: Chưa có | AE87: 0 | AF87: Chân đế mini 100-130m2 | AH87: WY | AI87: 46082 | AJ87: 3 | AK87: Hoàng Liệt, Hoàng Mai, Hà Nội | AL87: Linh Đàm Hoàng Mai HN, Hoàng Liệt, Hoàng Mai, Hà Nội | AM87: VNM.27.15.4_1 | AN87: Wow!Yakiniku Chân đế | AO87: Wow!Yakiniku|Hoàng Liệt, Hoàng Mai, Hà Nội | AP87: 8872 | AQ87: 102/584 | AR87: 324/11159 | AS87: 2 | AT87: 3/2 | AW87: =Plan_2026[[#This Row],[Tên brand]]&" "&Plan_2026[[#This Row],[Trục đường chính]]&Plan_2026[[#This Row],[Tên mall (chuẩn hóa)]]&Plan_2026[[#This Row],[Địa chỉ đầy đủ]] -> Wow!Yakiniku Linh Đàm Hoàng Mai HNLinh Đàm Hoàng Mai HN, Hoàng Liệt, Hoàng Mai, Hà Nội
A88: 83 | B88: 10SGNOBUD01 | C88: Shogun | D88: Nguyễn Thị Thùy | E88: 2026 | F88: 3 | G88: 7 | H88: 11 | J88: HN | K88: Bắc | L88: Hà Nội | M88: VNM.27_1 | N88: Tây Hồ | O88: Bưởi | P88: Trích Sài | Q88: Shophouse | R88: 6 - 8 | S88: 6 - 8 | T88: 150 - 200 | U88: 150 - 200 | V88: 1 | W88: UT1 | Z88: 220 | AB88: New | AC88: Chưa có | AE88: 0 | AH88: SG | AI88: 46204 | AJ88: 7 | AK88: Bưởi, Tây Hồ, Hà Nội | AL88: Trích Sài, Bưởi, Tây Hồ, Hà Nội | AM88: VNM.27.25.1_1 | AN88: Shogun Shophouse | AO88: Shogun|Bưởi, Tây Hồ, Hà Nội | AP88: 8382 | AQ88: 103/584 | AR88: 342/11159 | AS88: 10 | AT88: 10/10 | AW88: =Plan_2026[[#This Row],[Tên brand]]&" "&Plan_2026[[#This Row],[Trục đường chính]]&Plan_2026[[#This Row],[Tên mall (chuẩn hóa)]]&Plan_2026[[#This Row],[Địa chỉ đầy đủ]] -> Shogun Trích SàiTrích Sài, Bưởi, Tây Hồ, Hà Nội
A89: 84 | B89: TCHNEW002 | C89: The Coffee House | D89: Nguyễn Thị Thanh | E89: 2025 | F89: 3 | G89: 9 | H89: 1 | J89: HN | K89: Bắc | L89: Hà Nội | M89: VNM.27_1 | N89: Bắc Từ Liêm | O89: Phú Diễn | P89: 136 Đường Hồ Tùng Mậu | Q89: Chân đế | R89: 6 - 8 | S89: 6 - 8 | T89: 100 - 150 | U89: 100 - 150 | V89: 1 | W89: UT1 | X89: Ho Tung Mau Goldmark | Z89: 132 | AB89: New | AC89: Đang đàm phán | AE89: 1 | AF89: Đang đàm phán với MSB để lấy diện tích | AH89: TCH | AI89: 45901 | AJ89: 9 | AK89: Phú Diễn, Bắc Từ Liêm, Hà Nội | AL89: 136 Đường Hồ Tùng Mậu, Phú Diễn, Bắc Từ Liêm, Hà Nội | AM89: VNM.27.2.7_1 | AN89: The Coffee House Chân đế | AO89: The Coffee House|Phú Diễn, Bắc Từ Liêm, Hà Nội | AP89: 7970 | AQ89: 106/584 | AR89: 358/11159 | AS89: 81 | AT89: 53/81 | AW89: =Plan_2026[[#This Row],[Tên brand]]&" "&Plan_2026[[#This Row],[Trục đường chính]]&Plan_2026[[#This Row],[Tên mall (chuẩn hóa)]]&Plan_2026[[#This Row],[Địa chỉ đầy đủ]] -> The Coffee House 136 Đường Hồ Tùng Mậu136 Đường Hồ Tùng Mậu, Phú Diễn, Bắc Từ Liêm, Hà Nội
A90: 85 | B90: 10GGNEW46 | C90: Gogi House | D90: Hà Thị Hải Yến Nguyễn Thanh Bình | E90: 2026 | F90: 3 | G90: 8 | H90: 12 | J90: HN | K90: Bắc | L90: Hà Nội | M90: VNM.27_1 | N90: Hà Đông | O90: Phú La | P90: KĐT Văn Phú | Q90: Shophouse | R90: 8 | S90: 6 - 8 | T90: 220 - 240 | U90: 200 - 300 | V90: 1 | W90: UT1 | X90: Hà Đông, Văn Phú Lacasta | Z90: - | AB90: New | AC90: Đã cọc | AE90: 0 | AF90: Đã cọc thiện chí, chờ chủ đầu tư HQ đưa điều kiện thương mại | AH90: GG | AI90: 46235 | AJ90: 8 | AK90: Phú La, Hà Đông, Hà Nội | AL90: KĐT Văn Phú, Phú La, Hà Đông, Hà Nội | AM90: VNM.27.11.9_1 | AN90: Gogi House Shophouse | AO90: Gogi House|Phú La, Hà Đông, Hà Nội | AP90: 7576 | AQ90: 109/584 | AR90: 367/11159 | AS90: 144 | AT90: 62/144 | AW90: =Plan_2026[[#This Row],[Tên brand]]&" "&Plan_2026[[#This Row],[Trục đường chính]]&Plan_2026[[#This Row],[Tên mall (chuẩn hóa)]]&Plan_2026[[#This Row],[Địa chỉ đầy đủ]] -> Gogi House KĐT Văn PhúKĐT Văn Phú, Phú La, Hà Đông, Hà Nội
A91: 86 | B91: 10KKNEW77 | C91: Kichi Kichi | D91: Phạm Thị Thanh Hoa | E91: 2026 | F91: 3 | G91: 7 | H91: 11 | J91: HN | K91: Bắc | L91: Hà Nội | M91: VNM.27_1 | N91: Hà Đông | O91: Phú La | P91: KĐT Văn Phú | Q91: Shophouse | R91: 8 - 12 | S91: 8 - 12 | T91: 200 | U91: 200 - 300 | V91: 1 | W91: UT2 | X91: Hà Đông, Văn Phú Lacasta | Z91: - | AA91: 40 - 50tr | AB91: New | AC91: Đang đàm phán | AE91: 1 | AF91: standard: 204 m2 muốn thêm 1 mini: 150 - 160 m2 (gần ĐH Đại Nam) | AH91: KK | AI91: 46204 | AJ91: 7 | AK91: Phú La, Hà Đông, Hà Nội | AL91: KĐT Văn Phú, Phú La, Hà Đông, Hà Nội | AM91: VNM.27.11.9_1 | AN91: Kichi Kichi Shophouse | AO91: Kichi Kichi|Phú La, Hà Đông, Hà Nội | AP91: 7576 | AQ91: 109/584 | AR91: 367/11159 | AS91: 107 | AT91: 47/107 | AW91: =Plan_2026[[#This Row],[Tên brand]]&" "&Plan_2026[[#This Row],[Trục đường chính]]&Plan_2026[[#This Row],[Tên mall (chuẩn hóa)]]&Plan_2026[[#This Row],[Địa chỉ đầy đủ]] -> Kichi Kichi KĐT Văn PhúKĐT Văn Phú, Phú La, Hà Đông, Hà Nội
A92: 87 | B92: 10SMNOBUD04 | C92: Sumogoya | D92: Hà Anh Tuấn | E92: 2026 | F92: 3 | G92: 8 | H92: 12 | J92: HN | K92: Bắc | L92: Hà Nội | M92: VNM.27_1 | N92: Hà Đông | O92: Phú La | P92: KĐT Văn Phú | Q92: Shophouse | R92: 6 - 8 | S92: 6 - 8 | T92: 200 - 300 | U92: 200 - 300 | V92: 1 | W92: UT2 | X92: SH13-15 - Tầng 1 Dự án Lacasta Galler - Văn Phú | Z92: - | AB92: New | AC92: Đang offer | AE92: 1 | AH92: SM | AI92: 46235 | AJ92: 8 | AK92: Phú La, Hà Đông, Hà Nội | AL92: KĐT Văn Phú, Phú La, Hà Đông, Hà Nội | AM92: VNM.27.11.9_1 | AN92: Sumogoya Shophouse | AO92: Sumogoya|Phú La, Hà Đông, Hà Nội | AP92: 7576 | AQ92: 109/584 | AR92: 367/11159 | AS92: 11 | AT92: 7/11 | AW92: =Plan_2026[[#This Row],[Tên brand]]&" "&Plan_2026[[#This Row],[Trục đường chính]]&Plan_2026[[#This Row],[Tên mall (chuẩn hóa)]]&Plan_2026[[#This Row],[Địa chỉ đầy đủ]] -> Sumogoya KĐT Văn PhúKĐT Văn Phú, Phú La, Hà Đông, Hà Nội
A93: 88 | B93: 10GGNEW51 | C93: Gogi House | D93: Hà Thị Hải Yến Nguyễn Thanh Bình | E93: 2026 | F93: 3 | G93: 8 | H93: 12 | J93: HN | K93: Bắc | L93: Hà Nội | M93: VNM.27_1 | N93: Nam Từ Liêm | O93: Mỹ Đình 1 | P93: Nguyễn Cơ Thạch phía sau mạn Nollowa cuối Hàm Nghi | Q93: Shophouse | R93: 8 | S93: 6 - 8 | T93: 220 | U93: 200 - 300 | V93: 1 | W93: UT1 | X93: DV1 Nguyễn Văn Giáp | Z93: - | AB93: New | AC93: Reject | AE93: 0 | AF93: BOM không duyệt vì gần Gogi Nguyễn Hoàng và Gogi Hàm Nghi | AH93: GG | AI93: 46235 | AJ93: 8 | AK93: Mỹ Đình 1, Nam Từ Liêm, Hà Nội | AL93: Nguyễn Cơ Thạch phía sau mạn Nollowa cuối Hàm Nghi, Mỹ Đình 1, Nam Từ Liêm, Hà Nội | AM93: VNM.27.19.4_1 | AN93: Gogi House Shophouse | AO93: Gogi House|Mỹ Đình 1, Nam Từ Liêm, Hà Nội | AP93: 7556 | AQ93: 110/584 | AR93: 368/11159 | AS93: 144 | AT93: 62/144 | AW93: =Plan_2026[[#This Row],[Tên brand]]&" "&Plan_2026[[#This Row],[Trục đường chính]]&Plan_2026[[#This Row],[Tên mall (chuẩn hóa)]]&Plan_2026[[#This Row],[Địa chỉ đầy đủ]] -> Gogi House Nguyễn Cơ Thạch phía sau mạn Nollowa cuối Hàm NghiNguyễn Cơ Thạch phía sau mạn Nollowa cuối Hàm Nghi, Mỹ Đình 1, Nam Từ Liêm, Hà Nội
A94: 89 | B94: 10MWNEW4 | C94: Manwah | D94: Nguyễn Tuấn Dũng | E94: 2026 | F94: 1 | G94: 1 | H94: 5 | J94: HN | K94: Bắc | L94: Hà Nội | M94: VNM.27_1 | N94: Nam Từ Liêm | O94: Mỹ Đình 1 | P94: Lê Đức Thọ/Hàm nghi | Q94: Shophouse | R94: 8 - 12 | S94: 8 - 12 | T94: 200 - 300 | U94: 200 - 300 | V94: 1 | W94: UT1 | Z94: 200 | AB94: New | AC94: Chưa có | AE94: 0 | AF94: thay MW Nguyễn Hoàng đã đóng | AH94: MW | AI94: 46023 | AJ94: 1 | AK94: Mỹ Đình 1, Nam Từ Liêm, Hà Nội | AL94: Lê Đức Thọ/Hàm nghi, Mỹ Đình 1, Nam Từ Liêm, Hà Nội | AM94: VNM.27.19.4_1 | AN94: Manwah Shophouse | AO94: Manwah|Mỹ Đình 1, Nam Từ Liêm, Hà Nội | AP94: 7556 | AQ94: 110/584 | AR94: 368/11159 | AS94: 55 | AT94: 31/55 | AW94: =Plan_2026[[#This Row],[Tên brand]]&" "&Plan_2026[[#This Row],[Trục đường chính]]&Plan_2026[[#This Row],[Tên mall (chuẩn hóa)]]&Plan_2026[[#This Row],[Địa chỉ đầy đủ]] -> Manwah Lê Đức Thọ/Hàm nghiLê Đức Thọ/Hàm nghi, Mỹ Đình 1, Nam Từ Liêm, Hà Nội
A95: 90 | B95: 10UTNOBUD07 | C95: Universal Tea | D95: Phạm Minh Đức | E95: 2026 | F95: 1 | G95: 3 | H95: 7 | J95: HN | K95: Bắc | L95: Hà Nội | M95: VNM.27_1 | N95: Nam Từ Liêm | O95: Mỹ Đình 1 | P95: Mễ Trì | Q95: Chân đế | R95: 8 - 12 | S95: 8 - 12 | T95: 100 - 150 | U95: 100 - 150 | V95: 1 | W95: UT2 | X95: The Manor | Z95: 130tr | AB95: New | AC95: Hủy bỏ | AE95: 0 | AH95: UT | AI95: 46082 | AJ95: 3 | AK95: Mỹ Đình 1, Nam Từ Liêm, Hà Nội | AL95: Mễ Trì, Mỹ Đình 1, Nam Từ Liêm, Hà Nội | AM95: VNM.27.19.4_1 | AN95: Universal Tea Chân đế | AO95: Universal Tea|Mỹ Đình 1, Nam Từ Liêm, Hà Nội | AP95: 7556 | AQ95: 110/584 | AR95: 368/11159 | AS95: 16 | AT95: 15/16 | AW95: =Plan_2026[[#This Row],[Tên brand]]&" "&Plan_2026[[#This Row],[Trục đường chính]]&Plan_2026[[#This Row],[Tên mall (chuẩn hóa)]]&Plan_2026[[#This Row],[Địa chỉ đầy đủ]] -> Universal Tea Mễ TrìMễ Trì, Mỹ Đình 1, Nam Từ Liêm, Hà Nội
A96: 91 | B96: TCHNEW068 | C96: The Coffee House | D96: Nguyễn Thị Thanh | E96: 2026 | F96: 2 | G96: 6 | H96: 10 | J96: HN | K96: Bắc | L96: Hà Nội | M96: VNM.27_1 | N96: Nam Từ Liêm | O96: Mỹ Đình 1 | P96: Khu đô thị The Manor, Đường Mễ Trì | Q96: Mall | R96: 6 - 8 | S96: 6 - 8 | T96: 100 - 150 | U96: 100 - 150 | V96: 1 | W96: UT1 | X96: The Garden | Y96: The Garden Shopping Center | Z96: 132 | AB96: New | AC96: Chưa có | AE96: 0 | AH96: TCH | AI96: 46174 | AJ96: 6 | AK96: Mỹ Đình 1, Nam Từ Liêm, Hà Nội | AL96: Khu đô thị The Manor, Đường Mễ Trì, Mỹ Đình 1, Nam Từ Liêm, Hà Nội | AM96: VNM.27.19.4_1 | AN96: The Coffee House Mall | AO96: The Coffee House|The Garden Shopping Center | AP96: 7556 | AQ96: 110/584 | AR96: 368/11159 | AS96: 81 | AT96: 54/81 | AW96: =Plan_2026[[#This Row],[Tên brand]]&" "&Plan_2026[[#This Row],[Trục đường chính]]&Plan_2026[[#This Row],[Tên mall (chuẩn hóa)]]&Plan_2026[[#This Row],[Địa chỉ đầy đủ]] -> The Coffee House Khu đô thị The Manor, Đường Mễ TrìThe Garden Shopping CenterKhu đô thị The Manor, Đường Mễ Trì, Mỹ Đình 1, Nam Từ Liêm, Hà Nội
A97: 92 | B97: TCHNEW077 | C97: The Coffee House | D97: Nguyễn Thị Thanh | E97: 2026 | F97: 3 | G97: 7 | H97: 11 | J97: HN | K97: Bắc | L97: Hà Nội | M97: VNM.27_1 | N97: Nam Từ Liêm | O97: Mỹ Đình 1 | P97: 16 Phạm Hùng | Q97: Chân đế | R97: 6 - 8 | S97: 6 - 8 | T97: 100 - 150 | U97: 100 - 150 | V97: 1 | W97: UT1 | X97: Mỹ Đình 1 - Sunshine Center | Z97: 132 | AB97: New | AC97: Chưa có | AE97: 0 | AH97: TCH | AI97: 46204 | AJ97: 7 | AK97: Mỹ Đình 1, Nam Từ Liêm, Hà Nội | AL97: 16 Phạm Hùng, Mỹ Đình 1, Nam Từ Liêm, Hà Nội | AM97: VNM.27.19.4_1 | AN97: The Coffee House Chân đế | AO97: The Coffee House|Mỹ Đình 1, Nam Từ Liêm, Hà Nội | AP97: 7556 | AQ97: 110/584 | AR97: 368/11159 | AS97: 81 | AT97: 54/81 | AW97: =Plan_2026[[#This Row],[Tên brand]]&" "&Plan_2026[[#This Row],[Trục đường chính]]&Plan_2026[[#This Row],[Tên mall (chuẩn hóa)]]&Plan_2026[[#This Row],[Địa chỉ đầy đủ]] -> The Coffee House 16 Phạm Hùng16 Phạm Hùng, Mỹ Đình 1, Nam Từ Liêm, Hà Nội
A98: 93 | B98: 10DNNOBUD04 | C98: Dao Niu Guo | D98: Nguyễn Ngọc Hà | E98: 2026 | F98: 3 | G98: 7 | H98: 11 | J98: HN | K98: Bắc | L98: Hà Nội | M98: VNM.27_1 | N98: Hoàn Kiếm | O98: Hàng Trống | P98: Lê Thái Tổ | Q98: Shophouse | R98: 8 - 12 | S98: 8 - 12 | T98: 200 - 300 | U98: 200 - 300 | V98: 1 | W98: UT1 | Z98: 160 | AB98: Convert | AC98: Đã ký | AE98: 1 | AF98: Convert từ MW Lê Thái Tổ Khu dân cư đông đúc, nhiều VP và khu người HQ | AH98: DN | AI98: 46204 | AJ98: 7 | AK98: Hàng Trống, Hoàn Kiếm, Hà Nội | AL98: Lê Thái Tổ, Hàng Trống, Hoàn Kiếm, Hà Nội | AM98: VNM.27.14.13_1 | AN98: Dao Niu Guo Shophouse | AO98: Dao Niu Guo|Hàng Trống, Hoàn Kiếm, Hà Nội | AP98: 7551 | AQ98: 111/584 | AR98: 369/11159 | AS98: 6 | AT98: 4/6 | AW98: =Plan_2026[[#This Row],[Tên brand]]&" "&Plan_2026[[#This Row],[Trục đường chính]]&Plan_2026[[#This Row],[Tên mall (chuẩn hóa)]]&Plan_2026[[#This Row],[Địa chỉ đầy đủ]] -> Dao Niu Guo Lê Thái TổLê Thái Tổ, Hàng Trống, Hoàn Kiếm, Hà Nội
A99: 94 | B99: 10NRNOBUD02 | C99: Ngonya | D99: Hà Anh Tuấn | E99: 2026 | F99: 3 | G99: 7 | H99: 11 | J99: HN | K99: Bắc | L99: Hà Nội | M99: VNM.27_1 | N99: Hai Bà Trưng | O99: Phạm Đình Hổ | P99: Thi Sách | Q99: Shophouse | R99: 5 - 6 | S99: <= 6 | T99: 50 | U99: 30 - 50 | V99: 1 | W99: UT2 | Z99: - | AA99: < 50 tr | AB99: New | AC99: Chưa có | AE99: 0 | AH99: YA | AI99: 46204 | AJ99: 7 | AK99: Phạm Đình Hổ, Hai Bà Trưng, Hà Nội | AL99: Thi Sách, Phạm Đình Hổ, Hai Bà Trưng, Hà Nội | AM99: VNM.27.12.13_1 | AN99: Ngonya Shophouse | AO99: Ngonya|Phạm Đình Hổ, Hai Bà Trưng, Hà Nội | AP99: 15551 | AQ99: 60/584 | AR99: 169/11159 | AS99: 0 | AT99: 1/0 | AW99: =Plan_2026[[#This Row],[Tên brand]]&" "&Plan_2026[[#This Row],[Trục đường chính]]&Plan_2026[[#This Row],[Tên mall (chuẩn hóa)]]&Plan_2026[[#This Row],[Địa chỉ đầy đủ]] -> Ngonya Thi SáchThi Sách, Phạm Đình Hổ, Hai Bà Trưng, Hà Nội
A100: 95 | B100: 10SMNOBUD05 | C100: Sumogoya | D100: Hà Anh Tuấn | E100: 2026 | F100: 3 | G100: 7 | H100: 11 | J100: HN | K100: Bắc | L100: Hà Nội | M100: VNM.27_1 | N100: Hoàn Kiếm | O100: Tràng Tiền | P100: Hai Bà Trưng | Q100: Shophouse | R100: 6 - 8 | S100: 6 - 8 | T100: 220 - 250 | U100: 200 - 300 | V100: 1 | W100: UT2 | Z100: - | AB100: New | AC100: Chưa có | AE100: 0 | AG100: đổi phường từ Hai Bà Trưng sang | AH100: SM | AI100: 46204 | AJ100: 7 | AK100: Tràng Tiền, Hoàn Kiếm, Hà Nội | AL100: Hai Bà Trưng, Tràng Tiền, Hoàn Kiếm, Hà Nội | AM100: VNM.27.14.18_1 | AN100: Sumogoya Shophouse | AO100: Sumogoya|Tràng Tiền, Hoàn Kiếm, Hà Nội | AP100: 9088 | AQ100: 99/584 | AR100: 315/11159 | AS100: 11 | AT100: 6/11 | AW100: =Plan_2026[[#This Row],[Tên brand]]&" "&Plan_2026[[#This Row],[Trục đường chính]]&Plan_2026[[#This Row],[Tên mall (chuẩn hóa)]]&Plan_2026[[#This Row],[Địa chỉ đầy đủ]] -> Sumogoya Hai Bà TrưngHai Bà Trưng, Tràng Tiền, Hoàn Kiếm, Hà Nội
...

Sheet For consider
A1: Region | B1: SBU | C1: BR | D1: PC BUD | E1: PC | F1: Đã đổ fund | G1: Store | H1: Ngày dự kiến khới công | I1: Ngày dự kiến có sales trở lại | J1: Note | K1: Convert from | L1: FM | M1: Status | N1: Thời điểm trình | O1: CAPEX + Pre Op Ex | P1: CAPEX for consider | Q1: Pre - Opening and Restoring exp | R1: NSO | S1: Convert | T1: Reno | U1: Chi phí thiết kế | V1: Dự án CĐS | W1: CCDC | X1: Note_1 | Y1: Forecast Sales per FM | Z1: BE Sales per FM | AA1: CM per FM | AB1: UC per FM | AC1: Link FM | AD1: Status_2 | AE1: Total Capex | AF1: Total Capex exclude Other Exp | AG1: Status_1 | AH1: Column31
C2: CD | D2: 30CDNEW13 | E2: 30CD500101 | F2: Check | G2: Cloud Pot Aeon Mall Đà Nẵng | J2: Đã đổ Fund 2025 | P2: 4390140593 | Y2: 1213 | Z2: 900 | AD2: New
C3: CJ | D3: 30CJ4992 | E3: 30CJ499201 | F3: Check | G3: Crystal Jade Parc Mall | J3: Đã đổ Fund 2025 | P3: 4782772646 | Y3: 1136 | Z3: 909 | AC3: FM2 CJ PM_Q8 .xlsx | AD3: New
C4: CK | D4: 10CK5071 | E4: 10CK501801 | F4: Check | G4: Chixmax Vincom Thái Bình | J4: Đã đổ Fund 2025 | P4: 2747605922 | Y4: 562 | Z4: 337 | AC4: FM_Chixmax_Vincom Thái Bình_21.11.2025_V2.xlsx | AD4: New
C5: DN | D5: 30DNNOBUD01 | F5: 30DN505501 | G5: Dao Niu Guo 2/9 Hải Châu Đà Nẵng | P5: 5554294575 | Y5: 1501 | Z5: 825 | AC5: FM1 DNG 1 2.9 Hải Châu DNG_v1.xlsx | AD5: New
C6: DN | D6: 30DNNEW4 | E6: 30DN500601 | F6: 30DN500601 | G6: Dao Niu Guo Đà Lạt | J6: 0 | P6: 3177056348 | Y6: 1150 | Z6: 920 | AC6: FM1_Convert DNG Đà Lạt (từ MW)_(đã view Fin)_final.xlsx | AD6: Convert
C7: Dn | D7: 10DNNOBUD06 | E7: 10DN499301 | F7: Check | G7: Dao Niu Guo Tôn Đức Thắng Vĩnh Yên | J7: Đã đổ Fund 2025 | P7: 677780000 | Y7: 677 | Z7: 380 | AC7: FM_convert Dao Niu Gou Vĩnh Yên 1.xlsx | AD7: Convert
C8: Dn | D8: 10DNNOBUD07 | E8: Check | F8: Check | G8: Dao Niu Guo Bắc Ninh | J8: Chưa có Costcenter nên chưa gửi thông tin đổ fund | K8: Shogun Bắc Ninh | P8: 1626318536 | Y8: 600 | Z8: 800 | AC8: FM1 Convert DNG NĐĐ Bắc Ninh (từ SG)_v3_final.xlsx | AD8: Convert
C9: Dn | D9: 30DNNOBUD06 | F9: 30DN506701 | G9: Dao Niu Guo Bà Rịa Vũng Tàu | K9: Kpub Vũng Tàu | P9: 2055347847 | Y9: 1101 | Z9: 826 | AC9: FM1 KP - Vũng Tàu conver DNG_v4_final.xlsx | AD9: Convert
C10: DN | D10: 30DNNOBUD10 | E10: Check | F10: Check | G10: Dao Niu Guo Aeon Huế | J10: Chưa có Costcenter nên chưa gửi thông tin đổ fund | K10: Cloud Pot Aeon Huế | P10: 1763180300 | Y10: 1302 | Z10: 1000 | AC10: FM1_Convert DNG Aeon Huế (từ CD-KK)_v1.xlsx | AD10: Convert
C11: DN | D11: 10DNNOBUD08 | E11: 10DN5046 | F11: 10DN504601 | G11: Dao Niu Guo Cao Thắng Thanh Hóa | P11: 2422170370 | Y11: 915 | Z11: 640 | AC11: FM1 Convert DNG Thanh Hóa (từ HC)_v3 final.xlsx | AD11: Convert
C12: DN | D12: 30DN4958 | E12: 30DN495801 | F12: Check | G12: Dao Niu Guo Vạn Hạnh Mall | J12: Đã đổ Fund 2025 | P12: 1453000000 | Y12: 1788 | Z12: 1000 | AC12: 1. FM Convert HT-DNG VHM 29082025_v1.xlsx
C13: DN | D13: 30DN4960 | E13: 30DN496001 | F13: Check | G13: Dao Niu Guo Diamond Plaza | J13: Đã đổ Fund 2025 | P13: 2168603758 | Y13: 1138 | Z13: 911 | AC13: 3. FM Convert ISS-DNG Diamond 29082025_v1.xlsx
C14: FC | D14: FCNEW002 | E14: Check | F14: Check | G14: Flychef Điện Biên Phủ HCM | J14: Thuộc TCH | P14: 1810137314 | Y14: 648 | Z14: 497 | AC14: FM2_FC Dien Bien Phu_v3.xlsx
C15: FC | D15: FCNEW003 | E15: Check | F15: Check | G15: Flychef Nguyễn Thái Bình HCM | J15: Thuộc TCH | P15: 1628542108 | Y15: 810 | Z15: 810 | AC15: FM2_FC Nguyen Thai Binh_v1.xlsx
C16: GG | D16: 10GGNOBUD12 | F16: 10GG506201 | G16: Gogi House Aeon Hải Dương | P16: 3922000000 | Y16: 1197 | Z16: 861 | AC16: FM1 - GG Aeon Hải Dương.xlsx | AD16: New
C17: GG | D17: 10GGNEW42 | E17: Check | F17: Check | G17: Gogi House Aeon Thanh Hóa | J17: Chưa có Costcenter nên chưa gửi thông tin đổ fund | P17: 4420070485 | Y17: 1308 | Z17: 1046 | AC17: FM1 - GG AEON THANH HÓA.xlsx | AD17: New
C18: GG | D18: 10GGNOBUD21 | F18: 10GG506601 | G18: Gogi House Yên Bái | P18: 2163220000 | Y18: 567 | Z18: 283 | AC18: Template_FM1 - GG Yên Bái.xlsx | AD18: New
C19: GG | D19: 30GGNEW02 | F19: 30GG502501 | G19: Gogi Viettel Building Đường 3.2 | P19: 2.8362592e+09 | Y19: 1289 | Z19: 606 | AC19: FM GOGI VIETTEL convert - review.xlsx
C20: GG | D20: 30GGNEW38 | F20: 30GG503101 | G20: Gogi Ninh Thuận | P20: 3.6387141e+09 | Y20: 950 | Z20: 541 | AC20: FM2 GGH NINH THUẬN.xlsx
C21: GG | D21: 30GGNOBUD01 | E21: Check | F21: Check | G21: Gogi Pandora Truong Chinh | J21: Chưa có Costcenter nên chưa gửi thông tin đổ fund | P21: 3989230000 | Y21: 1071 | Z21: 381 | AC21: FM_ Gogi Pandora Trường Chinh 02.02.2026.xlsx
C22: GG | D22: 30GGNEW20 | E22: 30GG500001 | F22: Check | G22: Gogi Aeon Mall Đà Nẵng | J22: Đã đổ Fund 2025 | P22: 5008390000 | Y22: 1536 | Z22: 833 | AC22: FM1 GG - Aeon Đà Nẵng_approved.xlsx
C23: KK | D23: 30KKNEW09 | E23: 30KK500201 | F23: Check | G23: Kichi Kichi Aeon Mall Đà Nẵng | J23: Đã đổ Fund 2025 | P23: 4024134624 | Y23: 1269 | Z23: 555 | AC23: FM1 KK - Aeon Đà Nẵng (form mới 2025).xlsx
C24: KK | D24: 10KKNOBUD10 | E24: 10KK498701 | F24: Check | G24: Kichi Kichi Hoàng Đạo Thúy | J24: Đã đổ Fund 2025 | P24: 2.3876028e+09 | Y24: 875 | Z24: 453 | AC24: KK_HĐT_Convert_v2010.xlsx
C25: KK | D25: 30KKNEW23 | F25: 30KK503201 | G25: Kichi Kichi Ninh Thuận | P25: 3.5503287e+09 | Y25: 886 | Z25: 576 | AC25: FM2 KK NINH THUẬN Copy.xlsx
C26: KK | D26: 10KKNEW04 | F26: 10KK504201 | G26: Kichi Kichi Aeon Hạ Long | P26: 4.0529271e+09 | Y26: 1268 | Z26: 825 | AC26: FM1 - KICHI AEON HẠ LONG (1).xlsx
C27: KK | D27: 10KKNEW22 | F27: 10KK503601 | G27: Kichi Kichi Aeon Thanh Hóa | P27: 4.1586912e+09 | Y27: 1252 | Z27: 826 | AC27: FM1 - KICHI AEON THANH HÓA 3.xlsx
C28: KK | D28: 10KK4987 | E28: 10KK498701 | F28: Check | G28: KK Hoàng Đạo Thúy | J28: Đã đổ Fund 2025 | P28: 2387602817 | Y28: 875 | Z28: 525 | AC28: KK_HĐT_Convert_v2010.xlsx
C29: LC | D29: 30LC4964 | F29: 30LC496401 | G29: LCLC Lotte Mart Phú Thọ HCM | P29: 2.8992872e+09 | Y29: 2021 | Z29: 1507 | AC29: 1. LCLC Lotte HCM _ FM_19122025 v2.xlsb
C30: MW | D30: 30MWNEW9 | E30: 30MW500301 | F30: 30MW500301 | G30: Manwah Aeon Mall Đà Nẵng | P30: 6.0120789e+09 | Y30: 2159 | Z30: 557 | AC30: FM1_MW Aeon Đà Nẵng_040925_final.xlsx
C31: MW | D31: 30MWNEW2 | F31: 30MW498401 | G31: Manwah Aeon Bình Tân | P31: 4.1498776e+09 | Y31: 3948 | Z31: 1579 | AC31: FM1_MW AEON BT MỞ RỘNG - TỔNG 470M2-final.xlsx
C32: MW | D32: 10MWNOBUD03 | F32: 10MW503401 | G32: Manwah Aeon Thanh Hóa | P32: 4.5612973e+09 | Y32: 1500 | Z32: 1035 | AC32: FM1 - MW AEON THANH HÓA_final.xlsx
C33: PZ | D33: 10PZ4944 | E33: 10PZ494401 | F33: Check | G33: Pizza Royal Nguyễn Trãi | J33: Đã đổ Fund 2025 | Y33: 1101 | Z33: 881 | AC33: FM2_PZ360 Royal_14112025.xlsx
C34: SM | D34: 30SMNOBUD08 | E34: 30SM502301 | F34: Check | G34: Sumo Grand Park HCM | J34: Chưa đổ fund | P34: 4574303005 | Y34: 1249 | Z34: 619 | AC34: FM_SM_Grand Park.xlsx
C35: SS | D35: 30SSNEW08 | F35: 30SS505401 | G35: Isushi 2.9 Đà Nẵng | P35: 4.9212826e+09 | Y35: 1501 | Z35: 490 | AC35: SSFM1 Template_FM_2.9 (1).xlsx
C36: SS | D36: 10SSNEW03 | F36: 10SS506401 | G36: Isushi Aeon Hạ Long | P36: 6.0127156e+09 | Y36: 1524 | Z36: 1336 | AC36: FM1_Isushi Aeon mall Hạ Long (2).xlsx
C37: SS | D37: 10SSNOBUD03 | F37: 10SS505301 | G37: Isushi 90 Trần Thái Tông HN | P37: 6.6091839e+09 | Y37: 1725 | Z37: 1307 | AC37: FM1_90 Trần Thái Tông_FC cmt 1.xlsx
C38: SS | D38: 10SSNEW01 | E38: 10SS498101 | F38: Check | G38: Isushi Aeon Mall Hà Đông | J38: Đã đổ fund chi phí thiết kế | P38: 5476713254 | Y38: 1601 | Z38: 648 | AC38: FM 5 years_iSushi Aeon HĐ tầng 2.xlsx
C39: UP | D39: 10UP4966 | E39: 10UP496601 | F39: Check | G39: Union Pizza Vincom Bà Triệu | J39: Đã đổ Fund 2025 | P39: 982637600 | Y39: 1249 | Z39: 1000 | AC39: https://goldengatetradeservice-my.sharepoint.com/:x:/r/personal/chuong_nd_ggg_com_vn/_layouts/15/Doc.aspx?sourcedoc=%7B1731D71E-3D18-4025-8CB1-1BA23C1BB35D%7D&file=FM_28082025_UP%20VIN%20BT%20FM2.xlsx&action=default&mobileredirect=true
C40: WY | D40: 10WYNOBUD02 | F40: 10WY507401 | G40: Wow Lotte Võ Chí Công | P40: 3451081497 | Y40: 1147 | Z40: 1044 | AC40: FM1_Mini Lotte Vcc 18.01.2025 138m2 Fin 04.02 - TOS 13% - V2.xlsx | AD40: New
C41: WY | D41: 10WYNOBUD01 | E41: Check | F41: Check | G41: Wow Go Thăng Long | J41: Chưa có Costcenter nên chưa gửi thông tin đổ fund | P41: 4268258961 | Y41: 1384 | Z41: 996 | AC41: FM_WY_GO_slot_SX.xlsx | AD41: New
C42: WY | D42: 30WYNOBUD01 | E42: 30WY502401 | F42: Check | G42: Wow Vincom Mega Mall Grand Park | J42: Chưa đổ fund | P42: 4779303005 | Y42: 1249 | Z42: 687 | AC42: FM_SM_Grand Park.xlsx | AD42: New
C43: YT | D43: 30YT5008 | E43: 30YT500801 | F43: Check | G43: Yutang Lotte Tân Bình | J43: Đã đổ Fund 2025 | P43: 1942694153 | Y43: 703 | Z43: 507 | AC43: FM1_Lotte Tân Bình_YT 4.xlsx
C44: YT | D44: 30YTNEW02 | F44: 30YT501001 | G44: Yutang Vạn Hạnh Mall | P44: 2817020607 | Y44: 804 | Z44: 611 | AC44: FM2 Yutang - Vạn Hạnh Mall_v2.xlsx
C45: YT | D45: 30YT4995 | E45: 30YT499501 | F45: Check | G45: Yutang Bcon Dĩ An Bình Dương | J45: Đã đổ Fund 2025 | P45: 1256289972 | Y45: 245 | Z45: 190 | AC45: FM2_ YT Bcon Dĩ An BD_211125.xlsx
C46: GG | D46: 30GG4994 | E46: 30GG499401 | F46: Check | G46: Gogi Bcon Dĩ An Bình Dương | J46: Đã đổ Fund 2025 | P46: 3745531446 | Y46: 892 | Z46: 714 | AC46: FM2_GG Bcon Binh Duong_approved.xlsx
C47: UP | D47: 30UP4954 | E47: 30UP495401 | F47: 30UP495401 | G47: Union Pizza Xuân Thủy HCM | P47: 5291155312 | Y47: 1484 | Z47: 1000 | AC47: https://goldengatetradeservice-my.sharepoint.com/:x:/r/personal/chuong_nd_ggg_com_vn/_layouts/15/Doc.aspx?sourcedoc=%7B17048255-B84D-445E-9BE9-2E2E3CD6C7FE%7D&file=FM2.1_07112025_UP%20Xuan%20Thuy.xlsx&action=default&mobileredirect=true
C48: CV | D48: 10CV5020 | E48: 10CV502001 | F48: 10CV502001 | G48: Chả cá Vạn Vạn GO! Thăng Long | P48: 500000000 | Y48: 690 | Z48: 552 | AC48: FM1_Chả cá Go Thăng Long_v2.1.xlsx
C49: GG | D49: 30GG5007 | E49: 30GG500701 | F49: Check | G49: GG Lotte Tân Bình | J49: Đã đổ Fund 2025 | P49: 3427626691 | Y49: 1018 | Z49: 800 | AC49: FM1_Lotte Tân Bình_GG_convert_approved.xlsx
C50: GG | D50: 30GG5012 | E50: 30GG501201 | F50: Check | G50: GG Nguyễn Văn Lạc | J50: Đã đổ Fund 2025 | P50: 784233333 | Y50: 518 | Z50: 648 | AC50: FM_Gogi Nguyễn Văn Lạc convert_approved.xlsx | AD50: Convert
C51: GG | D51: 10GG4883 | E51: 10GG488301 | F51: 10GG488301 | G51: GG Hanoi Centre NTH | P51: 5422376292 | Y51: 1420 | Z51: 1161 | AC51: FM2 - GG Nguyễn Thái Học_approved.xlsx | AD51: New
C52: KK | D52: 10KK4858 | E52: 10KK485801 | F52: Check | G52: KK HN Centre NTH | J52: Đã đổ Fund 2025 | P52: 3776950805 | Y52: 990 | Z52: 766 | AC52: FM2 Kichi New Nguyễn Thái Học_V2.xlsx
C53: KK | D53: 30KK4996 | E53: 30KK499601 | F53: Check | G53: KK Bcons Bình Dương | J53: Đã đổ Fund 2025 | P53: 3045267457 | Y53: 689 | Z53: 358 | AC53: FM2_ KK Bcon Dĩ An BD_171125.xlsx
C54: MW | D54: 10MWNEW18 | E54: 10MW498901 | F54: Check | G54: Manwah Bắc Giang | J54: Đã đổ Fund 2025 | P54: 996886655 | Y54: 606 | Z54: 485 | AC54: FM Convert MWBG_16112025.xlsx
C55: IP | D55: 10IP4760 | E55: 10IP476001 | F55: Check | J55: Đã đổ Fund 2025 | P55: 845450946 | Y55: 1092 | Z55: 700 | AA55: 324 | AB55: 278 | AC55: 22_12_FM_PHỞ INN x TCH Nội Bài T1_Gate6.xlsx
C56: WY | D56: 10WYNOBUD03 | E56: Check | F56: Check | G56: Wow Yakiniku 90 Duy Tân | J56: Chưa có Costcenter nên chưa gửi thông tin đổ fund | P56: 3140150236 | Y56: 1016 | Z56: 813 | AA56: 181 | AB56: 111 | AC56: https://goldengatetradeservice-my.sharepoint.com/:x:/g/personal/thang_td_ggg_com_vn/IQCFAByVjckRQaX0K5e2rvTGAS1Bi5sCnKVb9w2xJgCDISE
A57: HO | C57: HO | D57: 40HO105002 | E57: 40HO105002 | G57: Ban Giám đốc | P57: 36200000 | Q57: 0 | R57: 0 | S57: 0 | T57: 0 | U57: 0 | V57: 0 | W57: 36200000 | AC57: HO không có FM | AE57: 36200000 | AF57: 36200000
A58: North | C58: AS | D58: 10ASNEW01 | E58: 10AS503001 | G58: Ashima Aeon Mall Hà Đông | L58: FM1 | N58: 46017 | O58: 5836753938 | P58: 5836753938 | Q58: 241928938 | R58: 5594825000 | S58: 0 | T58: 0 | U58: 0 | V58: 0 | W58: 0 | Y58: 1620 | Z58: 1264 | AC58: FM1_ASM Aeon Hà Đông 09.12 1.xlsx | AE58: 5836753938 | AF58: 5594825000 | AG58: New
A59: North | C59: AS | D59: 10ASNEW05 | E59: 10AS502901 | G59: Ashima Vincom Center Metropolis | L59: FM1 | N59: 46017 | O59: 4985038938 | P59: 4985038938 | Q59: 322038938 | R59: 4663000000 | S59: 0 | T59: 0 | U59: 0 | V59: 0 | W59: 0 | AC59: FM1_ASM Metropolis_25.11.2025 1.xlsx | AE59: 4985038938 | AF59: 4663000000
A60: South | C60: MW | D60: 30MWNEW2 | E60: 30MW498401 | G60: Manwah Aeon Bình Tân | K60: SS Aeon Bình Tân | L60: FM1 | N60: 46021 | O60: 4.1498776e+09 | P60: 4.1498776e+09 | Q60: 2.1584558e+08 | R60: 0 | S60: 3473512000 | T60: 460520000 | U60: 0 | V60: 0 | W60: 0 | Y60: 3948 | Z60: 1579 | AC60: FM1_MW AEON BT MỞ RỘNG - TỔNG 470M2-final.xlsx | AE60: 4.1498776e+09 | AF60: 3934032000 | AG60: Convert
A61: South | C61: KK | D61: 30KK4258 | E61: 30KK425801 | G61: Kichi Kichi Cao Thắng Q3 | L61: FM1 | M61: FM2 | N61: 46028 | O61: 3134535760 | P61: 3134535760 | Q61: 279000000 | R61: 0 | S61: 0 | T61: 2855535760 | U61: 0 | V61: 0 | W61: 0 | AC61: Reno_KK Cao Thắng Q3_30KK4258 | AE61: 3134535760 | AF61: 2855535760
A62: South | C62: KK | D62: 30KK4300 | E62: 30KK430001 | G62: Kichi Kichi BigC Thủ Dầu Một Bình Dương | L62: FM1 | N62: 46028 | O62: 1476811150 | P62: 1476811150 | Q62: 149000000 | R62: 0 | S62: 0 | T62: 1327811150 | U62: 0 | V62: 0 | W62: 0 | AC62: FM1_ KK Go TDM Renovate.xlsx | AE62: 1476811150 | AF62: 1327811150
A63: South | C63: KK | D63: 30KKNEW23 | E63: 30KK503201 | G63: Kichi Kichi Ninh Thuận | L63: FM1 | M63: FM2 | N63: 46034 | O63: 4848946707 | P63: 4848946707 | R63: 4848946707 | S63: 0 | T63: 0 | U63: 0 | V63: 0 | W63: 0 | AC63: FM1 KK NINH THUẬN (đã view với Fin).xlsx | AE63: 4848946707 | AF63: 4848946707 | AG63: New
A64: South | C64: KK | D64: 30KK4284 | E64: 30KK428401 | G64: Kichi Kichi An Dươnng Vương Q5 | L64: Vote Tổ 33 | P64: 70000000 | R64: 0 | S64: 0 | T64: 0 | U64: 70000000 | V64: 0 | W64: 0 | AE64: 70000000 | AF64: 70000000
A65: South | C65: KK | D65: 30KK4272 | E65: 30KK427201 | G65: Kichi Kichi Aeon Mall Q.Bình Tân | L65: Vote Tổ 33 | P65: 70000000 | R65: 0 | S65: 0 | T65: 0 | U65: 70000000 | V65: 0 | W65: 0 | AE65: 70000000 | AF65: 70000000
A66: North | C66: CK | D66: 10CKNEW02 | E66: 10CK502801 | G66: Chixmax Aeon Mall Hà Đông | L66: FM1 | N66: 46021 | O66: 1840722637 | P66: 1840722637 | Q66: 45722637 | R66: 1795000000 | S66: 0 | T66: 0 | U66: 0 | V66: 0 | W66: 0 | Y66: 720 | Z66: 504 | AC66: FM1_Chixmax Aeon Mall Hà Đông.xlsx | AE66: 1840722637 | AF66: 1795000000 | AG66: New
A67: South | C67: KK | D67: 30KK4259 | E67: 30KK425901 | G67: Kichi Kichi VC Đồng Khởi Q1 | L67: FM1 | N67: 46031 | O67: 4363842161 | P67: 4363842161 | Q67: 480574721 | R67: 0 | S67: 0 | T67: 3883267440 | U67: 0 | V67: 0 | W67: 0 | AC67: FM1_KK VC ĐK (2) (1).xlsx | AE67: 4363842161 | AF67: 3883267440
A68: South | C68: GG | D68: 30GGNEW38 | E68: 30GG503101 | G68: Gogi House Ninh Thuận | L68: FM1 | N68: 46034 | O68: 4588734394 | P68: 4588734394 | R68: 4588734394 | S68: 0 | T68: 0 | U68: 0 | V68: 0 | W68: 0 | AC68: FM1 GGH NINH THUẬN.xlsx | AE68: 4588734394 | AF68: 4588734394 | AG68: New
A69: South | C69: GG | D69: 30GGNEW01 | E69: 30GG502601 | G69: Gogi House Garden Mall | K69: 1 phần MW Garden Mall | L69: FM1 | N69: 46034 | O69: 2707387500 | P69: 2707387500 | Q69: 235387500 | R69: 0 | S69: 2472000000 | T69: 0 | U69: 0 | V69: 0 | W69: 0 | Y69: 1138 | Z69: 500 | AC69: FM GOGI GARDEN MALL - review v2.xlsx | AE69: 2707387500 | AF69: 2472000000 | AG69: Convert
A70: South | C70: GG | D70: 30GGNOBUD11 | E70: 30GG502501 | G70: Gogi House Viettell | K70: 1 phần MW Viettel | L70: FM1 | N70: 46034 | O70: 2594142000 | P70: 2594142000 | Q70: 230592000 | R70: 0 | S70: 2363550000 | T70: 0 | U70: 0 | V70: 0 | W70: 0 | AC70: FM GOGI VIETTEL convert - review.xlsx | AE70: 2594142000 | AF70: 2363550000
A71: North | C71: DN | D71: 10DN4929 | E71: 10DN492901 | G71: Dao Niu Guo Lê Đức Thọ | L71: FM1 | N71: 46041 | O71: 4348679976 | P71: 4348679976 | Q71: 170300000 | R71: 0 | S71: 0 | T71: 4138679976 | U71: 39700000 | V71: 0 | W71: 0 | AC71: FM Reno_DNG Lê Đức Thọ GĐ2-final.xlsx | AE71: 4348679976 | AF71: 4178379976
A72: North | C72: DN | D72: 10DNNOBUD03 | E72: 10DN501601 | G72: Dao Niu Guo Trần Huy Liệu | K72: CD Trần Huy Liệu | L72: FM1 | N72: 46039 | O72: 3163939412 | P72: 3163939412 | Q72: 389814457 | R72: 0 | S72: 2593224955 | T72: 0 | U72: 180900000 | V72: 0 | W72: 0 | Y72: 1600 | Z72: 886 | AC72: FM convert_DNG Trần Huy Liệu 23.1.26_final.xlsx | AE72: 3163939412 | AF72: 2774124955 | AG72: Convert
A73: North | C73: DN | D73: 10DNNEW5 | E73: 10DN501501 | G73: Dao Niu Guo Mipec Long Biên | K73: VX Mipec Long Biên | L73: FM1 | O73: 6672409930 | P73: 6672409930 | Q73: 148377635 | R73: 0 | S73: 6524032295 | T73: 0 | U73: 0 | V73: 0 | W73: 0 | Y73: 2021 | Z73: 1253 | AC73: FM1_Convert_DNG Mipec LB_v1_final.xlsx | AE73: 6672409930 | AF73: 6524032295 | AG73: Convert
A74: North | C74: DN | D74: 10DNNOBUD04 | E74: 10DN501401 | G74: Dao Niu Guo Lê Thái Tổ | K74: MW Lê Thái Tổ | L74: FM1 | O74: 3028907743 | P74: 3028907743 | Q74: 105532788 | R74: 0 | S74: 2923374955 | T74: 0 | U74: 0 | V74: 0 | W74: 0 | AC74: FM1 convert_DNG Lê Thái Tổ_v2 final.xlsx | AE74: 3028907743 | AF74: 2923374955 | AG74: Convert
A75: North | C75: DN | D75: 10DNNEW2 | E75: 10DN501301 | G75: Dao Niu Guo Thái Hà | K75: MW Thái Hà | L75: FM1 | N75: 46099 | O75: 8096832336 | P75: 8096832336 | Q75: 473075456 | R75: 0 | S75: 7623756880 | T75: 0 | U75: 0 | V75: 0 | W75: 0 | AC75: FM1 convert_DNG Thái Hà_v1 final.xlsx | AE75: 8096832336 | AF75: 7623756880 | AG75: Convert
A76: South | C76: YT | D76: 30YTNOBUD01 | E76: 30YT498201 | G76: Yutang Lotte 84 Mậu Thân CTH | K76: HC Lotte Cần Thơ | L76: FM1 | N76: 46021 | O76: 1330500000 | P76: 1330500000 | Q76: 356500000 | R76: 0 | S76: 974000000 | T76: 0 | U76: 0 | V76: 0 | W76: 0 | Y76: 479 | Z76: 374 | AC76: FM1_Yutang Cần Thơ.xlsx | AE76: 1330500000 | AF76: 974000000 | AG76: Convert
A77: North | C77: LC | D77: 10LC4779 | E77: 10LC487901 | G77: Lách Ca Lách Cách Aeon Long Biên | L77: Vote Tổ 33 | P77: 54864820 | R77: 0 | S77: 0 | T77: 0 | U77: 0 | V77: 0 | W77: 54864820 | AE77: 54864820 | AF77: 54864820
A78: South | C78: KK | D78: 30KK4268 | E78: 30KK426801 | G78: Kichi Kichi Aeon Mall Q.Tân Phú | L78: Vote Tổ 33 | P78: 29400000 | R78: 0 | S78: 0 | T78: 0 | U78: 29400000 | V78: 0 | W78: 0 | AE78: 29400000 | AF78: 29400000
A79: South | C79: KK | D79: 30KK4260 | E79: 30KK426001 | G79: Kichi Kichi Phan Xích Long Q.Phú Nhuận | L79: Vote Tổ 33 | P79: 40900000 | R79: 0 | S79: 0 | T79: 0 | U79: 40900000 | V79: 0 | W79: 0 | AE79: 40900000 | AF79: 40900000
A80: South | C80: KK | D80: 30KK4320 | E80: 30KK432001 | G80: Kichi Kichi Lê Thị Hà Hóc Môn | L80: Vote Tổ 33 | N80: 46029 | P80: 227023645 | R80: 0 | S80: 0 | T80: 227023645 | U80: 0 | V80: 0 | W80: 0 | AC80: Không FM_Reno nhỏ_Cải tạo mặt tiền | AE80: 227023645 | AF80: 227023645
A81: South | C81: KK | D81: 30KK4281 | E81: 30KK428101 | G81: Kichi Kichi Nguyễn Ảnh Thủ Hiệp Thành | L81: Vote Tổ 33 | N81: 46029 | P81: 432160120 | R81: 0 | S81: 0 | T81: 432160120 | U81: 0 | V81: 0 | W81: 0 | AC81: Không FM_Reno nhỏ_Cải tạo mặt tiền | AE81: 432160120 | AF81: 432160120
A82: South | C82: KK | D82: 30KK4314 | E82: 30KK431401 | G82: Kichi Kichi Nguyễn Văn Quá Q12 | L82: Vote Tổ 33 | N82: 46029 | P82: 294267720 | R82: 0 | S82: 0 | T82: 294267720 | U82: 0 | V82: 0 | W82: 0 | AC82: Không FM_Reno nhỏ_Cải tạo mặt tiền | AE82: 294267720 | AF82: 294267720
A83: South | C83: KK | D83: 30KK4276 | E83: 30KK427601 | G83: Kichi Kichi Nguyễn Hồng Đào Q.Tân Bình | L83: Vote Tổ 33 | N83: 46029 | P83: 550736200 | R83: 0 | S83: 0 | T83: 550736200 | U83: 0 | V83: 0 | W83: 0 | AC83: Không FM_Reno nhỏ_Cải tạo mặt tiền | AE83: 550736200 | AF83: 550736200
A84: South | C84: KK | D84: 30KK4315 | E84: 30KK431501 | G84: Kichi Kichi Tân Sơn Nhì Q.Tân Phú | L84: Vote Tổ 33 | N84: 46029 | P84: 420954204 | R84: 0 | S84: 0 | T84: 420954204 | U84: 0 | V84: 0 | W84: 0 | AC84: Không FM_Reno nhỏ_Cải tạo mặt tiền | AE84: 420954204 | AF84: 420954204
A85: South | C85: KK | D85: 30KK4261 | E85: 30KK426101 | G85: Kichi Kichi Nguyễn Trãi Q1 | L85: Vote Tổ 33 | N85: 46029 | P85: 323374300 | R85: 0 | S85: 0 | T85: 323374300 | U85: 0 | V85: 0 | W85: 0 | AC85: Không FM_Reno nhỏ_Cải tạo mặt tiền | AE85: 323374300 | AF85: 323374300
A86: South | C86: KK | D86: 30KK4294 | E86: 30KK429401 | G86: Kichi Kichi Phan Huy Ích Gò Vấp | L86: Vote Tổ 33 | N86: 46029 | P86: 337347067 | R86: 0 | S86: 0 | T86: 337347067 | U86: 0 | V86: 0 | W86: 0 | AC86: Không FM_Reno nhỏ_Cải tạo mặt tiền | AE86: 337347067 | AF86: 337347067
A87: South | C87: KK | D87: 30KK4263 | E87: 30KK426301 | G87: Kichi Kichi Sư Vạn Hạnh Q10 | L87: Vote Tổ 33 | N87: 46029 | P87: 330062688 | R87: 0 | S87: 0 | T87: 330062688 | U87: 0 | V87: 0 | W87: 0 | AC87: Không FM_Reno nhỏ_Cải tạo mặt tiền | AE87: 330062688 | AF87: 330062688
A88: South | C88: KK | D88: 30KK4282 | E88: 30KK428201 | G88: Kichi Kichi Trần Não Thủ Đức | L88: Vote Tổ 33 | N88: 46029 | P88: 326977373 | R88: 0 | S88: 0 | T88: 326977373 | U88: 0 | V88: 0 | W88: 0 | AC88: Không FM_Reno nhỏ_Cải tạo mặt tiền | AE88: 326977373 | AF88: 326977373
A89: North | C89: CV | D89: 10CV5020 | E89: 10CV502001 | G89: Chả cá Vạn Vạn GO! Thăng Long | P89: 8536000 | R89: 0 | S89: 0 | T89: 0 | U89: 0 | V89: 0 | W89: 8536000 | AE89: 8536000 | AF89: 8536000
A90: North | C90: VV | D90: 10VV5302 | E90: 10VV530201 | G90: Vuvuzela Trần Thái Tông Cầu giấy HN | P90: 648000 | R90: 0 | S90: 0 | T90: 0 | U90: 0 | V90: 0 | W90: 648000 | AE90: 648000 | AF90: 648000
A91: North | C91: IP | D91: 10IP4760 | E91: 10IP476001 | G91: Phở Inn Nội Bài | P91: 645000 | R91: 0 | S91: 0 | T91: 0 | U91: 0 | V91: 0 | W91: 645000 | AE91: 645000 | AF91: 645000
A92: South | C92: UP | D92: 30UP4954 | E92: 30UP495401 | G92: Union Pizza Xuân Thủy HCM | P92: 15120000 | R92: 0 | S92: 0 | T92: 0 | U92: 0 | V92: 0 | W92: 15120000 | AE92: 15120000 | AF92: 15120000
A93: North | C93: GG | D93: 10GG4100 | E93: 10GG410001 | G93: Gogi House BigC Thăng Long Cầu giấy HN | L93: Tổ 33 | N93: 46056 | P93: 65350000 | R93: 0 | S93: 0 | T93: 13850000 | U93: 51500000 | V93: 0 | W93: 0 | AC93: Không FM_Reno nhỏ_Bổ sung PCCC | AE93: 65350000 | AF93: 65350000
A94: North | C94: MW | D94: 10MW5140 | E94: 10MW514001 | G94: Manwah Giảng Võ | P94: 7200000 | R94: 0 | S94: 0 | T94: 7200000 | U94: 0 | V94: 0 | W94: 0 | AC94: Không FM_Reno nhỏ_Chống thấm | AE94: 7200000 | AF94: 7200000
A95: HO | C95: HO | D95: 40HO105011 | E95: 40HO105011 | G95: Phòng Quản lý Dự án | P95: 47000000 | R95: 0 | S95: 0 | T95: 0 | U95: 0 | V95: 0 | W95: 47000000 | AC95: HO không có FM | AE95: 47000000 | AF95: 47000000
A96: North | C96: CT | D96: 10CT6524 | E96: 10CT652401 | G96: Canteen Bạch Mai A11-2 | P96: 9000000 | R96: 0 | S96: 0 | T96: 0 | U96: 0 | V96: 0 | W96: 9000000 | AE96: 9000000 | AF96: 9000000
A97: South | C97: LC | D97: Nằm trong capex 2025 | E97: 30LC497501 | G97: Lách Ca Lách Cách Cao Thắng HCM | K97: HC Cao Thắng | L97: FM1 | O97: 2946139634 | P97: 2946139634 | Q97: 265991194 | R97: 0 | S97: 2680148440 | T97: 0 | U97: 0 | V97: 0 | W97: 0 | AC97: FM1_LCLC Cao Thắng_update 09.01.2026.xlsb | AE97: 2946139634 | AF97: 2680148440
A98: North | C98: UN | D98: 10UN4675 | E98: 10UN467501 | G98: Universal Coffee Phan Đình Phùng | P98: 2008800 | R98: 0 | S98: 0 | T98: 0 | U98: 0 | V98: 0 | W98: 2008800 | AE98: 2008800 | AF98: 2008800
A99: South | C99: LC | D99: 30LC4964 | E99: 30LC496401 | G99: Lách Ca Lách Cách Lotte Mart Phú Thọ HCM | K99: BB Lotte Mart | P99: 754407160 | R99: 0 | S99: 754407160 | T99: 0 | U99: 0 | V99: 0 | W99: 0 | AC99: Capex bổ sung so với FM đã trình | AE99: 754407160 | AF99: 754407160 | AG99: Convert
A100: North | C100: LC | D100: 10LC4961 | E100: 10LC496101 | G100: Lách Ca Lách Lách Lê Hồng Phong HP | P100: 20500000 | R100: 0 | S100: 0 | T100: 0 | U100: 0 | V100: 0 | W100: 20500000 | AE100: 20500000 | AF100: 20500000
...

Sheet Detail Capex 2026_Sumibi
A1: Region | B1: SBU | C1: BR | D1: PC BUD | E1: PC | F1: Store | G1: Ngày dự kiến khới công | H1: Ngày dự kiến có sales trở lại | I1: Convert from | J1: FM | K1: Status | L1: Thời điểm trình | M1: CAPEX + Pre Op Ex | N1: CAPEX for consider | O1: Pre - Opening and Restoring exp | P1: NSO | Q1: Convert | R1: Reno | S1: Chi phí thiết kế | T1: Dự án CĐS | U1: CCDC | V1: Total Capex | W1: Total Capex exclude Other Exp | X1: Note | Y1: Forecast Sales per FM | Z1: BE Sales per FM | AA1: CM per FM | AB1: UC per FM | AC1: Link FM | AD1: Status_1
C2: CH | D2: 09HNOCH003 | E2: 09HNOCH003 | F2: Chibo Aeon Hà Đông | N2: 3939433393 | P2: 3939433393 | V2: 3939433393 | W2: 3939433393 | Y2: 1318 | Z2: 988 | AC2: 22072025 FM1 chibo Aeon HĐ.xlsx | AD2: New

Sheet Detail Capex 2026
A1: Region | B1: SBU | C1: BR | D1: PC BUD | E1: PC | F1: Store | G1: Ngày dự kiến khới công | H1: Ngày dự kiến có sales trở lại | I1: Convert from | J1: FM | K1: Status | L1: Thời điểm trình | M1: CAPEX + Pre Op Ex | N1: CAPEX for consider | O1: Pre - Opening and Restoring exp | P1: NSO | Q1: Convert | R1: Reno | S1: Chi phí thiết kế | T1: Dự án CĐS | U1: CCDC | V1: Total Capex | W1: Total Capex exclude Other Exp | X1: Note | Y1: Forecast Sales per FM | Z1: BE Sales per FM | AA1: CM per FM | AB1: UC per FM | AC1: Link FM | AD1: Status_1 | AE1: Column31
A2: HO | C2: HO | D2: 40HO105002 | E2: 40HO105002 | F2: Ban Giám đốc | N2: 36200000 | O2: 0 | P2: 0 | Q2: 0 | R2: 0 | S2: 0 | T2: 0 | U2: 36200000 | V2: 36200000 | W2: 36200000 | AC2: HO không có FM
A3: North | C3: AS | D3: 10ASNEW01 | E3: 10AS503001 | F3: Ashima Aeon Mall Hà Đông | J3: FM1 | L3: 46017 | M3: 5836753938 | N3: 5836753938 | O3: 241928938 | P3: 5594825000 | Q3: 0 | R3: 0 | S3: 0 | T3: 0 | U3: 0 | V3: 5836753938 | W3: 5594825000 | Y3: 1620 | Z3: 1264 | AC3: FM1_ASM Aeon Hà Đông 09.12 1.xlsx | AD3: New
A4: North | C4: AS | D4: 10ASNEW05 | E4: 10AS502901 | F4: Ashima Vincom Center Metropolis | J4: FM1 | L4: 46017 | M4: 4985038938 | N4: 4985038938 | O4: 322038938 | P4: 4663000000 | Q4: 0 | R4: 0 | S4: 0 | T4: 0 | U4: 0 | V4: 4985038938 | W4: 4663000000 | AC4: FM1_ASM Metropolis_25.11.2025 1.xlsx
A5: South | C5: MW | D5: 30MWNEW2 | E5: 30MW498401 | F5: Manwah Aeon Bình Tân | I5: SS Aeon Bình Tân | J5: FM1 | L5: 46021 | M5: 4.1498776e+09 | N5: 4.1498776e+09 | O5: 2.1584558e+08 | P5: 0 | Q5: 3473512000 | R5: 460520000 | S5: 0 | T5: 0 | U5: 0 | V5: 4.1498776e+09 | W5: 3934032000 | Y5: 3948 | Z5: 1579 | AC5: FM1_MW AEON BT MỞ RỘNG - TỔNG 470M2-final.xlsx | AD5: Convert
A6: South | C6: KK | D6: 30KK4258 | E6: 30KK425801 | F6: Kichi Kichi Cao Thắng Q3 | J6: FM1 | K6: FM2 | L6: 46028 | M6: 3134535760 | N6: 3134535760 | O6: 279000000 | P6: 0 | Q6: 0 | R6: 2855535760 | S6: 0 | T6: 0 | U6: 0 | V6: 3134535760 | W6: 2855535760 | AC6: Reno_KK Cao Thắng Q3_30KK4258
A7: South | C7: KK | D7: 30KK4300 | E7: 30KK430001 | F7: Kichi Kichi BigC Thủ Dầu Một Bình Dương | J7: FM1 | L7: 46028 | M7: 1476811150 | N7: 1476811150 | O7: 149000000 | P7: 0 | Q7: 0 | R7: 1327811150 | S7: 0 | T7: 0 | U7: 0 | V7: 1476811150 | W7: 1327811150 | AC7: FM1_ KK Go TDM Renovate.xlsx
A8: South | C8: KK | D8: 30KKNEW23 | E8: 30KK503201 | F8: Kichi Kichi Ninh Thuận | J8: FM1 | K8: FM2 | L8: 46034 | M8: 4848946707 | N8: 4848946707 | P8: 4848946707 | Q8: 0 | R8: 0 | S8: 0 | T8: 0 | U8: 0 | V8: 4848946707 | W8: 4848946707 | AC8: FM1 KK NINH THUẬN (đã view với Fin).xlsx | AD8: New
A9: South | C9: KK | D9: 30KK4284 | E9: 30KK428401 | F9: Kichi Kichi An Dươnng Vương Q5 | J9: Vote Tổ 33 | N9: 70000000 | P9: 0 | Q9: 0 | R9: 0 | S9: 70000000 | T9: 0 | U9: 0 | V9: 70000000 | W9: 70000000
A10: South | C10: KK | D10: 30KK4272 | E10: 30KK427201 | F10: Kichi Kichi Aeon Mall Q.Bình Tân | J10: Vote Tổ 33 | N10: 70000000 | P10: 0 | Q10: 0 | R10: 0 | S10: 70000000 | T10: 0 | U10: 0 | V10: 70000000 | W10: 70000000
A11: North | C11: CK | D11: 10CKNEW02 | E11: 10CK502801 | F11: Chixmax Aeon Mall Hà Đông | J11: FM1 | L11: 46021 | M11: 1840722637 | N11: 1840722637 | O11: 45722637 | P11: 1795000000 | Q11: 0 | R11: 0 | S11: 0 | T11: 0 | U11: 0 | V11: 1840722637 | W11: 1795000000 | Y11: 720 | Z11: 504 | AC11: FM1_Chixmax Aeon Mall Hà Đông.xlsx | AD11: New
A12: South | C12: KK | D12: 30KK4259 | E12: 30KK425901 | F12: Kichi Kichi VC Đồng Khởi Q1 | J12: FM1 | L12: 46031 | M12: 4363842161 | N12: 4363842161 | O12: 480574721 | P12: 0 | Q12: 0 | R12: 3883267440 | S12: 0 | T12: 0 | U12: 0 | V12: 4363842161 | W12: 3883267440 | AC12: FM1_KK VC ĐK (2) (1).xlsx
A13: South | C13: GG | D13: 30GGNEW38 | E13: 30GG503101 | F13: Gogi House Ninh Thuận | J13: FM1 | L13: 46034 | M13: 4588734394 | N13: 4588734394 | P13: 4588734394 | Q13: 0 | R13: 0 | S13: 0 | T13: 0 | U13: 0 | V13: 4588734394 | W13: 4588734394 | AC13: FM1 GGH NINH THUẬN.xlsx | AD13: New
A14: South | C14: GG | D14: 30GGNEW01 | E14: 30GG502601 | F14: Gogi House Garden Mall | I14: 1 phần MW Garden Mall | J14: FM1 | L14: 46034 | M14: 2707387500 | N14: 2707387500 | O14: 235387500 | P14: 0 | Q14: 2472000000 | R14: 0 | S14: 0 | T14: 0 | U14: 0 | V14: 2707387500 | W14: 2472000000 | Y14: 1138 | Z14: 500 | AC14: FM GOGI GARDEN MALL - review v2.xlsx | AD14: Convert
A15: South | C15: GG | D15: 30GGNOBUD11 | E15: 30GG502501 | F15: Gogi House Viettell | I15: 1 phần MW Viettel | J15: FM1 | L15: 46034 | M15: 2594142000 | N15: 2594142000 | O15: 230592000 | P15: 0 | Q15: 2363550000 | R15: 0 | S15: 0 | T15: 0 | U15: 0 | V15: 2594142000 | W15: 2363550000 | AC15: FM GOGI VIETTEL convert - review.xlsx
A16: North | C16: DN | D16: 10DN4929 | E16: 10DN492901 | F16: Dao Niu Guo Lê Đức Thọ | J16: FM1 | L16: 46041 | M16: 4348679976 | N16: 4348679976 | O16: 170300000 | P16: 0 | Q16: 0 | R16: 4138679976 | S16: 39700000 | T16: 0 | U16: 0 | V16: 4348679976 | W16: 4178379976 | AC16: FM Reno_DNG Lê Đức Thọ GĐ2-final.xlsx
A17: North | C17: DN | D17: 10DNNOBUD03 | E17: 10DN501601 | F17: Dao Niu Guo Trần Huy Liệu | I17: CD Trần Huy Liệu | J17: FM1 | L17: 46039 | M17: 3163939412 | N17: 3163939412 | O17: 389814457 | P17: 0 | Q17: 2593224955 | R17: 0 | S17: 180900000 | T17: 0 | U17: 0 | V17: 3163939412 | W17: 2774124955 | Y17: 1600 | Z17: 886 | AC17: FM convert_DNG Trần Huy Liệu 23.1.26_final.xlsx | AD17: Convert
A18: North | C18: DN | D18: 10DNNEW5 | E18: 10DN501501 | F18: Dao Niu Guo Mipec Long Biên | I18: VX Mipec Long Biên | J18: FM1 | M18: 6672409930 | N18: 6672409930 | O18: 148377635 | P18: 0 | Q18: 6524032295 | R18: 0 | S18: 0 | T18: 0 | U18: 0 | V18: 6672409930 | W18: 6524032295 | Y18: 2021 | Z18: 1253 | AC18: FM1_Convert_DNG Mipec LB_v1_final.xlsx | AD18: Convert
A19: North | C19: DN | D19: 10DNNOBUD04 | E19: 10DN501401 | F19: Dao Niu Guo Lê Thái Tổ | I19: MW Lê Thái Tổ | J19: FM1 | M19: 3028907743 | N19: 3028907743 | O19: 105532788 | P19: 0 | Q19: 2923374955 | R19: 0 | S19: 0 | T19: 0 | U19: 0 | V19: 3028907743 | W19: 2923374955 | AC19: FM1 convert_DNG Lê Thái Tổ_v2 final.xlsx | AD19: Convert
A20: North | C20: DN | D20: 10DNNEW2 | E20: 10DN501301 | F20: Dao Niu Guo Thái Hà | I20: MW Thái Hà | J20: FM1 | L20: 46099 | M20: 8096832336 | N20: 8096832336 | O20: 473075456 | P20: 0 | Q20: 7623756880 | R20: 0 | S20: 0 | T20: 0 | U20: 0 | V20: 8096832336 | W20: 7623756880 | AC20: FM1 convert_DNG Thái Hà_v1 final.xlsx | AD20: Convert
A21: South | C21: YT | D21: 30YTNOBUD01 | E21: 30YT498201 | F21: Yutang Lotte 84 Mậu Thân CTH | I21: HC Lotte Cần Thơ | J21: FM1 | L21: 46021 | M21: 1330500000 | N21: 1330500000 | O21: 356500000 | P21: 0 | Q21: 974000000 | R21: 0 | S21: 0 | T21: 0 | U21: 0 | V21: 1330500000 | W21: 974000000 | Y21: 479 | Z21: 374 | AC21: FM1_Yutang Cần Thơ.xlsx | AD21: Convert
A22: North | C22: LC | D22: 10LC4779 | E22: 10LC487901 | F22: Lách Ca Lách Cách Aeon Long Biên | J22: Vote Tổ 33 | N22: 54864820 | P22: 0 | Q22: 0 | R22: 0 | S22: 0 | T22: 0 | U22: 54864820 | V22: 54864820 | W22: 54864820
A23: South | C23: KK | D23: 30KK4268 | E23: 30KK426801 | F23: Kichi Kichi Aeon Mall Q.Tân Phú | J23: Vote Tổ 33 | N23: 29400000 | P23: 0 | Q23: 0 | R23: 0 | S23: 29400000 | T23: 0 | U23: 0 | V23: 29400000 | W23: 29400000
A24: South | C24: KK | D24: 30KK4260 | E24: 30KK426001 | F24: Kichi Kichi Phan Xích Long Q.Phú Nhuận | J24: Vote Tổ 33 | N24: 40900000 | P24: 0 | Q24: 0 | R24: 0 | S24: 40900000 | T24: 0 | U24: 0 | V24: 40900000 | W24: 40900000
A25: South | C25: KK | D25: 30KK4320 | E25: 30KK432001 | F25: Kichi Kichi Lê Thị Hà Hóc Môn | J25: Vote Tổ 33 | L25: 46029 | N25: 227023645 | P25: 0 | Q25: 0 | R25: 227023645 | S25: 0 | T25: 0 | U25: 0 | V25: 227023645 | W25: 227023645 | AC25: Không FM_Reno nhỏ_Cải tạo mặt tiền
A26: South | C26: KK | D26: 30KK4281 | E26: 30KK428101 | F26: Kichi Kichi Nguyễn Ảnh Thủ Hiệp Thành | J26: Vote Tổ 33 | L26: 46029 | N26: 432160120 | P26: 0 | Q26: 0 | R26: 432160120 | S26: 0 | T26: 0 | U26: 0 | V26: 432160120 | W26: 432160120 | AC26: Không FM_Reno nhỏ_Cải tạo mặt tiền
A27: South | C27: KK | D27: 30KK4314 | E27: 30KK431401 | F27: Kichi Kichi Nguyễn Văn Quá Q12 | J27: Vote Tổ 33 | L27: 46029 | N27: 294267720 | P27: 0 | Q27: 0 | R27: 294267720 | S27: 0 | T27: 0 | U27: 0 | V27: 294267720 | W27: 294267720 | AC27: Không FM_Reno nhỏ_Cải tạo mặt tiền
A28: South | C28: KK | D28: 30KK4276 | E28: 30KK427601 | F28: Kichi Kichi Nguyễn Hồng Đào Q.Tân Bình | J28: Vote Tổ 33 | L28: 46029 | N28: 550736200 | P28: 0 | Q28: 0 | R28: 550736200 | S28: 0 | T28: 0 | U28: 0 | V28: 550736200 | W28: 550736200 | AC28: Không FM_Reno nhỏ_Cải tạo mặt tiền
A29: South | C29: KK | D29: 30KK4315 | E29: 30KK431501 | F29: Kichi Kichi Tân Sơn Nhì Q.Tân Phú | J29: Vote Tổ 33 | L29: 46029 | N29: 420954204 | P29: 0 | Q29: 0 | R29: 420954204 | S29: 0 | T29: 0 | U29: 0 | V29: 420954204 | W29: 420954204 | AC29: Không FM_Reno nhỏ_Cải tạo mặt tiền
A30: South | C30: KK | D30: 30KK4261 | E30: 30KK426101 | F30: Kichi Kichi Nguyễn Trãi Q1 | J30: Vote Tổ 33 | L30: 46029 | N30: 323374300 | P30: 0 | Q30: 0 | R30: 323374300 | S30: 0 | T30: 0 | U30: 0 | V30: 323374300 | W30: 323374300 | AC30: Không FM_Reno nhỏ_Cải tạo mặt tiền
A31: South | C31: KK | D31: 30KK4294 | E31: 30KK429401 | F31: Kichi Kichi Phan Huy Ích Gò Vấp | J31: Vote Tổ 33 | L31: 46029 | N31: 337347067 | P31: 0 | Q31: 0 | R31: 337347067 | S31: 0 | T31: 0 | U31: 0 | V31: 337347067 | W31: 337347067 | AC31: Không FM_Reno nhỏ_Cải tạo mặt tiền
